Workbook

Sheet README
A1: Project A open-items LEDGER
A2: Written for | B2: You (the student, thesis owner). This is the single canonical place for the current state of Project A's open items. Date 2026-10-19; repository HEAD d791135.
A3: Status of this file | B3: Tracked working document (record class SUM, unverified) at design/ledger/, committed locally under AUTH-016; a read-only CSV export of the Ledger, Archive, Questions, Links, Aliases and Change log sits in design/ledger/export/ (derived; this workbook stays canonical). The human pushes; nothing is pushed by the lead. Contents: 258 unique rows (174 in Ledger, 84 already closed in Archive), 52 questions, 173 question-to-item links. Categories, clusters, order and dependencies are MY JUDGEMENT [I]; every status has a basis column. Work on it is covered by AUTH-016 (evidence only; see ops/AUTHORIZATIONS.md).
A4: USE THESE THREE TABS | B4: 1) Questions: type your answers in the yellow cells (column K). 2) Ledger: filter by Active? = Yes, sort by Order; rows flagged REVISE have a new answer waiting for me. 3) Overview: counts and integrity checks (all checks must be 0).
A5: How answering works | B5: You type an answer in Questions (column K), optionally pick Answer type, date and provenance (was it verbatim? from which message or file?). The Links sheet connects each question to the ledger items it CLOSES / NARROWS / INFORMS. Ledger columns 'Unanswered linked questions' and 'Review flag' update by formula, so the rows that need revising light up. You do not edit statuses yourself.
A6: How I revise (next session) | B6: For each answered question I (1) re-read the linked ledger rows, (2) set their Current status, Status date, Status basis, Decision/result, (3) append one row per change to the Change log, (4) mark the question REVIEWED with 'Resulting ledger changes', (5) move rows whose status is CLOSED to the Archive (delete from Ledger, same columns), and (6) add any new items the answer opens, with the next free ID. Partly answered rows stay in the Ledger with status PARTLY ANSWERED and a sharper description of the remainder.
A7: No-duplicates rules | B7: One row per item, ever. A LedgerID is never reused or renumbered; a merged item keeps its ID with status SUPERSEDED / MERGED and a pointer. Other names (SRC-06/07 OI rows, CH-, HYP-, REQ-, REGISTER Q) live in the Aliases sheet, not as extra rows. Before adding a row, search Aliases and Ledger titles. Overview checks count duplicate IDs, duplicate titles, IDs in both Ledger and Archive, orphan links and duplicate aliases.
A8: Statuses | B8: OPEN; PARTLY ANSWERED (a named clause is answered; the remainder is stated); UNRUN (a test with no result); NOT LOCATED (bounded search found nothing; not 'does not exist'); LIMITATION - ACCEPTANCE PENDING; DEFERRED (parked with a reopen trigger); ANSWER RECEIVED - TO REVISE; CLOSED - BY EVIDENCE; CLOSED - BY DECISION (needs the decision-maker's own words and date); CLOSED - CLAUSE (a narrow clause closed within its cited record); ACCEPTED LIMITATION (you accepted it); SUPERSEDED / MERGED; WITHDRAWN. Active? = Yes for open-type statuses, Parked for DEFERRED, No for closed-type.
A9: Repo-answerable? | B9: Answered (see basis): the repo already answers it. Yes - stored text, unread: the source text is stored in evidence/sources.json but nobody has read the decisive passage in this workspace, so closing it is a cheap local read via tools/origin_extract.py. Partly: some parts stored or read. No: not in the repo. n/a: a decision or a test.
A10: Closes by / Gate / Cluster | B10: Closes by = what kind of action closes the item (decision by Joaa, decision by you, record fix, desk analysis, source re-read, directed literature search, author/vendor, pilot test, confirmatory study, accept as limitation, time recheck, cross-reference). Gate = the earliest stage it must precede (G1 before ANY implementation ... G5 housekeeping). Cluster = items that one answer or one test moves together.
A11: Other tabs | B11: Archive (closed rows) | Change log (append-only history) | Links | Supervisor statements (Joaa's 19 Oct messages, verbatim) | Aliases | Steps (25-step order in 6 waves) | Clusters | Decision effects (what each possible answer changes) | Gates (what must be solved before implementation) | Dependencies (HARD/SOFT edges) | Sources (coverage register: what was and was not read) | External evidence (INT-01/02 claims relayed by SRC-12, unverified) | Rules (carried from SRC-11/12) | Lists (vocabularies for the dropdowns).
A12: Coverage | B12: See Sources. Everything in SRC-11 and SRC-12 is represented (55 canonical items, 64 sub-rows, 8 answered clauses, Phase 0-2 items, evidence table, rules). The repo sweep covered REGISTER, COMPARISON, CAVEATS, SAFEGUARDS, STATE, AUTH, all 14 hypotheses, all 74 challenge records (front matter; 24 open ones read), v4 in full, v2-05/06, v3-04 and parts of v1-v3. Areas NOT read are listed in Sources; append rows if a later sweep finds more.
A13: Honest limits | B13: Formulas could not be pre-computed here (no spreadsheet engine installed); Excel/LibreOffice/Google Sheets compute them on open, and some previewers show blanks. 'Order', 'Wave', 'Unlocks' and Dependencies categories are derived at build time and do not update if you edit prerequisites; counts, flags and integrity checks are live.
... A16: Where it lives; how it changes | B16: design/ledger/PROJECT_A_OPEN_ITEMS_LEDGER.xlsx is the single canonical copy. Edit it in place and never rebuild it from scripts (a rebuild would overwrite typed answers). Each batch of closures is one local commit that includes the workbook and the regenerated CSV export (design/ledger/export_ledger.py). Evidence rule (AUTH-016): repo evidence first; if the repo has none, public web searches and fetches for that item, stored with URL, time and SHA-256. Closing a decision needs the decision-maker's own words and date.

Sheet Questions
A1: QID | B1: Asked of | C1: Question (neutral wording; one issue each) | D1: Answer format / options | E1: Why it matters | F1: Also known as | G1: Ask at step | H1: Ledger items it CLOSES / NARROWS (snapshot; see Links) | I1: Items it only INFORMS (snapshot) | J1: Ledger items open because of it (formula) | K1: YOUR ANSWER (type here) | L1: Answer type | M1: Answer date | N1: Review status | O1: Provenance (verbatim? where from) | P1: Revised on / by | Q1: Resulting ledger changes
A2: Q-J01 | B2: Joaa | C2: Does the June 2026 expose still govern the thesis scope? If anything changed, which exact clauses are amended (compact interfaces L0-L3, execute/expand/abstain, lifecycle/removal, staged policy, evaluation)? | D2: Governs unchanged | Amended in these clauses: ... | Replaced by the October staged-policy framing | Other | E2: Decides which parts of Project A every test and design choice must cover; the repo cannot see the June text. | F2: SRC-12 1B 'Governing scope'; REGISTER G.3 Q1 (part) | G2: S05 | H2: C-D01 (closes), C-D07 (narrows) | I2: C-D03, C-D06, C-D08, N-13 | J2: =COUNTIFS(Links!$A$2:$A$600,A2,Links!$C$2:$C$600,"<>INFORMS") | K2: [Answered by the human] line 6: the expose does not govern; its ideas are candidates verified like any other. | L2: You decided | M2: 2026-10-21 | N2: REVIEWED | O2: INT-T-005 (requirements/intake/2026-10-21-user-decisions-after-meetings.md) | P2: 2026-10-21 / Claude | Q2: see the Change log of 2026-10-21
A3: Q-J02 | B3: Joaa | C3: Is the research question's unit 'count of tools' (your 14 Oct wording) or model-visible tokens / cost, and does 'we don't need to change it' keep the 'count of tools' wording? | D3: Count of tools | Tokens | Cost | Combination: ... | Other | E3: Changes the criterion and which surface is chosen; with thousands of tools the count cannot decide feasibility (tokens do). | F3: REGISTER G.3 Q1; v4-01 Q3 (first part) | G3: S06 | H3: C-D02 (narrows) | I3: N-1, N-13 | J3: =COUNTIFS(Links!$A$2:$A$600,A3,Links!$C$2:$C$600,"<>INFORMS") | K3: [Answered] 'your idea was never to filter out tools. your idea was to save tokens ... The problem was to save token' (INT-T-004 E524-E526); RQ wording kept with 'count of tools' (INT-T-003 L159); 'narrowing down from 100 to 10 ... reducing 90% of token' (L377). | L3: Joaa said | M3: 2026-10-02 / 10-14 / 10-21 (meetings) | N3: REVIEWED | O3: Transcript lines in INT-T-002/003/004 (AUTH-018); mapping checked by FND-0035, FND-0036 | P3: 2026-10-21 / Claude | Q3: see the Change log of 2026-10-21
A4: Q-J03 | B4: Joaa | C4: What should be primarily minimised or reported: model-visible input tokens, the billed cost (input, cache write, cache read and output tokens under a named price table), or a stated combination? Should output tokens count? | D4: Tokens | Bill | Both with priority ... | Other; Output tokens: count / report only / ignore | E4: Replaces the AUTH-006 working objective if it changes; fixes what pilots report as primary (they can record everything either way). | F4: WhatsApp 19 Oct; STATE pending (a); SRC-12 1B 'Research objective' | G4: S06 | H4: C-D02 (closes), N-1 (closes), N-4 (closes), C-D08/EC5 (narrows) | I4: N-10, C-D08/TOK, C-E05, C-S20 | J4: =COUNTIFS(Links!$A$2:$A$600,A4,Links!$C$2:$C$600,"<>INFORMS") | K4: [Answered by the human] line 8 and line 16: minimise the bill on average over turns and sessions, accuracy nearly the same; canonical equation of components. | Earlier from the meetings: [Partly] Money cost per turn, tokens and response time averaged over turns (INT-T-002 L275, L302, L354); 'we will not drop the cost' (INT-T-004 E697). No single primary estimand or price table named. | L4: You decided | M4: 2026-10-21 | N4: REVIEWED | O4: INT-T-005 (requirements/intake/2026-10-21-user-decisions-after-meetings.md) | P4: 2026-10-21 / Claude | Q4: see the Change log of 2026-10-21
A5: Q-J04 | B5: Joaa | C5: Over what horizon should cost be measured: one run, several turns within a conversation, or across sessions? Is cache expiry between sessions in scope? | D5: One run | Several turns | Across sessions (with session gap assumptions ...) | Cache expiry in/out of scope | E5: Across sessions adds session count and gap as regime variables and needs a session vehicle. | F5: WhatsApp 19 Oct; STATE pending (a) | G5: S06 | H5: N-3 (closes), C-D02 (narrows), C-D08/EC1 (narrows) | I5: C-S04, N-12 | J5: =COUNTIFS(Links!$A$2:$A$600,A5,Links!$C$2:$C$600,"<>INFORMS") | K5: [Answered] Average over many turns, a few failing turns may cost more (INT-T-002 L306-L320); a return 'tomorrow' should start from a short summary (L369-L384); 'save token for a number of turns' (INT-T-004 E778). | L5: Joaa said | M5: 2026-10-02 / 10-14 / 10-21 (meetings) | N5: REVIEWED | O5: Transcript lines in INT-T-002/003/004 (AUTH-018); mapping checked by FND-0035, FND-0036 | P5: 2026-10-21 / Claude | Q5: see the Change log of 2026-10-21
A6: Q-J05 | B6: Joaa | C6: Memory scope: only our stored record of tools previously found and used (per user or role, so a returning user starts with those tools), or also storage/summarisation of conversation history, or full agent memory? | D6: Tool-usage memory only | Plus conversation memory | Full agent memory | Other | E6: Decides whether cross-session discovery memory (N-6, N-7) is in the thesis, deferred, or enlarged. | F6: STATE pending (b); WhatsApp 19 Oct | G6: S06 | H6: N-2 (closes), N-6 (narrows), N-7 (narrows), C-D07 (narrows), N-22 (narrows) | I6: N-3 | J6: =COUNTIFS(Links!$A$2:$A$600,A6,Links!$C$2:$C$600,"<>INFORMS") | K6: [Answered] 'it depends on what you are building' (INT-T-002 L146); 'you can do only memory and tool calls. Forget about knowledge ... memory should help tool calls' (L223-L225); summary of interaction and tool calls, relevant part first (L245, L375-L384); 'tools and memory' (L390). | L6: Joaa said | M6: 2026-10-02 / 10-14 / 10-21 (meetings) | N6: REVIEWED | O6: Transcript lines in INT-T-002/003/004 (AUTH-018); mapping checked by FND-0035, FND-0036 | P6: 2026-10-21 / Claude | Q6: see the Change log of 2026-10-21
A7: Q-J06 | B7: Joaa | C7: Joaa wrote: 'So you have to combine all three to find the best policy: MCP server context, memory, explicit caching.' How should the combination be treated in this thesis: all three as the design space, a subset, or later work? | D7: All three | A subset: ... | Later work | Other | E7: The combination has not been evaluated in the repo's sources yet; whether it is the design space is a scope choice, and the proposal can be adopted, refined or narrowed. | F7: Joaa 19 Oct 12:22 (S-J-004) | G7: S06 | H7: N-22 (closes), C-D07 (narrows), C-D08/ARMS-CACHE (narrows) | I7: N-2 | J7: =COUNTIFS(Links!$A$2:$A$600,A7,Links!$C$2:$C$600,"<>INFORMS") | K7: [Partly] Explicit cache 'applicable for memory ... knowledge' (INT-T-002 L197) in the 'all in theory' part (L221); practical scope tools and memory only (L223-L225). | L7: Joaa said | M7: 2026-10-02 / 10-14 / 10-21 (meetings) | N7: NEEDS FOLLOW-UP | O7: Transcript lines in INT-T-002/003/004 (AUTH-018); mapping checked by FND-0035, FND-0036 | P7: 2026-10-21 / Claude | Q7: see the Change log of 2026-10-21
A8: Q-J07 | B8: Joaa | C8: Must each stage (step) save tokens, or is it enough that the whole trajectory/policy does? Does the possibility of re-adding a tool change your answer? | D8: Per stage | Per trajectory | Per policy over many requests | Other | E8: Decides how 'a stage pays' is tested and whether insurance/recovery stages are allowed. | F8: REGISTER G.3 Q4; SRC-12 1B | G8: S07 | H8: C-D04 (closes) | I8: C-D08/ARMS | J8: =COUNTIFS(Links!$A$2:$A$600,A8,Links!$C$2:$C$600,"<>INFORMS") | K8: [Answered] 'each step is there to save some token' (INT-T-004 E774); saving judged over a number of turns, one dearer turn 'doesn't matter' (E778-E790). | L8: Joaa said | M8: 2026-10-02 / 10-14 / 10-21 (meetings) | N8: REVIEWED | O8: Transcript lines in INT-T-002/003/004 (AUTH-018); mapping checked by FND-0035, FND-0036 | P8: 2026-10-21 / Claude | Q8: see the Change log of 2026-10-21
A9: Q-J08 | B9: Joaa | C9: Is the staged 'one question per step' graph a binding form of the policy, or an illustration? Is a policy whose stages appear only where a stated test justifies them (including zero narrowing stages) acceptable? | D9: Binding | Illustration; stages only where justified | Other | E9: If binding, the graph must contain real narrowing stages even if the study finds none pays. | F9: REGISTER G.3 Q2; v4-01 Q1; SRC-12 1B 'Policy form' | G9: S07 | H9: C-D03 (closes) | I9: C-D10, C-S11, C-S11/CASCADE, C-D06 | J9: =COUNTIFS(Links!$A$2:$A$600,A9,Links!$C$2:$C$600,"<>INFORMS") | K9: [Answered by the supervisor's words and the human's decision] Supervisor 14 Oct: staged graph with re-adding (INT-T-003 L386-L404); the human: keep it and combine it with memory-informed tool offering (INT-T-005 line 5). | Earlier: [Partly] 14 Oct: a staged graph with re-adding, 'that is your novelty' (INT-T-003 L386-L404); 21 Oct: scope memory and tool calls, graph not mentioned (INT-T-002 L223-L225). | L9: You decided | M9: 2026-10-21 | N9: REVIEWED | O9: INT-T-005 (requirements/intake/2026-10-21-user-decisions-after-meetings.md); INT-T-002/003/004 | P9: 2026-10-21 / Claude | Q9: see the Change log of 2026-10-21
A10: Q-J09 | B10: Joaa | C10: What do 'context' and 'scenario' mean: the individual request, the trajectory so far, or the deployment? | D10: Request | Trajectory | Deployment | Combination | Other | E10: v4 adapts at deployment level and via the request/trajectory only through optional stages. | F10: v4-01 Q2; REQ-O14-09 | G10: S07 | H10: C-D03/CONTEXT (closes), C-D03 (narrows) | J10: =COUNTIFS(Links!$A$2:$A$600,A10,Links!$C$2:$C$600,"<>INFORMS") | K10: [Partly] 14 Oct: who invokes the agent (INT-T-003 L261); 21 Oct: what the model is given, tools, knowledge, memory, settings, modalities (INT-T-002 L176-L190). | L10: Joaa said | M10: 2026-10-02 / 10-14 / 10-21 (meetings) | N10: NEEDS FOLLOW-UP | O10: Transcript lines in INT-T-002/003/004 (AUTH-018); mapping checked by FND-0035, FND-0036 | P10: 2026-10-21 / Claude | Q10: see the Change log of 2026-10-21
A11: Q-J10 | B11: Joaa | C11: What does 'which one applies at which stage' mean: what are the 'stages' (policy stages or evaluation stages) and what is 'which one'? What does 'time' mean in 'which one works at which time'? | D11: Free text | E11: Undefined antecedents in the excerpts E4 and E6. | F11: REQ-O14-11; REQ-O14-06 | G11: S07 | H11: C-D03/STAGES (closes) | J11: =COUNTIFS(Links!$A$2:$A$600,A11,Links!$C$2:$C$600,"<>INFORMS") | K11: [Answered] 'which one applies at which stage. You will have different stages' (INT-T-003 L306-L308); 'At each step you have to ask yourself one question' (L390). | L11: Joaa said | M11: 2026-10-02 / 10-14 / 10-21 (meetings) | N11: REVIEWED | O11: Transcript lines in INT-T-002/003/004 (AUTH-018); mapping checked by FND-0035, FND-0036 | P11: 2026-10-21 / Claude | Q11: see the Change log of 2026-10-21
A12: Q-J11 | B12: Joaa | C12: Who or what should answer each stage's question: the model, a rule, or a score? | D12: Model | Rule | Score | Empirical question (test both) | Other | E12: v4 leaves it empirical; a restriction changes the arms. | F12: COMPARISON section 4 | G12: S07 | H12: C-D03/ANSWERER (closes) | I12: C-S11 | J12: =COUNTIFS(Links!$A$2:$A$600,A12,Links!$C$2:$C$600,"<>INFORMS") | K12: [Partly] Stage one from who invokes (INT-T-003 L261); later stage Executor-style or semantic narrowing, 'You have to figure it out' (L306-L308). | L12: Joaa said | M12: 2026-10-02 / 10-14 / 10-21 (meetings) | N12: NEEDS FOLLOW-UP | O12: Transcript lines in INT-T-002/003/004 (AUTH-018); mapping checked by FND-0035, FND-0036 | P12: 2026-10-21 / Claude | Q12: see the Change log of 2026-10-21
A13: Q-J12 | B13: Joaa | C13: Is graded/partial exposure (names only, compact schema, full schema) still a required lens, as in the June L0-L3 and the 2 Oct tier example? | D13: Required | Optional | Dropped | E13: The 14 Oct excerpts describe keep/remove and re-adding, not grades. | F13: COMPARISON C5; REQ-D1 R9 | G13: S05 | H13: C-D07/GRADED (closes), C-D07 (narrows), C-D08/EC3 (narrows) | J13: =COUNTIFS(Links!$A$2:$A$600,A13,Links!$C$2:$C$600,"<>INFORMS") | K13: [Answered by the supervisor's words and the human's decision] Supervisor 2 Oct: one lens, not the best way (INT-T-004 E550-E570); the human: treat such ideas as candidates (INT-T-005 lines 1, 6). | Earlier: [Partly] Partial information as 'this lens', 'not saying this is the best way', numbers 'not rigid' (INT-T-004 E550-E570, E774). | L13: You decided | M13: 2026-10-21 | N13: REVIEWED | O13: INT-T-005 (requirements/intake/2026-10-21-user-decisions-after-meetings.md); INT-T-002/003/004 | P13: 2026-10-21 / Claude | Q13: see the Change log of 2026-10-21
A14: Q-J13 | B14: Joaa | C14: Beyond the point where all tools cannot fit in the context window, is a frontier plus a gap to a pool reference (no noninferiority to expose-all) acceptable? Who sets the margin or token budget from which a policy is chosen? | D14: Acceptable; margin/budget set by ... | Not acceptable; require ... | Other | E14: Without it no claim above n_fit can be made against expose-all. | F14: v4-01 Q4; SRC-12 1B | G14: S08 | H14: C-E06 (closes), C-S13 (narrows), C-S13/CALIB (narrows), C-D08/DELTA (narrows) | I14: C-S13/POOLDIR | J14: =COUNTIFS(Links!$A$2:$A$600,A14,Links!$C$2:$C$600,"<>INFORMS") | K14: [Answered by the human] line 16 (no margin or budget): above the window the frontier is reported. | L14: You decided | M14: 2026-10-21 | N14: REVIEWED | O14: INT-T-005 (requirements/intake/2026-10-21-user-decisions-after-meetings.md) | P14: 2026-10-21 / Claude | Q14: see the Change log of 2026-10-21
A15: Q-J14 | B15: Joaa | C15: Does 'accuracy as high as possible' mean a margin (what size, per stratum?) or a frontier? May the tool count be a reported variable while tokens are the criterion? | D15: Margin of ... | Frontier | Other; Count: reported / criterion | E15: Fixes delta and whether noninferiority testing is used at all. | F15: v4-01 Q3 | G15: S08 | H15: C-D08/DELTA (closes), C-D08/STRATA (narrows), C-D02 (narrows), C-S14 (narrows) | J15: =COUNTIFS(Links!$A$2:$A$600,A15,Links!$C$2:$C$600,"<>INFORMS") | K15: [Answered by the human] line 16: no margin, no budget, no hard thresholds; accuracy nearly the same. | Earlier from the meetings: [Partly] 'match the baseline accuracy while giving lesser and lesser tool' (INT-T-004 E206); 'accuracy as high as possible' (INT-T-003 L159); no margin. | L15: You decided | M15: 2026-10-21 | N15: REVIEWED | O15: INT-T-005 (requirements/intake/2026-10-21-user-decisions-after-meetings.md) | P15: 2026-10-21 / Claude | Q15: see the Change log of 2026-10-21
A16: Q-J15 | B16: Joaa | C16: Would regime-conditional findings (including 'not established' and negative outcomes) count as the findings you require? Is a regime map a sufficient contribution? | D16: Yes | No | Only if ... | Other | E16: Decides whether a null/conditional result is a thesis; also whether a big study is worthwhile. | F16: v4-01 Q5; SRC-12 1B 'Contribution and success' | G16: S08 | H16: C-D06 (closes) | J16: =COUNTIFS(Links!$A$2:$A$600,A16,Links!$C$2:$C$600,"<>INFORMS") | K16: [Answered] 'even if the result is negative it's a thesis ... can you write a paper ... have to do it systematically' (INT-T-003 L363-L365). | L16: Joaa said | M16: 2026-10-02 / 10-14 / 10-21 (meetings) | N16: REVIEWED | O16: Transcript lines in INT-T-002/003/004 (AUTH-018); mapping checked by FND-0035, FND-0036 | P16: 2026-10-21 / Claude | Q16: see the Change log of 2026-10-21
A17: Q-J16 | B17: Joaa | C17: Must the existing code-mediated project ('Executor') be a baseline arm, and which tool or project did you mean by that name? | D17: Required arm | Optional | Not an arm | Identity: ... | E17: The identification of 'Executor' is the researchers', not in the transcript lines. | F17: v4-01 Q6 (first part); CAVEATS 6; A7 | G17: S08 | H17: C-D08/GATEWAY (closes), C-D08/EXEC (narrows), C-D08 (narrows) | I17: AS-07 | J17: =COUNTIFS(Links!$A$2:$A$600,A17,Links!$C$2:$C$600,"<>INFORMS") | K17: [Answered] Executor: 'download this run this ... benchmark it ... This is your baseline. You should have multiple baselines' (INT-T-004 E622-E626); identity: the startup he shared (E583-E612). | L17: Joaa said | M17: 2026-10-02 / 10-14 / 10-21 (meetings) | N17: REVIEWED | O17: Transcript lines in INT-T-002/003/004 (AUTH-018); mapping checked by FND-0035, FND-0036 | P17: 2026-10-21 / Claude | Q17: see the Change log of 2026-10-21
A18: Q-J17 | B18: Joaa | C18: Is writing the evaluation script part of the 21 Oct deliverable, and what does 'implement' cover (script, pilots, experiments)? | D18: Script due | Policy only | Script allowed but no runs | Other | E18: Hard gate before any implementation. | F18: REGISTER G.3 Q5; v4-01 Q6 (second part) | G18: S05 | H18: C-D05 (closes) | I18: C-D09 | J18: =COUNTIFS(Links!$A$2:$A$600,A18,Links!$C$2:$C$600,"<>INFORMS") | K18: [Answered] For 21 Oct: no implementation (INT-T-003 L439); after 21 Oct: experiments with a text-file memory, no engineering, many goals, settings, repeated runs (INT-T-002 L426-L458). | L18: Joaa said | M18: 2026-10-02 / 10-14 / 10-21 (meetings) | N18: REVIEWED | O18: Transcript lines in INT-T-002/003/004 (AUTH-018); mapping checked by FND-0035, FND-0036 | P18: 2026-10-21 / Claude | Q18: see the Change log of 2026-10-21
A19: Q-J18 | B19: Joaa | C19: Does the 21 Oct deliverable replace the 2 Oct one? Was the 2 Oct deliverable (document plus draft step-by-step policy) delivered? | D19: Replaces | Adds to | Other; Delivered: yes/no | E19: Not known to the repo. | F19: REGISTER G.3 Q6; SRC-12 1A-3 | G19: S05 | H19: C-D05 (narrows) | J19: =COUNTIFS(Links!$A$2:$A$600,A19,Links!$C$2:$C$600,"<>INFORMS") | K19: [Answered by the human] line 7: research and a drafted policy now; proof-of-concept tests of parts in a loop; end-to-end later. | Earlier from the meetings: [Partly] 2 Oct: 'write the draft version of uh your policy' (INT-T-004 E804); 14 Oct: 'You need to give me this policy' (INT-T-003 L429-L447). Delivery of the 2 Oct draft not stated. | L19: You decided | M19: 2026-10-21 | N19: REVIEWED | O19: INT-T-005 (requirements/intake/2026-10-21-user-decisions-after-meetings.md) | P19: 2026-10-21 / Claude | Q19: see the Change log of 2026-10-21
A20: Q-J19 | B20: Joaa | C20: Should the offline cost of choosing the configuration (development runs, amortised over a deployment horizon N_dep) be charged to the policy, and over what horizon? | D20: Charged over N = ... | Reported only | Not counted | E20: Part of the accounting contract. | F20: SRC-06 S35 | G20: S08 | H20: C-S17 (closes), C-S20 (narrows) | I20: C-D08/EPS | J20: =COUNTIFS(Links!$A$2:$A$600,A20,Links!$C$2:$C$600,"<>INFORMS") | K20: [Answered by the human] line 10 (see Q-J03): selection and discovery cost is part of the averaged bill. | Earlier from the meetings: [Partly] 'if you use many many more token to filter out the tools then there is no value' (INT-T-004 E230-E232); amortisation not discussed. | L20: You decided | M20: 2026-10-21 | N20: REVIEWED | O20: INT-T-005 (requirements/intake/2026-10-21-user-decisions-after-meetings.md) | P20: 2026-10-21 / Claude | Q20: see the Change log of 2026-10-21
A21: Q-J20 | B21: Joaa | C21: Which numeric parameters do you want fixed now (margin, alpha, strata, epsilon, search width, discovery budget) and which may be set after a pilot? | D21: List: now / after pilot | E21: A parameter can be deferred to a documented pilot only if it cannot change the pilot's interpretation. | F21: SRC-12 Phase 2 | G21: S08 | H21: C-D08 (narrows) | I21: C-D08/ALPHA, C-D08/STRATA, C-D08/EPS, C-D08/KAPPA, C-D08/BS, C-S14, C-D08/CALLLIM, C-D08/EC2, C-D08/EC4, C-D08/EC6, C-D08/HIER, C-D08/RANKER, C-D08/SCOPESTMT | J21: =COUNTIFS(Links!$A$2:$A$600,A21,Links!$C$2:$C$600,"<>INFORMS") | K21: [Answered by the supervisor's words and the human's decision] The human: no margin, budget or threshold (line 16); error control and strata in the end-to-end phase (line 7); kappa, discovery budget and call limit are set while drafting and testing the policy, not by the supervisor. | Earlier: [Partly] Tier sizes 'not rigid' (INT-T-004 E552-E560); start with about 20 samples (E749); delta, epsilon, N_dep not addressed. | L21: You decided | M21: 2026-10-21 | N21: REVIEWED | O21: INT-T-005 (requirements/intake/2026-10-21-user-decisions-after-meetings.md); INT-T-002/003/004 | P21: 2026-10-21 / Claude | Q21: see the Change log of 2026-10-21
A22: Q-J21 | B22: Joaa | C22: How many models or model families should evaluations cover (you said behaviour does not transfer across models)? | D22: N models; families: ... | E22: Drives cost and the sample plan. | F22: REQ-A1 A12 | G22: S08 | H22: AS-12 (narrows), C-D08/EC1 (narrows) | I22: C-D08/CORESWEEP | J22: =COUNTIFS(Links!$A$2:$A$600,A22,Links!$C$2:$C$600,"<>INFORMS") | K22: [Answered by the supervisor's words and the human's decision] The human: models chosen when implementing, several available through a free university API (line 9; REQ-U21-01); the supervisor: repeated runs and several settings (INT-T-002 L441-L443). | Earlier: [Partly] Multiple goals, settings, repeated runs (INT-T-002 L441-L443); number of models not given. | L22: You decided | M22: 2026-10-21 | N22: REVIEWED | O22: INT-T-005 (requirements/intake/2026-10-21-user-decisions-after-meetings.md); INT-T-002/003/004 | P22: 2026-10-21 / Claude | Q22: see the Change log of 2026-10-21
A23: Q-J22 | B23: Joaa | C23: Do you want a prior-art / novelty check of the staged graph (you said 'that is your novelty'), or is novelty not a thesis requirement? | D23: Check required | Not required | Other | E23: v4 makes no novelty claim; every mechanism exists. | F23: REQ-O14-07, -16 | G23: S08 | H23: C-D06/NOVELTY (closes) | J23: =COUNTIFS(Links!$A$2:$A$600,A23,Links!$C$2:$C$600,"<>INFORMS") | K23: [Answered by the supervisor's words and the human's decision] Supervisor: the novelty is the systematic combination and its findings, 'sell it as a novely' (INT-T-003 L227-L233), with a monthly search not to reinvent the wheel (INT-T-004 E591-E605); the human: success is the quality of the work (line 16) and no re-invention (line 1). No separate novelty assessment. | Earlier: [Partly] 'nothing is noble [novel] ... that is actually the novelty. You have to just sell it as a novely' (INT-T-003 L227-L233); monthly search not to reinvent the wheel (INT-T-004 E591-E605). | L23: You decided | M23: 2026-10-21 | N23: REVIEWED | O23: INT-T-005 (requirements/intake/2026-10-21-user-decisions-after-meetings.md); INT-T-002/003/004 | P23: 2026-10-21 / Claude | Q23: see the Change log of 2026-10-21
A24: Q-J23 | B24: Joaa | C24: What did you mean by 'What you have found and narrowed down is some methodologies' (whose findings)? | D24: Free text | E24: Undefined referent in excerpt E1; low priority. | F24: REQ-O14-02 | G24: S05 | H24: C-D01/REFERENT (closes) | J24: =COUNTIFS(Links!$A$2:$A$600,A24,Links!$C$2:$C$600,"<>INFORMS") | K24: [Answered] 'What you have found and narrowed down is some methodologies ... So, we have some mechanism families' (INT-T-003 L159-L161). | L24: Joaa said | M24: 2026-10-02 / 10-14 / 10-21 (meetings) | N24: REVIEWED | O24: Transcript lines in INT-T-002/003/004 (AUTH-018); mapping checked by FND-0035, FND-0036 | P24: 2026-10-21 / Claude | Q24: see the Change log of 2026-10-21
A25: Q-J24 | B25: Joaa | C25: Which providers and models should the bill/cache analysis cover (to choose the price tables)? | D25: Provider/model list | E25: Prices and cache rules are provider-specific. | F25: SRC-12 Phase 2 | G25: S06 | H25: C-D08/EC1 (narrows) | I25: N-5, C-E05, N-1 | J25: =COUNTIFS(Links!$A$2:$A$600,A25,Links!$C$2:$C$600,"<>INFORMS") | K25: [Answered by the human] line 9: chosen when implementing. | L25: You decided | M25: 2026-10-21 | N25: REVIEWED | O25: INT-T-005 (requirements/intake/2026-10-21-user-decisions-after-meetings.md) | P25: 2026-10-21 / Claude | Q25: see the Change log of 2026-10-21
A26: Q-U01 | B26: You | C26: Which dated copy of the June expose did you give Joaa, and what record shows he accepted it (file, email, message, date; or the words and date you recall)? | D26: File/date | Words recalled: ... | None | E26: Your account is not independently recorded. | F26: SRC-12 1A-1 | G26: S01 | H26: C-D01 (narrows) | I26: N-13 | J26: =COUNTIFS(Links!$A$2:$A$600,A26,Links!$C$2:$C$600,"<>INFORMS")
A27: Q-U02 | B27: You | C27: What newer Project A work, results or meeting records exist after 3 October (exact files, logs, dates)? | D27: List of files/dates | None | E27: Avoids duplicate runs; may narrow test items. | F27: SRC-12 1A-2 | G27: S02 | H27: C-D11 (narrows), N-11 (narrows) | J27: =COUNTIFS(Links!$A$2:$A$600,A27,Links!$C$2:$C$600,"<>INFORMS")
A28: Q-U03 | B28: You | C28: May earlier Project A results be reconciled with this workspace, and under which authorization? Or confirm none exist. | D28: Yes, supply and authorize | No | None exist | E28: Reconciliation is out of scope until you authorize it; one answer may narrow many test items. | F28: SRC-12 Phase 0 | G28: S02 | H28: C-D11 (closes), C-P03 (narrows), C-P03/P11 (narrows) | I28: C-S01, C-S02, C-S08, C-S12, C-S13, C-S15, C-S16 | J28: =COUNTIFS(Links!$A$2:$A$600,A28,Links!$C$2:$C$600,"<>INFORMS") | K28: 'also the 27 retreival methods keep it but take care where you use it ... never let it contaminate our work' (human, 2026-10-21, ops/AUTHORIZATIONS.md AUTH-018 section). | L28: You decided | M28: 2026-10-21 | N28: REVIEWED | O28: verbatim, chat 2026-10-21 | P28: 2026-10-21 / Claude | Q28: C-D11 closed by decision; N-11 deferred
A29: Q-U04 | B29: You | C29: What is the status of the Executor 426-slot comparison after 3 October (ran, results, or not run)? | D29: Status/records | Not run | E29: INT-01 shows it had not started at its 3 Oct snapshot. | F29: SRC-12 Phase 0 step 2 | G29: S02 | H29: N-11 (closes) | J29: =COUNTIFS(Links!$A$2:$A$600,A29,Links!$C$2:$C$600,"<>INFORMS")
A30: Q-U05 | B30: You | C30: Was the 2 Oct deliverable provided? What exactly, when, and how (sent file or email)? | D30: Delivered: file/date | Not delivered | E30: REGISTER Q6 cannot be settled without it. | F30: SRC-12 1A-3 | G30: S05 | H30: C-D05 (narrows) | J30: =COUNTIFS(Links!$A$2:$A$600,A30,Links!$C$2:$C$600,"<>INFORMS")
A31: Q-U06 | B31: You | C31: Which decisions do you want Joaa to make, and which are your own operational choices (budget, models, scope)? Keep preferences separate from agreed constraints. | D31: Two lists | E31: Prevents asking Joaa things only you can decide. | F31: SRC-12 1A-4 | G31: S04 | I31: C-D08, C-D09 | J31: =COUNTIFS(Links!$A$2:$A$600,A31,Links!$C$2:$C$600,"<>INFORMS")
A32: Q-U07 | B32: You | C32: What exactly did you send Joaa as 'V3' (files, date), and what was the intermediate presentation? | D32: File names/date | E32: Joaa's 19 Oct feedback is on what he saw; v4 corrections postdate it. | F32: WD-021 | G32: S01 | H32: N-8 (closes) | J32: =COUNTIFS(Links!$A$2:$A$600,A32,Links!$C$2:$C$600,"<>INFORMS")
A33: Q-U08 | B33: You | C33: Paste Joaa's 19 Oct message verbatim, including the 'one tenth' and any 'for an hour' wording. | D33: Paste | E33: The repo holds only a paraphrase. | F33: WhatsApp 19 Oct | G33: S01 | H33: N-9 (closes) | I33: N-5 | J33: =COUNTIFS(Links!$A$2:$A$600,A33,Links!$C$2:$C$600,"<>INFORMS") | K33: Pasted in chat on 2026-10-19; stored verbatim in the 'Supervisor statements' sheet (S-J-001..006), including the '1/10' and 'for an hour' wording. | L33: Document provided | M33: 2026-10-19 | N33: REVIEWED | O33: Forwarded by the student; verbatim copy in the 'Supervisor statements' sheet. | P33: 2026-10-19 / Claude | Q33: N-9 PARTLY ANSWERED (workbook copy; tracked copy pending); N-5 PARTLY ANSWERED; N-22 retitled; new N-25, N-26, N-27; Q-J06 reworded; Q-J25..J27 added
A34: Q-U09 | B34: You | C34: Supply the thesis research question verbatim (who stated it, when), or confirm none is established yet. | D34: Verbatim text | None yet | E34: THESIS_QUESTION.md is a placeholder; E1 is a fragment. | F34: REGISTER G.3 Q3 | G34: S01 | H34: N-13 (closes), C-D01 (narrows) | J34: =COUNTIFS(Links!$A$2:$A$600,A34,Links!$C$2:$C$600,"<>INFORMS")
A35: Q-U10 | B35: You | C35: Confirm or reverse the two-figure presentation (run-time policy vs study protocol), and decide what Joaa is shown. | D35: Confirm | Reverse | Show both | E35: The lead decided it under AUTH-010. | F35: WD-020 | G35: S07 | H35: C-D10 (closes), C-R02 (narrows), C-R02/C10-13 (narrows) | J35: =COUNTIFS(Links!$A$2:$A$600,A35,Links!$C$2:$C$600,"<>INFORMS")
A36: Q-U11 | B36: You | C36: Accept the documented safeguard limits, or authorize fixes; may the stale safeguard text (SAFEGUARDS rows 5 and 17, CLAUDE.md) be updated for your review? | D36: Accept | Fix: ... | Update text | E36: Hard gate before running code here. | F36: STATE open item 7 | G36: S03 | H36: C-D13 (closes), C-D13/HOOKOFF (narrows), C-D13/INTERP (narrows), C-D13/BASHWRITE (narrows), C-D13/INTERACTIVE (narrows), C-D13/PEERS (narrows), C-D13/LEADREG (narrows), C-D13/UNTESTED (narrows), C-D13/WEBTOOLS (narrows), C-D13/TEAMS (narrows), N-19 (narrows) | J36: =COUNTIFS(Links!$A$2:$A$600,A36,Links!$C$2:$C$600,"<>INFORMS") | K36: I accept all 8 in A, (the eight C-D13 limits listed in the lead's table). The second part of this question (whether the stale safeguard text may be updated for your review) is not answered. | L36: You decided | M36: 2026-10-20 | N36: NEEDS FOLLOW-UP | O36: Verbatim, the human's chat message of 2026-10-20 (reply to the lead's list of 17 limitations) | P36: 2026-10-20 / Claude | Q36: 8 limits accepted and archived; C-D13 narrowed; N-19 pinned-text part still waits
A37: Q-U12 | B37: You | C37: Keep or remove design/tool-exposure-policy-proposal.md and EXT-0067..0073 (author unknown)? | D37: Keep | Remove | E37: Provenance of the file is unrecorded. | F37: STATE open item 6 | G37: S03 | H37: N-15 (closes) | J37: =COUNTIFS(Links!$A$2:$A$600,A37,Links!$C$2:$C$600,"<>INFORMS")
A38: Q-U13 | B38: You | C38: Should the Phase 1/2/2b independent results inform the 21 Oct meeting (needs a new AUTH)? | D38: Yes (AUTH) | No | E38: The lead cannot read them. | F38: STATE open item 4 | G38: S02 | H38: N-14 (closes) | I38: C-D12 | J38: =COUNTIFS(Links!$A$2:$A$600,A38,Links!$C$2:$C$600,"<>INFORMS")
A39: Q-U14 | B39: You | C39: Which pilots do you authorize (token composition, billing/cache probe, search initiation, ...), on which provider and model, with what budget cap and whose approval? | D39: List with budgets | None yet | E39: Nothing may run without an AUTH row. | F39: STATE open item 5 | G39: S16 | H39: C-D09 (closes) | J39: =COUNTIFS(Links!$A$2:$A$600,A39,Links!$C$2:$C$600,"<>INFORMS")
A40: Q-U15 | B40: You | C40: Do you want a further independent replication track? | D40: Yes | No | Later | E40: Separate from this audit. | F40: SRC-06 D15 | G40: S25 | H40: C-D12 (closes) | J40: =COUNTIFS(Links!$A$2:$A$600,A40,Links!$C$2:$C$600,"<>INFORMS")
A41: Q-U16 | B41: You | C41: Add or decline the dated near-miss-source note. | D41: Add | Decline | E41: Optional provenance housekeeping. | F41: SRC-06 D17 | G41: S25 | H41: C-D14 (closes) | J41: =COUNTIFS(Links!$A$2:$A$600,A41,Links!$C$2:$C$600,"<>INFORMS")
A42: Q-U17 | B42: You | C42: Keep, move or remove the two copied thesis workspaces in the parent tree and the aborted-launch records? | D42: Keep | Move | Remove | E42: Moving cannot create independence retroactively. | F42: SRC-06 P01-P02 | G42: S25 | H42: C-P01 (closes), C-P01/P01 (closes), C-P01/P02 (closes) | J42: =COUNTIFS(Links!$A$2:$A$600,A42,Links!$C$2:$C$600,"<>INFORMS")
A43: Q-U18 | B43: You | C43: Record this review and ledger under an AUTH row and move them into tracked docs (when)? May SRC-11 and SRC-12 be admitted as inputs (intake route A)? | D43: Yes: now/after 21 Oct | No | E43: The workspace is untracked and not in the remote backup; scope is only granted in the AUTH register. | F43: review section 9 | G43: S03 | H43: N-23 (closes) | J43: =COUNTIFS(Links!$A$2:$A$600,A43,Links!$C$2:$C$600,"<>INFORMS") | K43: Ledger: yes, now, at design/ledger/ (workbook only in the first commit; text export yes). Review report and SRC-11/12: not in the first commit. AUTH row: AUTH-016 recorded. | L43: You decided | M43: 2026-10-19 | N43: REVIEWED | O43: Student's answers to the lead's four questions, 2026-10-19 (quoted in ops/AUTHORIZATIONS.md AUTH-016). | P43: 2026-10-19 / Claude | Q43: N-23 PARTLY ANSWERED (ledger tracked under AUTH-016; review and SRC-11/12 still untracked, admission undecided).
A44: Q-U19 | B44: You | C44: Locate in the SRC-05 transcript the lines where Joaa says a sound negative result can still be a thesis (timestamps and words), or confirm he did not. | D44: Quote with timestamp | Not found | E44: SRC-11 reports it; the repo's excerpts do not contain it. | F44: review section 6.2 | G44: S01 | H44: N-20 (closes) | I44: C-D06 | J44: =COUNTIFS(Links!$A$2:$A$600,A44,Links!$C$2:$C$600,"<>INFORMS") | K44: [Answered from the record] INT-T-003 L363 (14 Oct, 00:25:36): 'even if the result is negative it's a thesis'. | L44: Document provided | M44: 2026-10-21 | N44: REVIEWED | O44: INT-T-003 (AUTH-018) | P44: 2026-10-21 / Claude | Q44: N-20 closed
A45: Q-U20 | B45: You | C45: Accept the stated limitations: same model family across checks, no true full-catalogue reference above n_fit, historical coverage asymmetry and shared sources? | D45: Accept all | Accept some: ... | Fix: ... | E45: Limitations are closed by being stated, not by tests. | F45: SRC-11 C-E04, C-P02 | G45: S25 | H45: C-E04 (closes), C-P02 (narrows), C-R03/C21 (narrows), C-P02/P05 (closes), C-P02/P07 (closes), C-P02/P08 (closes), C-P02/P09 (closes), C-P03/P14 (closes) | J45: =COUNTIFS(Links!$A$2:$A$600,A45,Links!$C$2:$C$600,"<>INFORMS") | K45: I accept all 7 in B (C-E04, C-P02, C-P02/P05, P07, P08, P09, C-P03/P14); leave the C-E06 for now yes (C-E06 and C-R03/C21 were not covered). | L45: You decided | M45: 2026-10-20 | N45: NEEDS FOLLOW-UP | O45: Verbatim, the human's chat message of 2026-10-20 (reply to the lead's list of 17 limitations) | P45: 2026-10-20 / Claude | Q45: 6 limits accepted and archived; C-P02 narrowed; C-E06 left pending by the human; C-R03/C21 not asked
A46: Q-U21 | B46: You | C46: Authorize a re-fetch of provider price/billing pages (dated table) and a bounded different-vocabulary literature pass? (AUTH-013 is spent.) | D46: Authorize: scope ... | No | E46: A price recheck is needed once the bill is an objective. | F46: AUTH-013 | G46: S10 | H46: C-E05 (narrows), N-5 (narrows), C-S08/VOCAB (narrows), N-6 (narrows), C-E02/UNREADLEADS (narrows) | J46: =COUNTIFS(Links!$A$2:$A$600,A46,Links!$C$2:$C$600,"<>INFORMS") | K46: Authorized in principle: repo evidence first, and if the repo has none, web searches/fetches for that item (AUTH-016). Each fetch names its ledger item. | L46: You decided | M46: 2026-10-19 | N46: REVIEWED | O46: Student's answers to the lead's four questions, 2026-10-19 (quoted in ops/AUTHORIZATIONS.md AUTH-016). | P46: 2026-10-19 / Claude | Q46: AUTH-016 covers web use for closing items; 'Needs new AUTH?' updated on web-dependent rows. A price recheck (C-E05) and the different-vocabulary pass (C-S08/VOCAB) are now permitted per item.
A47: Q-U22 | B47: You | C47: Authorize downloading raw PDFs or page images to read garbled tables and figures (E23, E29, S42)? | D47: Yes | No | E47: The repo holds only extracted text. | F47: SRC-06 E23, E29, S42 | G47: S11 | H47: C-E02/E23 (narrows), C-E02/E29 (narrows), C-S19/S42 (narrows) | J47: =COUNTIFS(Links!$A$2:$A$600,A47,Links!$C$2:$C$600,"<>INFORMS") | K47: Covered by the same authorization: fetching a named source (including a PDF) when the repo lacks it. No code downloads or installs. | L47: You decided | M47: 2026-10-19 | N47: REVIEWED | O47: Student's answers to the lead's four questions, 2026-10-19 (quoted in ops/AUTHORIZATIONS.md AUTH-016). | P47: 2026-10-19 / Claude | Q47: C-E02/E23, E29 and C-S19/S42 may be closed by fetching the PDF and reading the table; recorded per item.
A48: Q-U23 | B48: You | C48: Supply the SRC-08 list of the eight prior-art leads (E30) and any SRC-06/07 rows you want tracked that SRC-11 does not reproduce. | D48: Paste/attach | E48: Names are not in SRC-11. | F48: SRC-06 E30 | G48: S11 | H48: C-E02/E30 (narrows) | J48: =COUNTIFS(Links!$A$2:$A$600,A48,Links!$C$2:$C$600,"<>INFORMS")
A49: Q-U24 | B49: You | C49: Supply the June expose (SRC-03) and April document (SRC-02) for the clause map, or authorize intake. | D49: Supply/authorize | No | E49: The scope map cannot be built from the repo. | F49: SRC-12 1A-1 | G49: S01 | H49: C-D07 (narrows), C-D01 (narrows) | J49: =COUNTIFS(Links!$A$2:$A$600,A49,Links!$C$2:$C$600,"<>INFORMS")
A50: Q-U25 | B50: You | C50: Which design records, if any, do you accept as approved (needs a design-level AUTH)? | D50: List | None | E50: Nothing is approved; everything is provisional. | F50: STATE open items 1-2 | G50: S08 | H50: N-16 (closes) | J50: =COUNTIFS(Links!$A$2:$A$600,A50,Links!$C$2:$C$600,"<>INFORMS")
A51: Q-J25 | B51: Joaa | C51: Which deployment scenarios should the policy and its evaluation target (you mentioned, for example, an automated bug-solving cloud agent and a customer-support agent), and does that imply repeated returning users or mostly single long runs? | D51: Scenario list: ... | Session pattern: ... | E51: Fixes the session pattern and whether memory and cache expiry between sessions matter. | F51: Joaa 19 Oct 12:16 (S-J-003) | G51: S06 | H51: N-25 (closes) | I51: C-D03/CONTEXT, N-3, N-2, C-D08/EC1 | J51: =COUNTIFS(Links!$A$2:$A$600,A51,Links!$C$2:$C$600,"<>INFORMS") | K51: [Answered by the human] line 14: one long run and returning users. | Earlier from the meetings: [Partly] 'The same problem is applicable for any kind of agent ... a salesman ... a recruiter ... marketing' (INT-T-002 L345-L354); no scenario chosen. | L51: You decided | M51: 2026-10-21 | N51: REVIEWED | O51: INT-T-005 (requirements/intake/2026-10-21-user-decisions-after-meetings.md) | P51: 2026-10-21 / Claude | Q51: see the Change log of 2026-10-21
A52: Q-J26 | B52: Joaa | C52: Should explicit caching choices (where cache breakpoints sit, how long to retain) be variables of the policy, or recorded provider behaviour while the policy concerns what is exposed? You also mentioned implicit caching. | D52: Policy variables: ... | Recorded only | Both | E52: Decides whether cache layout and retention are arms or covariates. | F52: Joaa 19 Oct 12:15 (S-J-001) | G52: S06 | H52: N-26 (closes), C-D08/ARMS-CACHE (narrows) | I52: C-S03, N-5, N-1 | J52: =COUNTIFS(Links!$A$2:$A$600,A52,Links!$C$2:$C$600,"<>INFORMS") | K52: [Partly] 'keep them in the explicit cache and that's negligible cost' (INT-T-002 L207-L209), in the 'all in theory' part (L221). | L52: Joaa said | M52: 2026-10-02 / 10-14 / 10-21 (meetings) | N52: NEEDS FOLLOW-UP | O52: Transcript lines in INT-T-002/003/004 (AUTH-018); mapping checked by FND-0035, FND-0036 | P52: 2026-10-21 / Claude | Q52: see the Change log of 2026-10-21
A53: Q-J27 | B53: Joaa | C53: Should the policy include anticipating likely needs before the first request (from role or deployment for a new user, from memory for a returning user), as in your stranger/colleague analogy, or is the first-request context left to the discovery stages? | D53: Include: ... | Out of scope | Later | E53: Decides whether new-user seeding is a mechanism to evaluate. | F53: Joaa 19 Oct 12:22, 12:25 (S-J-005, S-J-006) | G53: S06 | H53: N-27 (closes), C-D08/ARMS-CACHE (narrows) | I53: N-2, C-S15 | J53: =COUNTIFS(Links!$A$2:$A$600,A53,Links!$C$2:$C$600,"<>INFORMS") | K53: [Answered by the human] line 12: yes, as a small part, not the focus. | Earlier from the meetings: [Partly] Relevant part of memory first, more when asked (INT-T-002 L384); not all context 'just by saying hello' (L211-L216, theory part). | L53: You decided | M53: 2026-10-21 | N53: REVIEWED | O53: INT-T-005 (requirements/intake/2026-10-21-user-decisions-after-meetings.md) | P53: 2026-10-21 / Claude | Q53: see the Change log of 2026-10-21
A54: Q-J28 | B54: Joaa | C54: Which documentation or source did you mean when you said the partial-information idea comes from another party's documentation (transcript 00:41:23)? | D54: Name or link ... | Cannot recall | Not needed | E54: The stored sources hold twenty candidates of five kinds (hidden definitions with a search tool, facade with children revealed on use, names plus short descriptions, a listing step apart from a schema step, a category statement); without his answer the prior art for this idea cannot be named. | F54: A9 (EXT-0004); FND-0030 | G54: S13 | H54: AS-09 (closes) | I54: C-D06/NOVELTY | J54: =COUNTIFS(Links!$A$2:$A$600,A54,Links!$C$2:$C$600,"<>INFORMS") | K54: [Partly] 'this partial thingy ... cames out from someone else ... I just read their doc' (INT-T-004 E593); Executor 'doing the same thing' (E605-E607); not named. | L54: Joaa said | M54: 2026-10-02 / 10-14 / 10-21 (meetings) | N54: NEEDS FOLLOW-UP | O54: Transcript lines in INT-T-002/003/004 (AUTH-018); mapping checked by FND-0035, FND-0036 | P54: 2026-10-21 / Claude | Q54: see the Change log of 2026-10-21
A55: Q-J29 | B55: Joaa | C55: The stored literature suggests sharper versions of four of your statements. Do you accept, amend or drop each? (A6) Token reduction keeps accuracy while the required tools stay reachable and costs accuracy when a filter drops them or is lexical. (A12) Effect sizes and model rankings vary by model while the sign of exposure-reduction effects is often shared, so evaluate on several models and report per model. (A2) A symbolic selector with annotated contracts beat the all-tools LLM arm (85.7% vs 32.1%; 97.0% vs 53.5%), but no source gives an LLM selector the same annotations. (A11) In ComplexMCP an LLM-written query beat an embedded question (36.88 vs 27.65 for Gemini-3-flash). | D55: Accept / Amend: ... / Drop, for each of the four | E55: Turns the evidence into statements the supervisor owns; shapes the evaluation (how many models, which selector arms). | F55: A6, A12, A2, A11 (EXT-0004); FND-0028, FND-0029, FND-0031 | G55: S13 | H55: AS-06 (narrows), AS-12 (narrows), AS-02 (narrows), AS-11 (narrows) | I55: AS-13 | J55: =COUNTIFS(Links!$A$2:$A$600,A55,Links!$C$2:$C$600,"<>INFORMS")
A56: Q-U26 | B56: You | C56: Do you authorize a desk simulation, with arithmetic only (no model calls, no external services), of (a) the v3 greedy-core simulation, rerun to compare with its recorded results, and (b) the error rates of the arm-selection procedure (E6)? AUTH-016 excludes implementation, and a simulation is code, so it needs your authorization. | D56: Authorize (a) | Authorize (b) | Authorize both | No | Later | E56: Closes or narrows C-R03/C20 (no computational rerun), C-R03/C26 (cost algebra), C-X06 and C-S14 (error of the selection procedure) without waiting for any model run; the code of the v3 simulation is not in the repo, so (a) would be a re-implementation from its description. | F56: ledger C-R03/C20, C-X06 | G56: S12 | H56: C-R03/C20 (narrows), C-X06 (narrows), C-S14 (narrows) | I56: C-R03/C26 | J56: =COUNTIFS(Links!$A$2:$A$600,A56,Links!$C$2:$C$600,"<>INFORMS")
A57: Q-U27 | B57: You | C57: Do you accept as a stated limitation that the steward summaries (findings SUM and FND) stay 'unverified until a human checks' while their key quotes and numbers have been second-read by the lead and by reviewers of the same model family, or do you want to check chosen summaries yourself? | D57: Accept as a limitation | I will check these: ... | Other | E57: A limitation is closed by being stated; the alternative is a human check of 36 summaries. | F57: ledger C-R03/C25 | G57: S25 | H57: C-R03/C25 (closes) | J57: =COUNTIFS(Links!$A$2:$A$600,A57,Links!$C$2:$C$600,"<>INFORMS")
A58: Q-J30 | B58: Joaa | C58: On 14 October you asked for a staged graph that filters tools (one question per stage, tools can be added back); on 21 October you narrowed the practical scope to memory and tool calls. How do the two fit: is tool filtering one part of a memory-and-tools policy (memory deciding which tools are offered), does the staged graph remain the form of the policy, and which comparison should be the thesis's main one? | D58: Graph stays, memory is one stage | Memory-and-tools replaces the graph | Both, with this main comparison: ... | Other | E58: Every pilot and the evaluation contract depend on it (N-28, C-D03, C-D08). | F58: REGISTER H.2; INT-T-003 L386-L404; INT-T-002 L223-L225 | G58: S05 | H58: N-28 (closes), C-D03 (narrows), C-D08 (narrows) | I58: N-29, N-6 | J58: =COUNTIFS(Links!$A$2:$A$600,A58,Links!$C$2:$C$600,"<>INFORMS") | K58: [Answered by the human] line 5: do both; memory deciding which tools are offered is part of the staged policy. | L58: You decided | M58: 2026-10-21 | N58: REVIEWED | O58: INT-T-005 (requirements/intake/2026-10-21-user-decisions-after-meetings.md) | P58: 2026-10-21 / Claude | Q58: see the Change log of 2026-10-21
A59: Q-J31 | B59: Joaa | C59: Is the staged form satisfied by three tool-deciding stages (deployment configuration, memory-informed offering, discovery with a ranker)? | D59: Yes | No | Other | E59: Policy form of V5-R | F59: design/package-v5/05 s4 | G59: S05 | J59: =COUNTIFS(Links!$A$2:$A$600,A59,Links!$C$2:$C$600,"<>INFORMS") | K59: [Answered by the student on Joaa's behalf] line 23: a starting point; the staged form was an example and may change; memory must not stay off, test it properly in the right place | L59: You decided | M59: 2026-10-22 | N59: REVIEWED | O59: INT-T-006 (requirements/intake/2026-10-22-user-answers-after-v5.md) | P59: 2026-10-22 / Claude | Q59: see the Change log of 2026-10-22
A60: Q-J32 | B60: Joaa | C60: Does 'reduce the count of tools' mean tools offered or definitions billed? | D60: Offered | Billed | Other | E60: Objective | F60: design/package-v5/05 s4 | G60: S05 | J60: =COUNTIFS(Links!$A$2:$A$600,A60,Links!$C$2:$C$600,"<>INFORMS") | K60: [Answered by the student on Joaa's behalf] line 25: the count was an example of what could lower the bill; focus on the goal | L60: You decided | M60: 2026-10-22 | N60: REVIEWED | O60: INT-T-006 (requirements/intake/2026-10-22-user-answers-after-v5.md) | P60: 2026-10-22 / Claude | Q60: see the Change log of 2026-10-22
A61: Q-J33 | B61: Joaa | C61: Executor baseline: as its authors ship it, or a particular setup he has in mind? | D61: As shipped | A setup: ... | No preference | E61: Defines the Executor arm | F61: design/package-v5/05 s4 (reworded) | G61: S05 | J61: =COUNTIFS(Links!$A$2:$A$600,A61,Links!$C$2:$C$600,"<>INFORMS") | K61: [Answered by the student, reporting the supervisor] line 1: Executor could be a baseline but need not be taken as one or forced; learn from it and reuse it in parts (how it works, its parts, strengths, weaknesses) | L61: You decided | M61: 2026-10-22 | N61: REVIEWED | O61: INT-T-007 (requirements/intake/2026-10-22-user-reply-executor-paths-api.md) | P61: 2026-10-22 / Claude | Q61: see the Change log of 2026-10-22
A62: Q-U28 | B62: You | C62: Authorise P0 (university API reading, Executor docs)? | D62: Yes | No | E62: First loop item | F62: design/package-v5/05 s5 | G62: S05 | J62: =COUNTIFS(Links!$A$2:$A$600,A62,Links!$C$2:$C$600,"<>INFORMS") | K62: [Answered] line 2: fetch the status page (done); no keyed request authorised by these words | L62: You decided | M62: 2026-10-22 | N62: NEEDS FOLLOW-UP | O62: INT-T-006 (requirements/intake/2026-10-22-user-answers-after-v5.md) | P62: 2026-10-22 / Claude | Q62: see the Change log of 2026-10-22
A63: Q-U29 | B63: You | C63: Take DPR-0007 as the working draft? | D63: Yes | Keep V4 | Wait | E63: Which draft goes to the supervisor | F63: design/package-v5/05 s5 | G63: S05 | J63: =COUNTIFS(Links!$A$2:$A$600,A63,Links!$C$2:$C$600,"<>INFORMS") | K63: [Answered] line 4: yes, working draft | L63: You decided | M63: 2026-10-22 | N63: REVIEWED | O63: INT-T-006 (requirements/intake/2026-10-22-user-answers-after-v5.md) | P63: 2026-10-22 / Claude | Q63: see the Change log of 2026-10-22
A64: Q-U30 | B64: You | C64: Which average of the bill is primary: total over turns, or mean of per-session rates? | D64: Total over turns | Mean of session rates | Both | E64: Reading of every result | F64: design/package-v5/05 s5 (explained with an example) | G64: S05 | J64: =COUNTIFS(Links!$A$2:$A$600,A64,Links!$C$2:$C$600,"<>INFORMS") | K64: [Answered] lines 1-2: A (total bill over total turns) as the headline, with the lead's recommendation (B, the mean of per-session rates) shown beside it | L64: You decided | M64: 2026-10-25 | N64: REVIEWED | O64: INT-T-008 (requirements/intake/2026-10-25-user-answers-q-u30-expose-files.md) | P64: 2026-10-25 / Claude | Q64: see the Change log of 2026-10-25
A65: Q-U31 | B65: You | C65: Apply the ledger changes proposed in design/package-v5/08? | D65: Yes | No | Some: ... | E65: Ledger state | F65: design/package-v5/05 s5 | G65: S05 | J65: =COUNTIFS(Links!$A$2:$A$600,A65,Links!$C$2:$C$600,"<>INFORMS") | K65: [Answered] line 8: accepted (applied 2026-10-22) | L65: You decided | M65: 2026-10-22 | N65: REVIEWED | O65: INT-T-006 (requirements/intake/2026-10-22-user-answers-after-v5.md) | P65: 2026-10-22 / Claude | Q65: see the Change log of 2026-10-22
A66: Q-U32 | B66: You | C66: Supply the June exposé so its ideas can be tested against V5? | D66: Yes | Later | No | E66: Exposé ideas (N-34) | F66: design/package-v5/05 s5 | G66: S05 | J66: =COUNTIFS(Links!$A$2:$A$600,A66,Links!$C$2:$C$600,"<>INFORMS") | K66: [Answered] line 10: check its ideas only, as ordinary candidates; files are outside the workspace | Carried out 2026-10-25: both files placed in design/package-v5/inputs/expose/ and checked, ideas only (design/package-v5/09-expose-ideas-checked.md) | L66: You decided | M66: 2026-10-22 | N66: REVIEWED | O66: INT-T-006 (requirements/intake/2026-10-22-user-answers-after-v5.md) | P66: 2026-10-22 / Claude | Q66: see the Change log of 2026-10-25
A67: Q-U33 | B67: You | C67: Authorise P0 part 2: a few requests with your key to read usage records and test allowed_tools? | D67: Yes | No | E67: Cache terms on the university API (N-31) | F67: design/package-v5/05 s5 | G67: S05 | J67: =COUNTIFS(Links!$A$2:$A$600,A67,Links!$C$2:$C$600,"<>INFORMS")

Sheet Ledger
A1: LedgerID | B1: Title | C1: Current status | D1: Active? | E1: Review flag | F1: Unanswered linked questions | G1: Closes by (primary) | H1: Cluster | I1: Must precede (gate) | J1: Priority | K1: Order | L1: Wave | M1: Step closes | N1: Owner | O1: Next action | P1: Repo-answerable? | Q1: Kind | R1: Level | S1: Parent ID | T1: What is open (description) | U1: What is known now | V1: Closed when | W1: Hard prerequisites | X1: Soft inputs (may narrow it) | Y1: Linked questions | Z1: Also needs | AA1: Also in cluster(s) | AB1: Reason tags | AC1: Baseline status (SRC-11 / origin) | AD1: Change vs baseline | AE1: Status date | AF1: Status basis (evidence pointer) | AG1: Reopen trigger | AH1: Needs new AUTH? | AI1: Decision / result (on closure) | AJ1: Origin (first source) | AK1: Alias IDs (other names for this item) | AL1: Step first work
A2: N-8 | B2: What exactly did Joaa receive as 'V3'? | C2: OPEN | D2: =IFERROR(INDEX(Lists!$B$2:$B$14,MATCH(C2,Lists!$A$2:$A$14,0)),"?") | E2: =IF(COUNTIFS(Links!$B$2:$B$600,A2,Links!$E$2:$E$600,"Yes")>0,"REVISE","") | F2: =COUNTIFS(Links!$B$2:$B$600,A2,Links!$D$2:$D$600,"No",Links!$C$2:$C$600,"<>INFORMS") | G2: RECORDS-AT-HAND | H2: K1 Scope: what Project A is | I2: G5 Housekeeping / no block | J2: Low | K2: 2 | L2: W0 Orient (no AUTH) | M2: S01 | N2: You | O2: You record what you sent and when | P2: No | Q2: Record fix | R2: Item | T2: What exactly did Joaa receive as 'V3'? The intermediate presentation is not in the repository, and v4 postdates v3. | U2: Unknown from the repo. 2026-10-21 (AUTH-018): the 21 October transcript has the student asking 'Do you like the policy? Um you didn't like it?' (INT-T-002 L135) and no comment on the policy follows; what was sent is still not recorded. | V2: The file(s) you sent and the date are recorded. | Y2: Q-U07 | AC2: n/a (new) | AD2: NEW | AE2: 2026-10-21 | AF2: INT-T-002 (requirements/intake/2026-10-21-supervisor-meeting-2026-10-21-notes-and-transcript.md); mapping design/ledger/notes/MEETINGS-MAPPING-20261021.md checked line by line by FND-0035 and FND-0036; REGISTER section H | AH2: No | AJ2: Review 19 Oct (section 5) | AK2: WD-021 | AL2: S01
A3: N-9 | B3: Joaa's 19 Oct messages: verbatim now stored in this workbook; tracked copy in requirements/ pending | C3: PARTLY ANSWERED | D3: =IFERROR(INDEX(Lists!$B$2:$B$14,MATCH(C3,Lists!$A$2:$A$14,0)),"?") | E3: =IF(COUNTIFS(Links!$B$2:$B$600,A3,Links!$E$2:$E$600,"Yes")>0,"REVISE","") | F3: =COUNTIFS(Links!$B$2:$B$600,A3,Links!$D$2:$D$600,"No",Links!$C$2:$C$600,"<>INFORMS") | G3: RECORDS-AT-HAND | H3: K1 Scope: what Project A is | I3: G5 Housekeeping / no block | J3: Low | K3: 3 | L3: W0 Orient (no AUTH) | M3: S01 | N3: You | O3: Lead drafts the fix; you approve | P3: Partly | Q3: Record fix | R3: Item | T3: The student pasted Joaa's six 19 Oct messages; they are stored verbatim with provenance in the 'Supervisor statements' sheet. Not yet recorded in the repo's requirements/ area with provenance and hash (a tracked change that needs approval). | U3: Verbatim text stored (S-J-001..006). The repo's earlier paraphrase of the caching message ('1/10 of input token for an hour') matches his wording. | V3: Verbatim text recorded in requirements/ with provenance and hash (after your approval), or you decide the workbook copy is enough. | Y3: Q-U08 | AA3: K2 Objective & accounting | AC3: n/a (new) | AD3: NEW | AE3: 2026-10-19 | AF3: Supervisor statements sheet; Questions Q-U08 answer | AH3: No | AJ3: Review 19 Oct (section 5) | AK3: WhatsApp 19 Oct | AL3: S01
A4: C-P03/P11 | B4: First-session reconciliation not executed | C4: OPEN | D4: =IFERROR(INDEX(Lists!$B$2:$B$14,MATCH(C4,Lists!$A$2:$A$14,0)),"?") | E4: =IF(COUNTIFS(Links!$B$2:$B$600,A4,Links!$E$2:$E$600,"Yes")>0,"REVISE","") | F4: =COUNTIFS(Links!$B$2:$B$600,A4,Links!$D$2:$D$600,"No",Links!$C$2:$C$600,"<>INFORMS") | G4: USER-DECISION | H4: K16 Limits & provenance | I4: G5 Housekeeping / no block | J4: Low | K4: 5 | L4: W0 Orient (no AUTH) | M4: S02 | N4: You | O4: You decide (Q-U03) | P4: No | Q4: Record fix | R4: Sub-item | S4: C-P03 | T4: SRC-06 P11: the first-session reconciliation with the origin was not executed. | U4: Out of scope until a separate human authorization. | V4: Repaired or disclosed. | Y4: Q-U03 | AB4: RECORD+DEC | AC4: n/a (sub-item) | AD4: NEW (SRC-11 sub-row) | AE4: 2026-10-19 | AF4: CLAUDE.md; WD-009; CAVEATS row 14 | AH4: Yes (reconciliation) | AJ4: SRC-11 section D5 | AK4: SRC-06 P11, WD-009 | AL4: S02
A5: N-11 | B5: Executor 426-slot comparison: status after 3 October unknown | C5: DEFERRED | D5: =IFERROR(INDEX(Lists!$B$2:$B$14,MATCH(C5,Lists!$A$2:$A$14,0)),"?") | E5: =IF(COUNTIFS(Links!$B$2:$B$600,A5,Links!$E$2:$E$600,"Yes")>0,"REVISE","") | F5: =COUNTIFS(Links!$B$2:$B$600,A5,Links!$D$2:$D$600,"No",Links!$C$2:$C$600,"<>INFORMS") | G5: USER-DECISION | H5: K0 Earlier results | I5: G2 Before the affected pilot/arm | J5: High | K5: 6 | L5: W0 Orient (no AUTH) | M5: S02 | N5: You | O5: none until the trigger fires | P5: No | Q5: Decision | R5: Item | T5: SRC-12 Phase 0 step 2: INT-01 says the Executor 426-slot full comparison had not started at its 3 Oct snapshot; whether it later ran is unknown; the 'quiet-period' date passing does not establish it ran. | U5: Unknown. 2026-10-21 (AUTH-018): deferred: the Executor 426-slot comparison belongs to the earlier work that the human decided to keep outside this work (C-D11). | V5: You supply the later run record or confirm it did not run. | Y5: Q-U02, Q-U04 | Z5: RECORDS-AT-HAND | AB5: ACCESS | AC5: n/a (new) | AD5: NEW (repo sweep) | AE5: 2026-10-21 | AF5: ops/AUTHORIZATIONS.md (AUTH-018) | AG5: The human decides to use the earlier work | AH5: No | AJ5: SRC-12 Phase 0 | AK5: SRC-12 Phase 0 step 2 | AL5: S02
A6: N-14 | B6: Independent Phase 1/2/2b results: should they inform the 21 Oct meeting? | C6: OPEN | D6: =IFERROR(INDEX(Lists!$B$2:$B$14,MATCH(C6,Lists!$A$2:$A$14,0)),"?") | E6: =IF(COUNTIFS(Links!$B$2:$B$600,A6,Links!$E$2:$E$600,"Yes")>0,"REVISE","") | F6: =COUNTIFS(Links!$B$2:$B$600,A6,Links!$D$2:$D$600,"No",Links!$C$2:$C$600,"<>INFORMS") | G6: USER-DECISION | H6: K0 Earlier results | I6: G5 Housekeeping / no block | J6: Low | K6: 7 | L6: W0 Orient (no AUTH) | M6: S02 | N6: You | O6: Answer Q-U13 | P6: No | Q6: Decision | R6: Item | T6: STATE open item 4: the human holds Phase 1 / Phase 2 / Phase 2b results outside the repo; admitting them would need a new AUTH; the lead cannot read them. | U6: Held outside; not read. | V6: Admitted under a new AUTH with labelled provenance, or explicitly kept out. | Y6: Q-U13 | AB6: ACCESS+DEC | AC6: n/a (new) | AD6: NEW (repo sweep) | AE6: 2026-10-19 | AF6: STATE; AUTH-007..009 | AH6: Yes (to admit) | AJ6: repo: STATE open item 4 | AK6: STATE open item 4, AUTH-007..009 | AL6: S02
A7: C-D13 | B7: Workspace safeguards (hooks, deny rules, no sandbox) have known limits; the remote, web tools and fetch hel... | C7: PARTLY ANSWERED | D7: =IFERROR(INDEX(Lists!$B$2:$B$14,MATCH(C7,Lists!$A$2:$A$14,0)),"?") | E7: =IF(COUNTIFS(Links!$B$2:$B$600,A7,Links!$E$2:$E$600,"Yes")>0,"REVISE","") | F7: =COUNTIFS(Links!$B$2:$B$600,A7,Links!$D$2:$D$600,"No",Links!$C$2:$C$600,"<>INFORMS") | G7: USER-DECISION | H7: K16 Limits & provenance | I7: G1 Before any implementation | J7: High | K7: 8 | L7: W0 Orient (no AUTH) | M7: S03 | N7: You | O7: Answer the second part of Q-U11; decide on C-D13/WEBTOOLS | P7: Partly | Q7: Decision | R7: Item | T7: Workspace safeguards (hooks, deny rules, no sandbox) have known limits; the remote, web tools and fetch helper changed the surface; two safeguard texts are stale. | U7: Verifier pass 875 / warn 1 / fail 0 (warn = untracked .workspace). SAFEGUARDS rows 5 and 17 and CLAUDE.md predate AUTH-012/014/015. 2026-10-20: the human accepted eight of the nine documented safeguard limits in their own words ("I accept all 8 in A,"): BASHWRITE, HOOKOFF, INTERACTIVE, INTERP, LEADREG, PEERS, TEAMS, UNTESTED (now in the Archive as ACCEPTED LIMITATION). Open under this item: C-D13/WEBTOOLS and the second part of Q-U11 (whether the stale safeguard text in SAFEGUARDS rows 5 and 17 and CLAUDE.md may be updated for review; the proposal is in design/ledger/notes/N-19-proposed-text-for-pinned-files.md). | V7: Limits accepted or fixed; stale text updated (pinned files need your review). | Y7: Q-U11 | Z7: RECORDS-AT-HAND | AB7: RECORD+DEC | AC7: BOUNDARY - OPEN | AD7: RE-CHARACTERISED | AE7: 2026-10-20 | AF7: Questions Q-U11; chat message of 2026-10-20 | AH7: No | AJ7: SRC-11 canonical | AK7: SRC-06 D16, SRC-06 P12, STATE open item 7 | AL7: S03
A8: C-D13/WEBTOOLS | B8: WebSearch/WebFetch and the fetch helper are now allow-listed; scope rests on the AUTH text only | C8: OPEN | D8: =IFERROR(INDEX(Lists!$B$2:$B$14,MATCH(C8,Lists!$A$2:$A$14,0)),"?") | E8: =IF(COUNTIFS(Links!$B$2:$B$600,A8,Links!$E$2:$E$600,"Yes")>0,"REVISE","") | F8: =COUNTIFS(Links!$B$2:$B$600,A8,Links!$D$2:$D$600,"No",Links!$C$2:$C$600,"<>INFORMS") | G8: USER-DECISION | H8: K16 Limits & provenance | I8: G1 Before any implementation | J8: High | K8: 17 | L8: W0 Orient (no AUTH) | M8: S03 | N8: You | O8: You decide (Q-U11) | P8: Answered (see basis) | Q8: Safeguard limit | R8: Sub-item | S8: C-D13 | T8: AUTH-014 moved WebSearch/WebFetch to allow; AUTH-015 added a pinned fetch helper rule. Scope limits are instructions, not mechanisms. | U8: Documented limit. | V8: Accepted, or fixed (OS sandbox, separate account). | Y8: Q-U11 | Z8: ACCEPT-LIMITATION | AB8: RECORD+DEC | AC8: n/a (sub-item) | AD8: NEW (repo sweep) | AE8: 2026-10-19 | AF8: AUTH-014, AUTH-015; commits bde0cdd, d791135 | AH8: No | AJ8: repo: AUTHORIZATIONS | AL8: S03
A9: C-P03/P12 | B9: Safeguards untested | C9: PARTLY ANSWERED | D9: =IFERROR(INDEX(Lists!$B$2:$B$14,MATCH(C9,Lists!$A$2:$A$14,0)),"?") | E9: =IF(COUNTIFS(Links!$B$2:$B$600,A9,Links!$E$2:$E$600,"Yes")>0,"REVISE","") | F9: =COUNTIFS(Links!$B$2:$B$600,A9,Links!$D$2:$D$600,"No",Links!$C$2:$C$600,"<>INFORMS") | G9: USER-DECISION | H9: K16 Limits & provenance | I9: G5 Housekeeping / no block | J9: Low | K9: 18 | L9: W0 Orient (no AUTH) | M9: S03 | N9: You | O9: You decide | P9: Partly | Q9: Record fix | R9: Sub-item | S9: C-P03 | T9: SRC-06 P12: safeguards were untested. | U9: Deterministic tests exist; interactive/VS Code and adversarial behaviour are untested (see C-D13 children). | V9: Repaired or disclosed. | AB9: RECORD+DEC | AC9: n/a (sub-item) | AD9: NEW (SRC-11 sub-row) | AE9: 2026-10-19 | AF9: ops/SAFEGUARDS.md test index (A1..C8, guard_cases.py 57 cases, R2); known bypasses list | AH9: Yes (reconciliation) | AJ9: SRC-11 section D5 | AK9: SRC-06 P12 | AL9: S03
A10: N-15 | B10: Untracked 19 Oct draft and EXT-0067..0073: keep or remove (author unknown) | C10: OPEN | D10: =IFERROR(INDEX(Lists!$B$2:$B$14,MATCH(C10,Lists!$A$2:$A$14,0)),"?") | E10: =IF(COUNTIFS(Links!$B$2:$B$600,A10,Links!$E$2:$E$600,"Yes")>0,"REVISE","") | F10: =COUNTIFS(Links!$B$2:$B$600,A10,Links!$D$2:$D$600,"No",Links!$C$2:$C$600,"<>INFORMS") | G10: USER-DECISION | H10: K16 Limits & provenance | I10: G5 Housekeeping / no block | J10: Low | K10: 19 | L10: W0 Orient (no AUTH) | M10: S03 | N10: You | O10: Answer Q-U12 | P10: n/a | Q10: Decision | R10: Item | T10: design/tool-exposure-policy-proposal.md and EXT-0067..0073 were committed with a provenance banner; author and authorization unrecorded. | U10: Not adopted as a record; flagged. | V10: Kept (with provenance) or removed. | Y10: Q-U12 | AB10: RECORD+DEC | AC10: n/a (new) | AD10: NEW (repo sweep) | AE10: 2026-10-19 | AF10: v4-03 section 4 | AH10: No | AJ10: repo: STATE open item 6; v4-03 section 4 | AK10: STATE open item 6 | AL10: S03
A11: N-13 | B11: Thesis question not supplied | C11: OPEN | D11: =IFERROR(INDEX(Lists!$B$2:$B$14,MATCH(C11,Lists!$A$2:$A$14,0)),"?") | E11: =IF(COUNTIFS(Links!$B$2:$B$600,A11,Links!$E$2:$E$600,"Yes")>0,"REVISE","") | F11: =COUNTIFS(Links!$B$2:$B$600,A11,Links!$D$2:$D$600,"No",Links!$C$2:$C$600,"<>INFORMS") | G11: USER-DECISION | H11: K1 Scope: what Project A is | I11: G3 Before confirmatory study | J11: Normal | K11: 22 | L11: W1 Decide | M11: S05 | N11: You (verbatim text, who, when), Joaa if wording is contested | O11: Answer Q-U09 | P11: No | Q11: Decision | R11: Item | T11: requirements/THESIS_QUESTION.md is a placeholder (status awaiting-user); excerpt E1 is a mid-sentence fragment and was not entered; Q3 asks whether and in what exact wording E1 may be entered. | U11: Not supplied. | V11: The question is entered verbatim with provenance and hash. | Y11: Q-J01, Q-J02, Q-U01, Q-U09 | Z11: JOAA-DECISION | AB11: DEC+ACCESS | AC11: n/a (new) | AD11: NEW (repo sweep) | AE11: 2026-10-19 | AF11: THESIS_QUESTION.md; CAVEATS 17 | AH11: No | AJ11: repo: STATE; REGISTER F and G.3 Q3 | AK11: REGISTER G.3 Q3, CAVEATS 17, STATE open item 3 | AL11: S01
A12: N-26 | B12: Caching mechanisms as policy variables: implicit, explicit (breakpoints, retention) or recorded only? | C12: PARTLY ANSWERED | D12: =IFERROR(INDEX(Lists!$B$2:$B$14,MATCH(C12,Lists!$A$2:$A$14,0)),"?") | E12: =IF(COUNTIFS(Links!$B$2:$B$600,A12,Links!$E$2:$E$600,"Yes")>0,"REVISE","") | F12: =COUNTIFS(Links!$B$2:$B$600,A12,Links!$D$2:$D$600,"No",Links!$C$2:$C$600,"<>INFORMS") | G12: JOAA-DECISION | H12: K9 Cache & billing | I12: G2 Before the affected pilot/arm | J12: High | K12: 33 | L12: W1 Decide | M12: S06 | N12: Joaa | O12: Candidate for the first proof-of-concept | P12: Partly | Q12: Decision | R12: Item | T12: Joaa wrote that vendors 'provide implicit and explicit caching mechanisms so this should also be included in your policy' (S-J-001). Which caching choices are design variables of the policy (explicit breakpoints, cache layout, retention period) and which are provider behaviour that is only recorded? Treated as his proposal, to be adopted, refined or narrowed. | U12: Documented mechanisms in the pages read (facts, not the decision): Anthropic automatic or explicit via cache_control (EXT-0115); Bedrock explicit checkpoints (EXT-0137); Gemini implicit caching on by default, and the Interactions API supports implicit only (EXT-0141); OpenAI GPT-5.6 and later: prompt_cache_options.mode with explicit breakpoints (up to four writes per request) and ttl (EXT-0142); OpenAI earlier models implicit only with prompt_cache_retention (EXT-0142); MCP: server-set ttlMs and cacheScope hints for client-side caching, not a provider prompt cache (EXT-0143). Which of these are variables of the policy is Joaa's decision (Q-J26). Recheck 2026-10-19: the Gemini pricing page now lists Gemini 4 Argon as 'Implicit caching only (explicit caching is not supported)', so explicit-caching availability varies by model within one provider (price-gemini-20261019). 2026-10-21 (AUTH-018): his statement that added information can stay in the explicit cache for the whole conversation at 'negligible cost' (INT-T-002 L207-L209) is in the 'in theory' part (L221); it is recorded as an assertion to test (AS-15). 2026-10-21 (AUTH-019, the human's decisions): the human notes that prompt caching 'may use this as conversation memory in the begining' (line 8): caching as an early, simple memory is a candidate design element. | V12: Variables and recorded-only items listed in the evaluation contract. | X12: C-S03, N-5, C-D02 | Y12: Q-J26 | Z12: DESK-ANALYSIS | AA12: K2 Objective & accounting | AB12: DEC | AC12: n/a (new) | AD12: NEW | AE12: 2026-10-21 | AF12: INT-T-005 (requirements/intake/2026-10-21-user-decisions-after-meetings.md) | AH12: No | AJ12: Joaa 19 Oct (Supervisor statements sheet) | AK12: Joaa 19 Oct 12:15 (implicit and explicit caching), Joaa 19 Oct 12:15 (implicit and explicit caching) | AL12: S06
A13: N-22 | B13: Joaa's proposal: combine MCP server context, memory and explicit caching to find the best policy | C13: PARTLY ANSWERED | D13: =IFERROR(INDEX(Lists!$B$2:$B$14,MATCH(C13,Lists!$A$2:$A$14,0)),"?") | E13: =IF(COUNTIFS(Links!$B$2:$B$600,A13,Links!$E$2:$E$600,"Yes")>0,"REVISE","") | F13: =COUNTIFS(Links!$B$2:$B$600,A13,Links!$D$2:$D$600,"No",Links!$C$2:$C$600,"<>INFORMS") | G13: JOAA-DECISION | H13: K4 Memory & sessions | I13: G2 Before the affected pilot/arm | J13: High | K13: 35 | L13: W1 Decide | M13: S06 | N13: Joaa | O13: N-28 and AS-15 | P13: Partly | Q13: Decision | R13: Sub-item | S13: C-D07 | T13: Joaa wrote: 'So you have to combine all three to find the best policy: 1. MCP server context 2. Memory 3. Explicit caching' (S-J-004). Treated as his proposal for the policy's design space. The repo's sources have not evaluated the three together yet; whether the design space is all three, a subset, or later work is his scope choice, and the proposal may be adopted, refined or narrowed. | U13: Each of the three has separate evidence in the repo; their combination has not been tested. 2026-10-21 (AUTH-018): explicit caching 'is also applicable for memory ... for knowledge' (INT-T-002 L197), said in the part he calls 'all in theory' (L221); 'back to practical' he keeps memory and tool calls only (L223-L225) and does not return to caching. The combination is narrowed to tools and memory; whether explicit caching is part of the practical scope is not said. | V13: In or out of scope; if in, an arm set is defined. | W13: N-9 | Y13: Q-J05, Q-J06 | Z13: TEST-PILOT | AB13: DEC+DATA | AC13: n/a (new) | AD13: NEW (repo sweep) | AE13: 2026-10-21 | AF13: INT-T-002 (requirements/intake/2026-10-21-supervisor-meeting-2026-10-21-notes-and-transcript.md); mapping design/ledger/notes/MEETINGS-MAPPING-20261021.md checked line by line by FND-0035 and FND-0036; REGISTER section H | AH13: No | AJ13: review 19 Oct section 3.2 | AK13: Joaa 19 Oct 12:22 (combine all three) | AL13: S06
A14: C-D03/ANSWERER | B14: Who or what answers each stage's question (model, rule, score)? | C14: PARTLY ANSWERED | D14: =IFERROR(INDEX(Lists!$B$2:$B$14,MATCH(C14,Lists!$A$2:$A$14,0)),"?") | E14: =IF(COUNTIFS(Links!$B$2:$B$600,A14,Links!$E$2:$E$600,"Yes")>0,"REVISE","") | F14: =COUNTIFS(Links!$B$2:$B$600,A14,Links!$D$2:$D$600,"No",Links!$C$2:$C$600,"<>INFORMS") | G14: JOAA-DECISION | H14: K3 Policy form | I14: G2 Before the affected pilot/arm | J14: High | K14: 36 | L14: W1 Decide | M14: S07 | N14: Joaa | O14: Decided by evaluation (pilot design) | P14: No | Q14: Decision | R14: Sub-item | S14: C-D03 | T14: The excerpt does not say; v4 treats system-vs-model as an empirical question. | U14: v4 leaves it empirical. 2026-10-21 (AUTH-018): stage one is decided from context, who invokes the agent (INT-T-003 L261); for a later stage he names Executor-style capability listing or semantic narrowing, 'which one is better ... You have to figure it out' (L306-L308). | V14: Joaa's answer recorded in his words. | Y14: Q-J11 | AB14: DEC | AC14: n/a (sub-item) | AD14: NEW (repo sweep) | AE14: 2026-10-21 | AF14: INT-T-003 (requirements/intake/2026-10-21-supervisor-meeting-2026-10-14-notes-and-transcript.md); mapping design/ledger/notes/MEETINGS-MAPPING-20261021.md checked line by line by FND-0035 and FND-0036; REGISTER section H | AH14: No | AJ14: repo: REGISTER / COMPARISON | AK14: COMPARISON section 4 | AL14: S05
A15: C-D03/CONTEXT | B15: What do 'context' and 'scenario' mean (the request, the trajectory so far, the deployment)? | C15: PARTLY ANSWERED | D15: =IFERROR(INDEX(Lists!$B$2:$B$14,MATCH(C15,Lists!$A$2:$A$14,0)),"?") | E15: =IF(COUNTIFS(Links!$B$2:$B$600,A15,Links!$E$2:$E$600,"Yes")>0,"REVISE","") | F15: =COUNTIFS(Links!$B$2:$B$600,A15,Links!$D$2:$D$600,"No",Links!$C$2:$C$600,"<>INFORMS") | G15: JOAA-DECISION | H15: K3 Policy form | I15: G2 Before the affected pilot/arm | J15: High | K15: 37 | L15: W1 Decide | M15: S07 | N15: Joaa | O15: Use both senses explicitly in the contract; ask only if a choice depends on it | P15: No | Q15: Decision | R15: Sub-item | S15: C-D03 | T15: REQ-O14-09 / brief Q2: 'based on the context and based on the scenario it will be different' are undefined; the excerpt may be prescriptive or a prediction. | U15: Open. 2026-10-21 (AUTH-018): two senses in his words: on 14 October context is the situation, who invokes the agent and in what role ('based on who is invoking ... you will change the tools', INT-T-003 L261); on 21 October context is what the model is given: tools, knowledge, memory, invocation settings, input and output modalities (INT-T-002 L176-L190). 'Scenario' is not defined separately. | V15: Joaa's answer recorded in his words. | Y15: Q-J09, Q-J25 | AB15: DEC | AC15: n/a (sub-item) | AD15: NEW (repo sweep) | AE15: 2026-10-21 | AF15: INT-T-003 (requirements/intake/2026-10-21-supervisor-meeting-2026-10-14-notes-and-transcript.md); INT-T-002 (requirements/intake/2026-10-21-supervisor-meeting-2026-10-21-notes-and-transcript.md); mapping design/ledger/notes/MEETINGS-MAPPING-20261021.md checked line by line by FND-0035 and FND-0036; REGISTER section H | AH15: No | AJ15: repo: REGISTER / COMPARISON | AK15: REQ-O14-09, v4-01 Q2 | AL15: S05
A16: C-R02/C10-13 | B16: Offline/runtime label, D-node presentation, G vs C-A, A1-A5 disagreements | C16: PARTLY ANSWERED | D16: =IFERROR(INDEX(Lists!$B$2:$B$14,MATCH(C16,Lists!$A$2:$A$14,0)),"?") | E16: =IF(COUNTIFS(Links!$B$2:$B$600,A16,Links!$E$2:$E$600,"Yes")>0,"REVISE","") | F16: =COUNTIFS(Links!$B$2:$B$600,A16,Links!$D$2:$D$600,"No",Links!$C$2:$C$600,"<>INFORMS") | G16: RECORDS-AT-HAND | H16: K17 Record repair & procedure error | I16: G5 Housekeeping / no block | J16: Low | K16: 39 | L16: W1 Decide | M16: S07 | N16: You (presentation); team (E6) | O16: Lead drafts the fix; you approve | P16: Partly | Q16: Disagreement | R16: Sub-item | S16: C-R02 | T16: SRC-06 C10-C13 (grouped in SRC-11 D4): label accepted as accurate; D-node presentation is the user's decision; G vs C-A has no winner and selection inflation is unmeasured; A1-A5 disagreements persist; A6 withdrawn in v3. | U16: Presentation decided by the lead (AUTH-010); retained disagreements listed in v2-06 and v3-04. | V16: Independent re-check and a dated fix. | Y16: Q-U10 | AB16: RECORD+DATA | AC16: n/a (sub-item) | AD16: NEW (SRC-11 sub-row) | AE16: 2026-10-19 | AF16: WD-019/020; v2-06 section A; v3-04 section 3 | AH16: No for presentation | AJ16: SRC-11 section D4 | AK16: SRC-06 C10-C13, v2-06 A1-A5 | AL16: S05
A17: C-D10 | B17: Confirm the presentation: run-time policy figure separate from the study-protocol figure (D-nodes offline). | C17: PARTLY ANSWERED | D17: =IFERROR(INDEX(Lists!$B$2:$B$14,MATCH(C17,Lists!$A$2:$A$14,0)),"?") | E17: =IF(COUNTIFS(Links!$B$2:$B$600,A17,Links!$E$2:$E$600,"Yes")>0,"REVISE","") | F17: =COUNTIFS(Links!$B$2:$B$600,A17,Links!$D$2:$D$600,"No",Links!$C$2:$C$600,"<>INFORMS") | G17: USER-DECISION | H17: K3 Policy form | I17: G5 Housekeeping / no block | J17: Low | K17: 43 | L17: W1 Decide | M17: S07 | N17: You | O17: You decide (Q-J08, Q-U10) | P17: n/a | Q17: Decision | R17: Item | T17: Confirm the presentation: run-time policy figure separate from the study-protocol figure (D-nodes offline). | U17: Decided by the lead under AUTH-010 (WD-020); not yet confirmed by you; Joaa saw v3. | V17: You confirm or reverse; decide what Joaa is shown. | W17: C-D03 | Y17: Q-J08, Q-U10 | AB17: DEC | AC17: PARTLY ANSWERED - OPEN | AD17: RE-CHARACTERISED | AE17: 2026-10-19 | AF17: WD-020; v4-03 section 1 | AH17: No | AJ17: SRC-11 canonical | AK17: SRC-06 D13, SRC-06 C10 | AL17: S05
A18: C-R02 | B18: Challenge residuals: D-node presentation (decided by lead), no winner between G and C-A, selection inflatio... | C18: PARTLY ANSWERED | D18: =IFERROR(INDEX(Lists!$B$2:$B$14,MATCH(C18,Lists!$A$2:$A$14,0)),"?") | E18: =IF(COUNTIFS(Links!$B$2:$B$600,A18,Links!$E$2:$E$600,"Yes")>0,"REVISE","") | F18: =COUNTIFS(Links!$B$2:$B$600,A18,Links!$D$2:$D$600,"No",Links!$C$2:$C$600,"<>INFORMS") | G18: USER-DECISION | H18: K17 Record repair & procedure error | I18: G5 Housekeeping / no block | J18: Low | K18: 44 | L18: W1 Decide | M18: S07 | N18: You (presentation); team (E6) | O18: You decide (Q-U10) | P18: n/a | Q18: Decision | R18: Item | T18: Challenge residuals: D-node presentation (decided by lead), no winner between G and C-A, selection inflation unmeasured. | U18: Presentation part decided by lead; selection-error part waits on E6. | V18: Presentation confirmed; selection error measured (X06). | W18: C-D03 | Y18: Q-U10 | Z18: TEST-PILOT | AA18: K3 Policy form | AB18: DEC+DATA | AC18: PARTLY ANSWERED - OPEN | AD18: RE-CHARACTERISED | AE18: 2026-10-19 | AF18: WD-019/020; CH-0010..0013 | AH18: No for presentation | AJ18: SRC-11 canonical | AK18: SRC-06 C10-C13, HYP-0013 | AL18: S05
A19: N-16 | B19: No design record is approved; human review of the v4 package pending | C19: OPEN | D19: =IFERROR(INDEX(Lists!$B$2:$B$14,MATCH(C19,Lists!$A$2:$A$14,0)),"?") | E19: =IF(COUNTIFS(Links!$B$2:$B$600,A19,Links!$E$2:$E$600,"Yes")>0,"REVISE","") | F19: =COUNTIFS(Links!$B$2:$B$600,A19,Links!$D$2:$D$600,"No",Links!$C$2:$C$600,"<>INFORMS") | G19: USER-DECISION | H19: K6 Deliverable & authorization | I19: G5 Housekeeping / no block | J19: Low | K19: 45 | L19: W1 Decide | M19: S08 | N19: You | O19: Answer Q-U25 | P19: n/a | Q19: Decision | R19: Item | T19: Every design record is provisional/proposed; `approved` needs the human and a design-level AUTH. STATE asks you to review the brief first, then 02 and 03; AUTHORIZATIONS 'Not yet authorized' lists review/acceptance of results. | U19: Nothing is approved. | V19: Records you accept are marked approved under an AUTH, the rest stay proposed. | Y19: Q-U25 | AB19: DEC | AC19: n/a (new) | AD19: NEW (repo sweep) | AE19: 2026-10-19 | AF19: STATE; AUTHORIZATIONS | AH19: Yes (design-level) | AJ19: repo: STATE open item 1; AUTHORIZATIONS 'Not yet authorized' | AK19: STATE open item 1, STATE open item 2 | AL19: S05
A20: C-E06 | B20: True full-catalogue reference cannot run above n_fit (roughly 200 to 10,000 tools); a substitute does not b... | C20: LIMITATION - ACCEPTANCE PENDING | D20: =IFERROR(INDEX(Lists!$B$2:$B$14,MATCH(C20,Lists!$A$2:$A$14,0)),"?") | E20: =IF(COUNTIFS(Links!$B$2:$B$600,A20,Links!$E$2:$E$600,"Yes")>0,"REVISE","") | F20: =COUNTIFS(Links!$B$2:$B$600,A20,Links!$D$2:$D$600,"No",Links!$C$2:$C$600,"<>INFORMS") | G20: ACCEPT-LIMITATION | H20: K7 Large-catalogue reference | I20: G3 Before confirmatory study | J20: Normal | K20: 47 | L20: W1 Decide | M20: S08 | N20: You (+Joaa, brief Q4) | O20: Accept the limitation when you review it (it is a physical limit) | P20: n/a | Q20: Limitation | R20: Item | T20: True full-catalogue reference cannot run above n_fit (roughly 200 to 10,000 tools); a substitute does not become full exposure. | U20: Stated explicitly in v4: above n_fit no noninferiority-to-expose-all claim; a policy from a frontier needs a human margin or budget. 2026-10-20: the human said to leave it for now ("leave the C-E06 for now yes"); it stays pending, with the margin or budget question for Joaa (Q-J13). 2026-10-21 (AUTH-019, the human's decisions): no margin or budget is set (line 16): above the window the study reports the cost-accuracy frontier and the gap to the pool reference; no feasibility test against expose-all is needed there. | V20: Boundary accepted and claim narrowed; who sets the margin/budget recorded. | W20: C-D02 | Y20: Q-J13 | Z20: JOAA-DECISION | AA20: K5 Evaluation contract | AB20: BOUND | AC20: BOUNDARY | AD20: UNCHANGED | AE20: 2026-10-21 | AF20: INT-T-005 (requirements/intake/2026-10-21-user-decisions-after-meetings.md) | AH20: No | AJ20: SRC-11 canonical | AK20: SRC-06 S31, SRC-07 32 | AL20: S08
A21: C-S17 | B21: Is offline selection cost charged (N_dep, deployment horizon) and shown with and without? | C21: PARTLY ANSWERED | D21: =IFERROR(INDEX(Lists!$B$2:$B$14,MATCH(C21,Lists!$A$2:$A$14,0)),"?") | E21: =IF(COUNTIFS(Links!$B$2:$B$600,A21,Links!$E$2:$E$600,"Yes")>0,"REVISE","") | F21: =COUNTIFS(Links!$B$2:$B$600,A21,Links!$D$2:$D$600,"No",Links!$C$2:$C$600,"<>INFORMS") | G21: JOAA-DECISION | H21: K2 Objective & accounting | I21: G3 Before confirmatory study | J21: Normal | K21: 48 | L21: W1 Decide | M21: S08 | N21: Joaa + you | O21: Decide the treatment of one-time development runs when the end-to-end study is designed | P21: No | Q21: Decision | R21: Item | T21: Is offline selection cost charged (N_dep, deployment horizon) and shown with and without? | U21: C_tok includes O_dev/N_dep; N_dep unset. 2026-10-21 (AUTH-018): filtering cost counts against the saving: 'you cannot use many tokens because you're saving tokens ... if you use many many more token to filter out the tools then there is no value' (INT-T-004 E230-E232); amortising offline selection cost over a deployment horizon is not discussed. 2026-10-21 (AUTH-019, the human's decisions): the human points the offline-cost question to the bill on average (line 10 'go chcek what i said for QJ03', line 8): what the policy spends to select or discover tools is part of the averaged bill; how a one-time offline development run is charged is not stated. | V21: Convention and horizon fixed. | W21: C-D02 | Y21: Q-J19 | Z21: USER-DECISION | AA21: K5 Evaluation contract | AB21: DEC+DATA | AC21: PARTLY ANSWERED - OPEN | AD21: UNCHANGED | AE21: 2026-10-21 | AF21: INT-T-005 (requirements/intake/2026-10-21-user-decisions-after-meetings.md) | AH21: No | AJ21: SRC-11 canonical | AK21: SRC-06 S35 | AL21: S08
A22: C-D08/ARMS-CACHE | B22: New arm candidates from the cache/memory addendum (memory-seeded core, re-ordering vs append-only, 5-min vs 1-h write) | C22: PARTLY ANSWERED | D22: =IFERROR(INDEX(Lists!$B$2:$B$14,MATCH(C22,Lists!$A$2:$A$14,0)),"?") | E22: =IF(COUNTIFS(Links!$B$2:$B$600,A22,Links!$E$2:$E$600,"Yes")>0,"REVISE","") | F22: =COUNTIFS(Links!$B$2:$B$600,A22,Links!$D$2:$D$600,"No",Links!$C$2:$C$600,"<>INFORMS") | G22: DESK-ANALYSIS | H22: K9 Cache & billing | I22: G1 Before any implementation | J22: High | K22: 50 | L22: W2 Desk work (no model runs) | M22: S09 | N22: Joaa + you (or a documented pilot) | O22: 05 P1, P2 | P22: No | Q22: Parameter | R22: Sub-item | S22: C-D08 | T22: v4-04 section 5 lists candidate arms not yet in the arm table: a memory-seeded core after a shared prefix; core re-ordering vs append-only; a one-hour vs five-minute write choice by expected session gap. | U22: Unset. | V5 2026-10-22: arms fixed for the loop: DPR-0008 against V5-R on returning sessions (05 P1), all-offered against subset-offered (05 P2) | V22: Set in the evaluation contract, or deferred to a documented pilot with Joaa's agreement. | X22: N-2, C-D02 | Y22: Q-J06, Q-J26, Q-J27 | Z22: JOAA-DECISION | AB22: DEC+DATA | AC22: n/a (sub-item) | AD22: NEW (repo sweep) | AE22: 2026-10-22 | AF22: design/package-v5/05 s2 | AH22: No | AJ22: repo: v4-02 / v3-04 section 5 / v2-05 section 3 | AL22: S06
A23: C-D08/ALPHA | B23: alpha / family error rate | C23: DEFERRED | D23: =IFERROR(INDEX(Lists!$B$2:$B$14,MATCH(C23,Lists!$A$2:$A$14,0)),"?") | E23: =IF(COUNTIFS(Links!$B$2:$B$600,A23,Links!$E$2:$E$600,"Yes")>0,"REVISE","") | F23: =COUNTIFS(Links!$B$2:$B$600,A23,Links!$D$2:$D$600,"No",Links!$C$2:$C$600,"<>INFORMS") | G23: JOAA-DECISION | H23: K5 Evaluation contract | I23: G1 Before any implementation | J23: High | K23: 51 | L23: W2 Desk work (no model runs) | M23: S09 | N23: Joaa + you (or a documented pilot) | O23: none until the trigger fires | P23: No | Q23: Parameter | R23: Sub-item | S23: C-D08 | T23: alpha and the family error rate over the arm table are unset (R7: unnamed). | U23: Unset. 2026-10-21 (AUTH-019, the human's decisions): deferred to the end-to-end phase: the human's process is research and a drafted policy, then proof-of-concept tests of parts in a loop ('not rigirous tests or full tests'), then an end-to-end study and final findings (INT-T-005 (requirements/intake/2026-10-21-user-decisions-after-meetings.md) line 7); error control, strata and the selection procedure's error rates belong to that last phase. | V23: Set in the evaluation contract, or deferred to a documented pilot with Joaa's agreement. | Y23: Q-J20 | Z23: DESK-ANALYSIS | AB23: DEC+DATA | AC23: n/a (sub-item) | AD23: NEW (repo sweep) | AE23: 2026-10-21 | AF23: INT-T-005 (requirements/intake/2026-10-21-user-decisions-after-meetings.md) | AG23: The end-to-end study is designed | AH23: No | AJ23: repo: v4-02 / v3-04 section 5 / v2-05 section 3 | AK23: alpha, R7 | AL23: S08
A24: C-D08/ARMS | B24: Arm-table composition (trigger arms, navigated hierarchy, ordered-core arms, size of the table) | C24: OPEN | D24: =IFERROR(INDEX(Lists!$B$2:$B$14,MATCH(C24,Lists!$A$2:$A$14,0)),"?") | E24: =IF(COUNTIFS(Links!$B$2:$B$600,A24,Links!$E$2:$E$600,"Yes")>0,"REVISE","") | F24: =COUNTIFS(Links!$B$2:$B$600,A24,Links!$D$2:$D$600,"No",Links!$C$2:$C$600,"<>INFORMS") | G24: JOAA-DECISION | H24: K5 Evaluation contract | I24: G1 Before any implementation | J24: High | K24: 52 | L24: W2 Desk work (no model runs) | M24: S09 | N24: Joaa + you (or a documented pilot) | O24: Ask Joaa (Q-J07) | P24: No | Q24: Parameter | R24: Sub-item | S24: C-D08 | T24: The arm table must be fixed before any run: at least three trigger arms (after results, at finish, both), the navigated-hierarchy arm, ordered-core arms if a need estimator exists; its size drives multiplicity and power. | U24: Unset. | V24: Set in the evaluation contract, or deferred to a documented pilot with Joaa's agreement. | Y24: Q-J07 | Z24: DESK-ANALYSIS | AB24: DEC+DATA | AC24: n/a (sub-item) | AD24: NEW (repo sweep) | AE24: 2026-10-19 | AF24: v4-02 notes 4, section 5 | AH24: No | AJ24: repo: v4-02 / v3-04 section 5 / v2-05 section 3 | AK24: CH-0040 (a), CH-0049 | AL24: S08
A25: C-D08/BS | B25: Discovery budget B_s (and whether the budget is adequate: RA8, RA4) | C25: OPEN | D25: =IFERROR(INDEX(Lists!$B$2:$B$14,MATCH(C25,Lists!$A$2:$A$14,0)),"?") | E25: =IF(COUNTIFS(Links!$B$2:$B$600,A25,Links!$E$2:$E$600,"Yes")>0,"REVISE","") | F25: =COUNTIFS(Links!$B$2:$B$600,A25,Links!$D$2:$D$600,"No",Links!$C$2:$C$600,"<>INFORMS") | G25: JOAA-DECISION | H25: K5 Evaluation contract | I25: G1 Before any implementation | J25: High | K25: 53 | L25: W2 Desk work (no model runs) | M25: S09 | N25: Joaa + you (or a documented pilot) | O25: Ask Joaa (Q-J20) | P25: No | Q25: Parameter | R25: Sub-item | S25: C-D08 | T25: The discovery budget B_s and the trajectory/search budgets that must allow the extra calls (RA4, RA8) are unset. | U25: Unset. | V25: Set in the evaluation contract, or deferred to a documented pilot with Joaa's agreement. | Y25: Q-J20 | Z25: DESK-ANALYSIS | AB25: DEC+DATA | AC25: n/a (sub-item) | AD25: NEW (repo sweep) | AE25: 2026-10-19 | AF25: v4-02 header ('unset') | AH25: No | AJ25: repo: v4-02 / v3-04 section 5 / v2-05 section 3 | AK25: B_s, RA8, RA4 | AL25: S08
A26: C-D08/CALLLIM | B26: Call limit: its value and what counts (discovery calls, LLM-classifier calls, the vehicle's 12 tool-call budget) | C26: OPEN | D26: =IFERROR(INDEX(Lists!$B$2:$B$14,MATCH(C26,Lists!$A$2:$A$14,0)),"?") | E26: =IF(COUNTIFS(Links!$B$2:$B$600,A26,Links!$E$2:$E$600,"Yes")>0,"REVISE","") | F26: =COUNTIFS(Links!$B$2:$B$600,A26,Links!$D$2:$D$600,"No",Links!$C$2:$C$600,"<>INFORMS") | G26: DESK-ANALYSIS | H26: K5 Evaluation contract | I26: G1 Before any implementation | J26: High | K26: 54 | L26: W2 Desk work (no model runs) | M26: S09 | N26: Joaa + you (or a documented pilot) | O26: Lead computes or writes it (no model runs) | P26: No | Q26: Parameter | R26: Sub-item | S26: C-D08 | T26: The call limit's value is the vehicle's; whether discovery calls count against the vehicle's 12 tool-call budget (a bias against discovery arms) and whether an LLM classifier's calls count are unset. | U26: Unset. | V26: Set in the evaluation contract, or deferred to a documented pilot with Joaa's agreement. | Y26: Q-J20 | Z26: USER-DECISION | AB26: DEC+DATA | AC26: n/a (sub-item) | AD26: NEW (repo sweep) | AE26: 2026-10-19 | AF26: v4-02 notes 3-4; EXT-0084 | AH26: No | AJ26: repo: v4-02 / v3-04 section 5 / v2-05 section 3 | AK26: RA4 | AL26: S08
A27: C-D08/CORESWEEP | B27: Core-size sweep points and models / catalogue sizes | C27: OPEN | D27: =IFERROR(INDEX(Lists!$B$2:$B$14,MATCH(C27,Lists!$A$2:$A$14,0)),"?") | E27: =IF(COUNTIFS(Links!$B$2:$B$600,A27,Links!$E$2:$E$600,"Yes")>0,"REVISE","") | F27: =COUNTIFS(Links!$B$2:$B$600,A27,Links!$D$2:$D$600,"No",Links!$C$2:$C$600,"<>INFORMS") | G27: DESK-ANALYSIS | H27: K5 Evaluation contract | I27: G1 Before any implementation | J27: High | K27: 55 | L27: W2 Desk work (no model runs) | M27: S09 | N27: Joaa + you (or a documented pilot) | O27: Lead computes or writes it (no model runs) | P27: No | Q27: Parameter | R27: Sub-item | S27: C-D08 | T27: Core-size sweep points, the catalogue sizes and the model set are unset. | U27: Unset. | V27: Set in the evaluation contract, or deferred to a documented pilot with Joaa's agreement. | Y27: Q-J21 | Z27: DESK-ANALYSIS | AB27: DEC+DATA | AC27: n/a (sub-item) | AD27: NEW (repo sweep) | AE27: 2026-10-19 | AF27: v4-02 header ('unset') | AH27: No | AJ27: repo: v4-02 / v3-04 section 5 / v2-05 section 3 | AK27: v1-A9 | AL27: S08
A28: C-D08/EC1 | B28: Unit of analysis, eligible tasks, models/provider/client versions, repeats | C28: PARTLY ANSWERED | D28: =IFERROR(INDEX(Lists!$B$2:$B$14,MATCH(C28,Lists!$A$2:$A$14,0)),"?") | E28: =IF(COUNTIFS(Links!$B$2:$B$600,A28,Links!$E$2:$E$600,"Yes")>0,"REVISE","") | F28: =COUNTIFS(Links!$B$2:$B$600,A28,Links!$D$2:$D$600,"No",Links!$C$2:$C$600,"<>INFORMS") | G28: DESK-ANALYSIS | H28: K5 Evaluation contract | I28: G1 Before any implementation | J28: High | K28: 57 | L28: W2 Desk work (no model runs) | M28: S09 | N28: Lead drafts; Joaa/you approve | O28: At implementation | P28: Partly | Q28: Contract element | R28: Sub-item | S28: C-D08 | T28: SRC-12 Phase 2: the unit of analysis (turn or complete trajectory), eligible tasks, models, provider and client versions and repeats are not fixed. | U28: Complete trajectories are the working unit; models, providers, repeats unset. 2026-10-21 (AUTH-018): requirements now in his words: 'multiple different goals for your agent ... multiple different settings and also run all the same settings multiple time to ... show the statistical variance' (INT-T-002 L441-L443); any kind of agent (L345-L354); start small, about 20 samples (INT-T-004 E749); the human: several models through a free university API (REQ-U21-01). 2026-10-21 (AUTH-019, the human's decisions): models and providers are chosen when implementing ('we will get the model list when we start implementing doesnt matter for now', line 9); session patterns: one long run and returning users (line 14). | V28: Written in the evaluation contract. | Y28: Q-J04, Q-J21, Q-J24, Q-J25 | Z28: JOAA-DECISION, USER-DECISION | AB28: DEC+DATA | AC28: n/a (sub-item) | AD28: NEW (SRC-12) | AE28: 2026-10-21 | AF28: INT-T-005 (requirements/intake/2026-10-21-user-decisions-after-meetings.md) | AH28: No | AJ28: SRC-12 Phase 2 | AK28: SRC-12 Phase 2 bullet 1, A12 | AL28: S08
A29: C-D08/EC2 | B29: Success/failure, argument-error and no-call outcomes: definitions and adjudication | C29: OPEN | D29: =IFERROR(INDEX(Lists!$B$2:$B$14,MATCH(C29,Lists!$A$2:$A$14,0)),"?") | E29: =IF(COUNTIFS(Links!$B$2:$B$600,A29,Links!$E$2:$E$600,"Yes")>0,"REVISE","") | F29: =COUNTIFS(Links!$B$2:$B$600,A29,Links!$D$2:$D$600,"No",Links!$C$2:$C$600,"<>INFORMS") | G29: DESK-ANALYSIS | H29: K5 Evaluation contract | I29: G1 Before any implementation | J29: High | K29: 58 | L29: W2 Desk work (no model runs) | M29: S09 | N29: Lead drafts; Joaa/you approve | O29: Lead computes or writes it (no model runs) | P29: Partly | Q29: Contract element | R29: Sub-item | S29: C-D08 | T29: SRC-12 Phase 2: how success, failure, argument errors and no-call outcomes are defined and adjudicated. | U29: One scorer required (E2); outcome splits not specified. | V29: Written in the evaluation contract. | Y29: Q-J20 | Z29: JOAA-DECISION, USER-DECISION | AB29: DEC+DATA | AC29: n/a (sub-item) | AD29: NEW (SRC-12) | AE29: 2026-10-19 | AF29: v4-02 (one scorer); C-S09 | AH29: No | AJ29: SRC-12 Phase 2 | AK29: SRC-12 Phase 2 bullet 2 | AL29: S08
A30: C-D08/EC3 | B30: Exposure levels and allowed discovery / re-addition behaviour | C30: OPEN | D30: =IFERROR(INDEX(Lists!$B$2:$B$14,MATCH(C30,Lists!$A$2:$A$14,0)),"?") | E30: =IF(COUNTIFS(Links!$B$2:$B$600,A30,Links!$E$2:$E$600,"Yes")>0,"REVISE","") | F30: =COUNTIFS(Links!$B$2:$B$600,A30,Links!$D$2:$D$600,"No",Links!$C$2:$C$600,"<>INFORMS") | G30: DESK-ANALYSIS | H30: K5 Evaluation contract | I30: G1 Before any implementation | J30: High | K30: 59 | L30: W2 Desk work (no model runs) | M30: S09 | N30: Lead drafts; Joaa/you approve | O30: Lead computes or writes it (no model runs) | P30: Partly | Q30: Contract element | R30: Sub-item | S30: C-D08 | T30: SRC-12 Phase 2: the exposure levels and the discovery or re-addition behaviour allowed in each arm. | U30: Figure 1 expresses the configurations; exposure levels (named-only/compact/full) not fixed. | V30: Written in the evaluation contract. | Y30: Q-J12 | Z30: JOAA-DECISION, USER-DECISION | AB30: DEC+DATA | AC30: n/a (sub-item) | AD30: NEW (SRC-12) | AE30: 2026-10-19 | AF30: v4-02 Figure 1 and arm table | AH30: No | AJ30: SRC-12 Phase 2 | AK30: SRC-12 Phase 2 bullet 3 | AL30: S08
A31: C-D08/EC4 | B31: Reference arm(s), substitute reference, margin, strata, minimum counts | C31: OPEN | D31: =IFERROR(INDEX(Lists!$B$2:$B$14,MATCH(C31,Lists!$A$2:$A$14,0)),"?") | E31: =IF(COUNTIFS(Links!$B$2:$B$600,A31,Links!$E$2:$E$600,"Yes")>0,"REVISE","") | F31: =COUNTIFS(Links!$B$2:$B$600,A31,Links!$D$2:$D$600,"No",Links!$C$2:$C$600,"<>INFORMS") | G31: DESK-ANALYSIS | H31: K5 Evaluation contract | I31: G1 Before any implementation | J31: High | K31: 60 | L31: W2 Desk work (no model runs) | M31: S09 | N31: Lead drafts; Joaa/you approve | O31: Lead computes or writes it (no model runs) | P31: Partly | Q31: Contract element | R31: Sub-item | S31: C-D08 | T31: SRC-12 Phase 2: reference arm(s), any substitute reference, success margin, strata and minimum counts. | U31: Reference ladder defined; margin, strata, counts unset. | V31: Written in the evaluation contract. | Y31: Q-J20 | Z31: JOAA-DECISION, USER-DECISION | AB31: DEC+DATA | AC31: n/a (sub-item) | AD31: NEW (SRC-12) | AE31: 2026-10-19 | AF31: v4-02 sections 4, 6, 7 | AH31: No | AJ31: SRC-12 Phase 2 | AK31: SRC-12 Phase 2 bullet 4 | AL31: S08
A32: C-D08/EC5 | B32: Accounting: input tokens, cached/billed cost, latency, offline selection cost | C32: PARTLY ANSWERED | D32: =IFERROR(INDEX(Lists!$B$2:$B$14,MATCH(C32,Lists!$A$2:$A$14,0)),"?") | E32: =IF(COUNTIFS(Links!$B$2:$B$600,A32,Links!$E$2:$E$600,"Yes")>0,"REVISE","") | F32: =COUNTIFS(Links!$B$2:$B$600,A32,Links!$D$2:$D$600,"No",Links!$C$2:$C$600,"<>INFORMS") | G32: DESK-ANALYSIS | H32: K5 Evaluation contract | I32: G1 Before any implementation | J32: High | K32: 61 | L32: W2 Desk work (no model runs) | M32: S09 | N32: Lead drafts; Joaa/you approve | O32: Adopt the equation (N-30) into the contract | P32: Partly | Q32: Contract element | R32: Sub-item | S32: C-D08 | T32: SRC-12 Phase 2: input-token accounting, cached and billed cost, latency and offline selection cost (separate columns if the objective is undecided). | U32: Tokens are the working criterion; bill recorded separately; latency is not in any criterion. 2026-10-21 (AUTH-018): money cost per turn, tokens and response time, averaged over turns (INT-T-002 L275, L302, L354); filtering cost counts (INT-T-004 E230-E232). 2026-10-21 (AUTH-019, the human's decisions): accounting = the bill on average over turns and sessions with its components (C-D02 closed); the canonical equation is being drafted (N-30). | V32: Written in the evaluation contract. | Y32: Q-J03 | Z32: JOAA-DECISION, USER-DECISION | AB32: DEC+DATA | AC32: n/a (sub-item) | AD32: NEW (SRC-12) | AE32: 2026-10-21 | AF32: INT-T-005 (requirements/intake/2026-10-21-user-decisions-after-meetings.md) | AH32: No | AJ32: SRC-12 Phase 2 | AK32: SRC-12 Phase 2 bullet 5 | AL32: S08
A33: C-D08/EC6 | B33: Analysis plan, stopping rule, uncertainty intervals, exclusions, large-catalogue claim boundary | C33: PARTLY ANSWERED | D33: =IFERROR(INDEX(Lists!$B$2:$B$14,MATCH(C33,Lists!$A$2:$A$14,0)),"?") | E33: =IF(COUNTIFS(Links!$B$2:$B$600,A33,Links!$E$2:$E$600,"Yes")>0,"REVISE","") | F33: =COUNTIFS(Links!$B$2:$B$600,A33,Links!$D$2:$D$600,"No",Links!$C$2:$C$600,"<>INFORMS") | G33: DESK-ANALYSIS | H33: K5 Evaluation contract | I33: G1 Before any implementation | J33: High | K33: 62 | L33: W2 Desk work (no model runs) | M33: S09 | N33: Lead drafts; Joaa/you approve | O33: Write the analysis plan | P33: Partly | Q33: Contract element | R33: Sub-item | S33: C-D08 | T33: SRC-12 Phase 2: analysis plan, stopping rule, intervals, exclusions and the large-catalogue claim boundary. | U33: Decision rule S5A and Figure 2 exist; stopping rule and exclusions unspecified. 2026-10-21 (AUTH-018): repeated runs per setting to show statistical variance (INT-T-002 L441-L443); averaging over turns with failing turns allowed (L302-L320). | V33: Written in the evaluation contract. | Y33: Q-J20 | Z33: JOAA-DECISION, USER-DECISION | AB33: DEC+DATA | AC33: n/a (sub-item) | AD33: NEW (SRC-12) | AE33: 2026-10-21 | AF33: INT-T-002 (requirements/intake/2026-10-21-supervisor-meeting-2026-10-21-notes-and-transcript.md); mapping design/ledger/notes/MEETINGS-MAPPING-20261021.md checked line by line by FND-0035 and FND-0036; REGISTER section H | AH33: No | AJ33: SRC-12 Phase 2 | AK33: SRC-12 Phase 2 bullet 6 | AL33: S08
A34: C-D08/GATEWAY | B34: Does a code-mediated or gateway path count as exposure / must it be a baseline arm? | C34: PARTLY ANSWERED | D34: =IFERROR(INDEX(Lists!$B$2:$B$14,MATCH(C34,Lists!$A$2:$A$14,0)),"?") | E34: =IF(COUNTIFS(Links!$B$2:$B$600,A34,Links!$E$2:$E$600,"Yes")>0,"REVISE","") | F34: =COUNTIFS(Links!$B$2:$B$600,A34,Links!$D$2:$D$600,"No",Links!$C$2:$C$600,"<>INFORMS") | G34: JOAA-DECISION | H34: K5 Evaluation contract | I34: G1 Before any implementation | J34: High | K34: 65 | L34: W2 Desk work (no model runs) | M34: S09 | N34: Joaa + you (or a documented pilot) | O34: Write into the contract | P34: No | Q34: Parameter | R34: Sub-item | S34: C-D08 | T34: Whether the existing code-mediated project (and gateways) is a baseline arm or an exposure policy is unset (brief Q6). | U34: Unset. 2026-10-21 (AUTH-018): Executor is a required baseline: 'download this run this and figure out okay benchmark it ... This is your baseline. You should have multiple baselines' (INT-T-004 E622-E626); whether a code-mediated path 'counts as exposure' is not discussed. The human added on 21 October: 'executor doesnot have to be locked i am using an API free from my university and it offer bunch of different AI models' (REQ-U21-01). | V34: Set in the evaluation contract, or deferred to a documented pilot with Joaa's agreement. | Y34: Q-J16 | Z34: DESK-ANALYSIS | AB34: DEC+DATA | AC34: n/a (sub-item) | AD34: NEW (repo sweep) | AE34: 2026-10-21 | AF34: INT-T-004 (requirements/intake/2026-10-21-supervisor-meeting-2026-10-02-excerpts.md); ops/AUTHORIZATIONS.md (AUTH-018); mapping design/ledger/notes/MEETINGS-MAPPING-20261021.md checked line by line by FND-0035 and FND-0036; REGISTER section H | AH34: No | AJ34: repo: v4-02 / v3-04 section 5 / v2-05 section 3 | AK34: v4-01 Q6 | AL34: S08
A35: C-D08/HIER | B35: Navigated hierarchy: source of the hierarchy and budget unit | C35: OPEN | D35: =IFERROR(INDEX(Lists!$B$2:$B$14,MATCH(C35,Lists!$A$2:$A$14,0)),"?") | E35: =IF(COUNTIFS(Links!$B$2:$B$600,A35,Links!$E$2:$E$600,"Yes")>0,"REVISE","") | F35: =COUNTIFS(Links!$B$2:$B$600,A35,Links!$D$2:$D$600,"No",Links!$C$2:$C$600,"<>INFORMS") | G35: DESK-ANALYSIS | H35: K5 Evaluation contract | I35: G1 Before any implementation | J35: High | K35: 66 | L35: W2 Desk work (no model runs) | M35: S09 | N35: Joaa + you (or a documented pilot) | O35: Lead computes or writes it (no model runs) | P35: No | Q35: Parameter | R35: Sub-item | S35: C-D08 | T35: The source of the hierarchy (catalogue's own structure or derived) and the budget unit (one level = one discovery) are unset; untested above 400 tools. | U35: Unset. | V35: Set in the evaluation contract, or deferred to a documented pilot with Joaa's agreement. | Y35: Q-J20 | Z35: DESK-ANALYSIS | AB35: DEC+DATA | AC35: n/a (sub-item) | AD35: NEW (repo sweep) | AE35: 2026-10-19 | AF35: v4-02 section 5 | AH35: No | AJ35: repo: v4-02 / v3-04 section 5 / v2-05 section 3 | AL35: S08
A36: C-D08/KAPPA | B36: Search width kappa | C36: OPEN | D36: =IFERROR(INDEX(Lists!$B$2:$B$14,MATCH(C36,Lists!$A$2:$A$14,0)),"?") | E36: =IF(COUNTIFS(Links!$B$2:$B$600,A36,Links!$E$2:$E$600,"Yes")>0,"REVISE","") | F36: =COUNTIFS(Links!$B$2:$B$600,A36,Links!$D$2:$D$600,"No",Links!$C$2:$C$600,"<>INFORMS") | G36: DESK-ANALYSIS | H36: K5 Evaluation contract | I36: G1 Before any implementation | J36: High | K36: 67 | L36: W2 Desk work (no model runs) | M36: S09 | N36: Joaa + you (or a documented pilot) | O36: Lead computes or writes it (no model runs) | P36: No | Q36: Parameter | R36: Sub-item | S36: C-D08 | T36: The top-kappa search width is unset. | U36: Unset. | V36: Set in the evaluation contract, or deferred to a documented pilot with Joaa's agreement. | Y36: Q-J20 | Z36: JOAA-DECISION | AB36: DEC+DATA | AC36: n/a (sub-item) | AD36: NEW (repo sweep) | AE36: 2026-10-19 | AF36: v4-02 header ('unset') | AH36: No | AJ36: repo: v4-02 / v3-04 section 5 / v2-05 section 3 | AK36: kappa | AL36: S08
A37: C-D08/RANKER | B37: Ranker / selector type and disclosure-grade set | C37: OPEN | D37: =IFERROR(INDEX(Lists!$B$2:$B$14,MATCH(C37,Lists!$A$2:$A$14,0)),"?") | E37: =IF(COUNTIFS(Links!$B$2:$B$600,A37,Links!$E$2:$E$600,"Yes")>0,"REVISE","") | F37: =COUNTIFS(Links!$B$2:$B$600,A37,Links!$D$2:$D$600,"No",Links!$C$2:$C$600,"<>INFORMS") | G37: DESK-ANALYSIS | H37: K5 Evaluation contract | I37: G1 Before any implementation | J37: High | K37: 68 | L37: W2 Desk work (no model runs) | M37: S09 | N37: Joaa + you (or a documented pilot) | O37: Lead computes or writes it (no model runs) | P37: No | Q37: Parameter | R37: Sub-item | S37: C-D08 | T37: The ranker type, the selector type and the set of disclosure grades are unset. | U37: Unset. | V37: Set in the evaluation contract, or deferred to a documented pilot with Joaa's agreement. | Y37: Q-J20 | Z37: DESK-ANALYSIS | AB37: DEC+DATA | AC37: n/a (sub-item) | AD37: NEW (repo sweep) | AE37: 2026-10-19 | AF37: v4-02 header ('unset') | AH37: No | AJ37: repo: v4-02 / v3-04 section 5 / v2-05 section 3 | AK37: v1-A9 | AL37: S08
A38: C-D08/SCOPESTMT | B38: Scope-statement and interface-contract wording; statement ladder wordings | C38: OPEN | D38: =IFERROR(INDEX(Lists!$B$2:$B$14,MATCH(C38,Lists!$A$2:$A$14,0)),"?") | E38: =IF(COUNTIFS(Links!$B$2:$B$600,A38,Links!$E$2:$E$600,"Yes")>0,"REVISE","") | F38: =COUNTIFS(Links!$B$2:$B$600,A38,Links!$D$2:$D$600,"No",Links!$C$2:$C$600,"<>INFORMS") | G38: DESK-ANALYSIS | H38: K5 Evaluation contract | I38: G1 Before any implementation | J38: High | K38: 69 | L38: W2 Desk work (no model runs) | M38: S09 | N38: Joaa + you (or a documented pilot) | O38: Lead computes or writes it (no model runs) | P38: No | Q38: Parameter | R38: Sub-item | S38: C-D08 | T38: The wording of the metadata-only scope statement, the interface contract and the statement ladder (generic, catalogue-specific, existence hint) is unset; a catalogue-specific statement partly exposes the catalogue. | U38: Unset. | V38: Set in the evaluation contract, or deferred to a documented pilot with Joaa's agreement. | Y38: Q-J20 | Z38: DESK-ANALYSIS | AB38: DEC+DATA | AC38: n/a (sub-item) | AD38: NEW (repo sweep) | AE38: 2026-10-19 | AF38: v4-05 section 2 item 3; CH-0062 | AH38: No | AJ38: repo: v4-02 / v3-04 section 5 / v2-05 section 3 | AK38: CH-0062, RA6 | AL38: S08
A39: C-D08/STRATA | B39: Strata and minimum stratum size (and source of strata annotations) | C39: DEFERRED | D39: =IFERROR(INDEX(Lists!$B$2:$B$14,MATCH(C39,Lists!$A$2:$A$14,0)),"?") | E39: =IF(COUNTIFS(Links!$B$2:$B$600,A39,Links!$E$2:$E$600,"Yes")>0,"REVISE","") | F39: =COUNTIFS(Links!$B$2:$B$600,A39,Links!$D$2:$D$600,"No",Links!$C$2:$C$600,"<>INFORMS") | G39: JOAA-DECISION | H39: K5 Evaluation contract | I39: G1 Before any implementation | J39: High | K39: 70 | L39: W2 Desk work (no model runs) | M39: S09 | N39: Joaa + you (or a documented pilot) | O39: none until the trigger fires | P39: No | Q39: Parameter | R39: Sub-item | S39: C-D08 | T39: Strata, the minimum stratum size and the source of strata annotations are unset (CH-0038 residual). | U39: Unset. 2026-10-21 (AUTH-019, the human's decisions): deferred to the end-to-end phase: the human's process is research and a drafted policy, then proof-of-concept tests of parts in a loop ('not rigirous tests or full tests'), then an end-to-end study and final findings (INT-T-005 (requirements/intake/2026-10-21-user-decisions-after-meetings.md) line 7); error control, strata and the selection procedure's error rates belong to that last phase. | V39: Set in the evaluation contract, or deferred to a documented pilot with Joaa's agreement. | Y39: Q-J14, Q-J20 | Z39: DESK-ANALYSIS | AB39: DEC+DATA | AC39: n/a (sub-item) | AD39: NEW (repo sweep) | AE39: 2026-10-21 | AF39: INT-T-005 (requirements/intake/2026-10-21-user-decisions-after-meetings.md) | AG39: The end-to-end study is designed | AH39: No | AJ39: repo: v4-02 / v3-04 section 5 / v2-05 section 3 | AK39: strata | AL39: S08
A40: C-D08/TOK | B40: Tokenizer convention | C40: OPEN | D40: =IFERROR(INDEX(Lists!$B$2:$B$14,MATCH(C40,Lists!$A$2:$A$14,0)),"?") | E40: =IF(COUNTIFS(Links!$B$2:$B$600,A40,Links!$E$2:$E$600,"Yes")>0,"REVISE","") | F40: =COUNTIFS(Links!$B$2:$B$600,A40,Links!$D$2:$D$600,"No",Links!$C$2:$C$600,"<>INFORMS") | G40: DESK-ANALYSIS | H40: K5 Evaluation contract | I40: G1 Before any implementation | J40: High | K40: 71 | L40: W2 Desk work (no model runs) | M40: S09 | N40: Joaa + you (or a documented pilot) | O40: Lead computes or writes it (no model runs) | P40: No | Q40: Parameter | R40: Sub-item | S40: C-D08 | T40: The tokenizer or usage-field convention (provider-reported vs own tokenizer) is unset. | U40: Unset. | V40: Set in the evaluation contract, or deferred to a documented pilot with Joaa's agreement. | Y40: Q-J03 | Z40: JOAA-DECISION | AB40: DEC+DATA | AC40: n/a (sub-item) | AD40: NEW (repo sweep) | AE40: 2026-10-19 | AF40: v4-02 header ('unset') | AH40: No | AJ40: repo: v4-02 / v3-04 section 5 / v2-05 section 3 | AK40: tokenizer | AL40: S08
A41: N-30 | B41: Canonical billing equation of turns and sessions (model-agnostic components) | C41: PARTLY ANSWERED | D41: =IFERROR(INDEX(Lists!$B$2:$B$14,MATCH(C41,Lists!$A$2:$A$14,0)),"?") | E41: =IF(COUNTIFS(Links!$B$2:$B$600,A41,Links!$E$2:$E$600,"Yes")>0,"REVISE","") | F41: =COUNTIFS(Links!$B$2:$B$600,A41,Links!$D$2:$D$600,"No",Links!$C$2:$C$600,"<>INFORMS") | G41: DESK-ANALYSIS | H41: K5 Evaluation contract | I41: G1 Before any implementation | J41: High | K41: 72 | L41: W2 Desk work (no model runs) | M41: S09 | N41: Lead + steward; you approve | O41: Your approval of DPR-0006 (proposed); then the first billing probe | P41: Yes - stored text, unread | Q41: Parameter | R41: Item | T41: The human asked for the canonical parts of the billing equation of turns and sessions, not tied to one model: input, reasoning, output, tools, prompt caching (possibly used as conversation memory at first), averaged over turns and sessions (INT-T-005 line 8). | U41: The stored provider pages cover the components (EXT-0085, EXT-0086, EXT-0089, EXT-0115, EXT-0123, EXT-0150, EXT-0152, EXT-0158, EXT-0183 and the 2026-10-19 rechecks). 2026-10-21 (AUTH-019): drafted as design/proposals/DPR-0006.md (proposed): per request C_r = p·[F_r + w·W_r + ρ·R_r + κ·(O_r + H_r)]·m_r + T_r; per session B_s = Σ C_r + storage S_s + session-time charges X_s; objective = mean bill per turn over all sessions, accuracy beside it, no margin; gap cost after a cache lifetime follows from the lifetime rules; components from FND-0039 (findings/SUM-0041), which leaves open: reasoning-token billing at Anthropic and OpenAI, Gemini explicit-cache lifetime and write fee, Bedrock multipliers, Anthropic cross-session sharing. Under review (RV-0020). 2026-10-21 (AUTH-019): reviewed by the design-challenger (RV-0020: 1 high, 9 medium, 6 low defects, nothing withdrawn) and corrected in DPR-0006: a price table per component, tier and mode replaces the single multiplier; cache writes split into 5-minute and 1-hour classes; reasoning tokens priced inside billed output only; the session sum covers requests outside turns (prewarm, memory writing, keep-alive); container time counted once (X_s); free allowances reported apart; gap cost p·P·(c_cold − ρ) stated as a consequence already inside W and R; primary figure (ratio of sums per turn) marked as the lead's [I] with the per-session mean as the alternative. Still open: reasoning-token billing at Anthropic and OpenAI, whether OpenAI's usage record separates cache writes, Gemini cache lifetimes and write fee (checked by the first billing probe, C-X07). | V5 2026-10-25: the headline averaging is decided: total bill over total turns, with the mean of per-session rates beside it (REQ-U22-08); DPR-0006 approval still the human's | V41: A drafted equation with every component cited per provider, reviewed, and approved by the human. | AB41: SOURCE | AC41: n/a (new) | AD41: NEW (the human's decision 2026-10-21) | AE41: 2026-10-25 | AF41: design/proposals/DPR-0006.md; reviews/RV-0020.md; FND-0039 | AH41: No (AUTH-019) | AJ41: INT-T-005 line 8 | AL41: S08
A42: C-D08 | B42: Arms and baselines (incl. | C42: PARTLY ANSWERED | D42: =IFERROR(INDEX(Lists!$B$2:$B$14,MATCH(C42,Lists!$A$2:$A$14,0)),"?") | E42: =IF(COUNTIFS(Links!$B$2:$B$600,A42,Links!$E$2:$E$600,"Yes")>0,"REVISE","") | F42: =COUNTIFS(Links!$B$2:$B$600,A42,Links!$D$2:$D$600,"No",Links!$C$2:$C$600,"<>INFORMS") | G42: JOAA-DECISION | H42: K5 Evaluation contract | I42: G1 Before any implementation | J42: High | K42: 73 | L42: W2 Desk work (no model runs) | M42: S09 | N42: Joaa + you | O42: Ask Joaa (Q-J01, Q-J16, Q-J20, Q-U06) | P42: Partly | Q42: Decision | R42: Item | T42: Arms and baselines (incl. who or what 'Executor' is), maintained-performance margin, alpha, strata, N_dep, epsilon, tokenizer, ranker, search budget are unset. | U42: v4 added the navigated-hierarchy arm; parameters still unset. 'Executor as named baseline' is a researcher identification, not transcript text. Arms and baselines are G1; numeric parameters are G3. | V42: Arm table and comparison contract fixed in writing; unset numbers deferred to a pilot only with Joaa's agreement. | W42: C-D01, C-D02, C-D03, C-D05 | X42: C-D11 | Y42: Q-J01, Q-J16, Q-J20, Q-U06, Q-J30 | Z42: USER-DECISION, DESK-ANALYSIS | AA42: K11 End-to-end comparison | AB42: DEC+DATA | AC42: PARTLY ANSWERED - OPEN | AD42: UNCHANGED | AE42: 2026-10-19 | AF42: v4-02 sections 5-7; CAVEATS row 6 | AH42: No | AJ42: SRC-11 canonical | AK42: SRC-06 D10, SRC-06 D11, v1-A9, v3-04 section 5 | AL42: S08
A43: C-E05 | B43: Provider prices and implementation change; the repo's price evidence is dated 2026-10-11 (SRC-11 reports a ... | C43: PARTLY ANSWERED | D43: =IFERROR(INDEX(Lists!$B$2:$B$14,MATCH(C43,Lists!$A$2:$A$14,0)),"?") | E43: =IF(COUNTIFS(Links!$B$2:$B$600,A43,Links!$E$2:$E$600,"Yes")>0,"REVISE","") | F43: =COUNTIFS(Links!$B$2:$B$600,A43,Links!$D$2:$D$600,"No",Links!$C$2:$C$600,"<>INFORMS") | G43: TIME-RECHECK | H43: K15 Expiring provider facts | I43: G2 Before the affected pilot/arm | J43: High | K43: 76 | L43: W2 Desk work (no model runs) | M43: S10 | N43: Lead (web) with a dated table | O43: Recheck at claim time | P43: Partly | Q43: Source check | R43: Item | T43: Provider prices and implementation change; the repo's price evidence is dated 2026-10-11 (SRC-11 reports a 17-18 Oct check). | U43: Rechecked 2026-10-19 (pages stored as price-anthropic-20261019, price-openai-20261019, price-gemini-20261019 in evidence/literature-20261019/, compared with the 2026-10-11 copies): Anthropic multipliers unchanged (5-minute write 1.25x, 1-hour write 2x, read 0.1x; 0.05x on Opus 5.5 and Sonnet 5.5; 0.025x on Fable 5.1 and Mythos 5.1) and its worked examples now use Opus 5.5 ($4 input, $20 output, 0.05x reads); the OpenAI pricing page is unchanged apart from HTML anchors (similarity 0.997); Gemini storage price unchanged ($0.50 per million tokens per hour through 2026, $1.00 from 2027-01-01), and the page now lists a new model, Gemini 4 Argon, marked 'Implicit caching only (explicit caching is not supported)', plus a Contributor Tier note. The comparison is a text diff by the lead after stripping markup. What remains: repeat the check at the time any current-price claim is written; prices and models move. | V43: A dated price table now (before Pilot A); repeat at step S24 before any current-price claim, because prices expire. | W43: N-5, C-D02 | Y43: Q-J03, Q-J24, Q-U21 | Z43: SOURCE-REREAD | AA43: K9 Cache & billing | AB43: TIME+SOURCE | AC43: BOUNDARY - OPEN | AD43: UNCHANGED | AE43: 2026-10-19 | AF43: evidence/literature-20261019/price-*-20261019 and MANIFEST.jsonl (the manifest's 'auth' field says AUTH-013 because the pinned fetch helper hard-codes it; the fetch was made under AUTH-016); EXT-0085, EXT-0086, EXT-0089 | AG43: Before any current-price claim, and whenever a provider/model is chosen or the bill becomes the objective | AH43: No (AUTH-016 covers web fetches for this item) | AJ43: SRC-11 canonical | AK43: SRC-07 31 | AL43: S10
A44: C-E01 | B44: Ten disputed or unverified paper/vendor claims and propagation defects (e.g., the 292K flat-catalogue figure). | C44: PARTLY ANSWERED | D44: =IFERROR(INDEX(Lists!$B$2:$B$14,MATCH(C44,Lists!$A$2:$A$14,0)),"?") | E44: =IF(COUNTIFS(Links!$B$2:$B$600,A44,Links!$E$2:$E$600,"Yes")>0,"REVISE","") | F44: =COUNTIFS(Links!$B$2:$B$600,A44,Links!$D$2:$D$600,"No",Links!$C$2:$C$600,"<>INFORMS") | G44: SOURCE-REREAD | H44: K14 Source & vendor verification | I44: G4 Before claims | J44: Normal | K44: 78 | L44: W2 Desk work (no model runs) | M44: S11 | N44: Lead + steward (authors for table conflicts) | O44: Read the stored text first (tools/origin_extract.py) | P44: Yes - stored text, unread | Q44: Source check | R44: Item | T44: Ten disputed or unverified paper/vendor claims and propagation defects (e.g., the 292K flat-catalogue figure). | U44: One sub-claim (292K figure) traced to the benchmark repo's development document, not the paper (v4-03 section 2); the others concern the Phase 1 dossier outside the repo. | V44: Original versions/tables opened; derivative claims corrected; unreplicable vendor data labelled. | X44: C-D01, C-D08 | Z44: AUTHOR-OR-VENDOR, RECORDS-AT-HAND | AB44: SOURCE+RECORD+AUTHOR | AC44: OPEN | AD44: NARROWED | AE44: 2026-10-19 | AF44: v4-03 section 2; EXT-0084 | AH44: No (AUTH-016 covers web fetches for this item) | AJ44: SRC-11 canonical | AK44: SRC-06 E01-E10 | AL44: S11
A45: C-E01/E02 | B45: Toollery replay library, selector comparability, pricing protocol unstated | C45: NOT LOCATED | D45: =IFERROR(INDEX(Lists!$B$2:$B$14,MATCH(C45,Lists!$A$2:$A$14,0)),"?") | E45: =IF(COUNTIFS(Links!$B$2:$B$600,A45,Links!$E$2:$E$600,"Yes")>0,"REVISE","") | F45: =COUNTIFS(Links!$B$2:$B$600,A45,Links!$D$2:$D$600,"No",Links!$C$2:$C$600,"<>INFORMS") | G45: AUTHOR-OR-VENDOR | H45: K14 Source & vendor verification | I45: G4 Before claims | J45: Normal | K45: 81 | L45: W2 Desk work (no model runs) | M45: S11 | N45: Authors | O45: You send the drafted ask (design/ledger/notes/AUTHOR-ASKS-DRAFT-20261020.md, section 4) and record the reply; until then it waits on the authors | P45: Partly | Q45: Source check | R45: Sub-item | S45: C-E01 | T45: SRC-06 E02: Toollery's replay library, selector comparability and pricing protocol are unstated in the stored text. | U45: The repo confirms the stored text lacks them; the fitted multiplier is treated as study-specific. | V45: Authors answer, or 'not provided' recorded and the number labelled study-specific. | AB45: SOURCE+AUTHOR | AC45: n/a (sub-item) | AD45: NEW (SRC-11 sub-row) | AE45: 2026-10-20 | AF45: v3-01 section 5: 'the model, pricing and candidate-list construction are not in the stored text'; sources.json s4b-wd-toollery | AH45: No (AUTH-016 covers web fetches for this item) | AJ45: SRC-11 section D1 | AK45: SRC-06 E02 | AL45: S11
A46: C-E01/E05 | B46: Did the earlier body use the MCP-Bench distractor-server result? | C46: OPEN | D46: =IFERROR(INDEX(Lists!$B$2:$B$14,MATCH(C46,Lists!$A$2:$A$14,0)),"?") | E46: =IF(COUNTIFS(Links!$B$2:$B$600,A46,Links!$E$2:$E$600,"Yes")>0,"REVISE","") | F46: =COUNTIFS(Links!$B$2:$B$600,A46,Links!$D$2:$D$600,"No",Links!$C$2:$C$600,"<>INFORMS") | G46: RECORDS-AT-HAND | H46: K14 Source & vendor verification | I46: G4 Before claims | J46: Normal | K46: 84 | L46: W2 Desk work (no model runs) | M46: S11 | N46: You (Phase 1 records) | O46: Lead drafts the fix; you approve | P46: No | Q46: Source check | R46: Sub-item | S46: C-E01 | T46: SRC-06 E05: unknown whether the earlier body incorporated the MCP-Bench distractor-server result (audit-history question). | U46: Outside the repo. | V46: Original record and paper checked; audit-history recorded. | AB46: RECORD+SOURCE | AC46: n/a (sub-item) | AD46: NEW (SRC-11 sub-row) | AE46: 2026-10-19 | AF46: Concerns the independent Phase 1 body (outside repo); r3-mcpbench is stored | AH46: No (AUTH-016 covers web fetches for this item) | AJ46: SRC-11 section D1 | AK46: SRC-06 E05 | AL46: S11
A47: C-E01/E08 | B47: CAPC lazy-tools scope, ToolMenuBench sizes, ProMCP figures not fully verified | C47: DEFERRED | D47: =IFERROR(INDEX(Lists!$B$2:$B$14,MATCH(C47,Lists!$A$2:$A$14,0)),"?") | E47: =IF(COUNTIFS(Links!$B$2:$B$600,A47,Links!$E$2:$E$600,"Yes")>0,"REVISE","") | F47: =COUNTIFS(Links!$B$2:$B$600,A47,Links!$D$2:$D$600,"No",Links!$C$2:$C$600,"<>INFORMS") | G47: SOURCE-REREAD | H47: K14 Source & vendor verification | I47: G4 Before claims | J47: Normal | K47: 88 | L47: W2 Desk work (no model runs) | M47: S11 | N47: Lead + steward | O47: none until the trigger fires | P47: Partly | Q47: Source check | R47: Sub-item | S47: C-E01 | T47: SRC-06 E08: CAPC lazy-tools scope, ToolMenuBench sizes and ProMCP figures are not fully verified. | U47: ToolMenuBench and ProMCP rows were read by the steward/lead; CAPC is stored but unread. Batch 5: CAPC is Cache-Aware Prompt Compression (arXiv 2607.15516v1, Yan Song, PayPal; EXT-0193): query-agnostic compression with explicit cache_control and a tier-preserving ratio bound. It has no lazy-tools mechanism of its own in lines 1-1260; 'lazy tool catalog (USE_LAZY_TOOLS=True)' appears once, in the author's enterprise assistant, and the gap between the simulator's -51.7% and the production-path -45.5% is attributed to its lazy-tool-loading behaviour, with no description and no ablation (EXT-0191). Measured: 1,312-token system prompt plus 287 tool definitions 'totaling 93k tokens' (the text gives 71 + 217 = 288), 15 queries x 4 strategies, Sonnet 4.6 only, 5-minute TTL; Table 11 vanilla $5.55 / 85.7% hit rate against CAPC $3.03 / 99.1%; cache_read about 106k tokens per call after the first against a stated 94k prefix, unexplained; token-count method not stated. The only scope sentence is 'Query-agnostic compression preserves the full tool catalog uniformly'; it makes no claim about discovery, search, stubs or invisible tools. ToolMenuBench ranges outside 364-520 remain unread. Batch 9: ToolMenuBench was read in full (751 lines). Size: 26,460 executions = 7 settings x 7 models x 3 menu sizes x 6 methods x 30 tasks (arithmetic checks); menu sizes 25, 100, 250 tools; 'all tools' exposes the full registry (average 125.00 visible); keyword top-k ranks tools by lexical overlap of the task with name, description and optionally schema fields (k = 5 and 10). Table I (EXT-0207): all tools 32.1% (56,062 tokens), keyword top-5 22.1% (3,200 tokens), keyword top-10 22.4%, state-aware 24.0%, full causal path 24.0%, CMTF 85.7% (1,125 tokens); 53.6 points and 98% token figures check. The registry is 'synthetic but structured' and the environment a 'deterministic mocked tool environment'. Not stated: who wrote the tasks, registry and contracts; the number of distinct tasks (only 'thirty tasks for each condition'); the paper calls its CMTF contracts 'manually specified' and says the benefit 'depends on the availability and quality of tool contracts'. Tables II and III are ragged in the text. CAPC was read in batch 5; ProMCP rows were read earlier by a steward and the lead and not re-read in this batch. Deferred 2026-10-20 with reason and trigger: CAPC and ToolMenuBench were read (batches 5 and 9); the ProMCP rows are named in the live documents only in the notes that correct an earlier draft's misattribution (01 line 79, 03 lines 21 and 69), and no live sentence quotes a ProMCP figure. | V47: Each table/setting checked separately. | AB47: SOURCE | AC47: n/a (sub-item) | AD47: NEW (SRC-11 sub-row) | AE47: 2026-10-20 | AF47: grep of design/package-v3 and design/package-v4 01-05 (lead, 2026-10-20) | AG47: A document quotes a ProMCP figure | AH47: No (AUTH-016 covers web fetches for this item) | AJ47: SRC-11 section D1 | AK47: SRC-06 E08 | AL47: S11
A48: C-E01/E09 | B48: Frozen Copilot cache-hit row mixes serving and client telemetry | C48: OPEN | D48: =IFERROR(INDEX(Lists!$B$2:$B$14,MATCH(C48,Lists!$A$2:$A$14,0)),"?") | E48: =IF(COUNTIFS(Links!$B$2:$B$600,A48,Links!$E$2:$E$600,"Yes")>0,"REVISE","") | F48: =COUNTIFS(Links!$B$2:$B$600,A48,Links!$D$2:$D$600,"No",Links!$C$2:$C$600,"<>INFORMS") | G48: RECORDS-AT-HAND | H48: K14 Source & vendor verification | I48: G4 Before claims | J48: Normal | K48: 89 | L48: W2 Desk work (no model runs) | M48: S11 | N48: You | O48: Lead drafts the fix; you approve | P48: No | Q48: Source check | R48: Sub-item | S48: C-E01 | T48: SRC-06 E09: the frozen dossier's Copilot cache-hit row mixes serving and client telemetry; a correction exists elsewhere, not in the frozen record. | U48: Outside the repo. | V48: Dated correction issued alongside the frozen artefact. | AB48: RECORD+SOURCE | AC48: n/a (sub-item) | AD48: NEW (SRC-11 sub-row) | AE48: 2026-10-19 | AF48: Phase 1 dossier outside repo; stored s4-copilottraces-2608-00101 and r4-github-copilot-fewer-tools | AH48: No (AUTH-016 covers web fetches for this item) | AJ48: SRC-11 section D1 | AK48: SRC-06 E09 | AL48: S11
A49: C-E01/E10 | B49: Phase 1 frozen dossier retains later-contradicted claims | C49: OPEN | D49: =IFERROR(INDEX(Lists!$B$2:$B$14,MATCH(C49,Lists!$A$2:$A$14,0)),"?") | E49: =IF(COUNTIFS(Links!$B$2:$B$600,A49,Links!$E$2:$E$600,"Yes")>0,"REVISE","") | F49: =COUNTIFS(Links!$B$2:$B$600,A49,Links!$D$2:$D$600,"No",Links!$C$2:$C$600,"<>INFORMS") | G49: RECORDS-AT-HAND | H49: K14 Source & vendor verification | I49: G4 Before claims | J49: Normal | K49: 90 | L49: W2 Desk work (no model runs) | M49: S11 | N49: You | O49: Lead drafts the fix; you approve | P49: No | Q49: Source check | R49: Sub-item | S49: C-E01 | T49: SRC-06 E10: the frozen Phase 1 dossier retains claims later contradicted or unsupported (trajectory-only, caching, 56.7%, 85%, paraphrased 'verbatim' quotes, MCPVerse wording, version drift). | U49: Outside the repo. | V49: Explicit errata linked to each statement; frozen original preserved. | AB49: RECORD+SOURCE | AC49: n/a (sub-item) | AD49: NEW (SRC-11 sub-row) | AE49: 2026-10-19 | AF49: Outside repo | AH49: No (AUTH-016 covers web fetches for this item) | AJ49: SRC-11 section D1 | AK49: SRC-06 E10 | AL49: S11
A50: C-E02 | B50: Fifteen groups of unread, partial, snippet-only or unreadable sources; historical 'not found' searches were... | C50: PARTLY ANSWERED | D50: =IFERROR(INDEX(Lists!$B$2:$B$14,MATCH(C50,Lists!$A$2:$A$14,0)),"?") | E50: =IF(COUNTIFS(Links!$B$2:$B$600,A50,Links!$E$2:$E$600,"Yes")>0,"REVISE","") | F50: =COUNTIFS(Links!$B$2:$B$600,A50,Links!$D$2:$D$600,"No",Links!$C$2:$C$600,"<>INFORMS") | G50: SOURCE-REREAD | H50: K14 Source & vendor verification | I50: G4 Before claims | J50: Normal | K50: 91 | L50: W2 Desk work (no model runs) | M50: S11 | N50: Lead + steward | O50: E30 needs your list (Q-U23); UNREADLEADS in progress (memory survey read in batch 13); then close this item | P50: Yes - stored text, unread | Q50: Source check | R50: Item | T50: Fifteen groups of unread, partial, snippet-only or unreadable sources; historical 'not found' searches were bounded. | U50: E20, E22, E31 partly addressed (provider pages, BFCL data, MCP-Zero/ScaleMCP/MemTool bodies); others not touched. Batches 8-9 (2026-10-19): pivotal tables rendered and read (ComplexMCP, LiveMCPBench, token-reduction paper, ToolRet, MCPVerse v2 pages 5, 7, 9); MCP-Zero versions compared; scaffolding, ToolMenuBench, GIST-CMTF and the DynamicMCPBench code read; the non-pivotal papers are deferred with reason and trigger in C-E02/E29-OTHERS. Still open under this item: E21 (Cursor documentation), E22 remainder, E24 (other vendors), E26 (Schlapbach PDF, other agent docs), E30, E31 remainder, E32, E33, UNREADLEADS, STEWARDUNREAD (TheMCPCompany main text). 2026-10-20 (batch 13a): nine children deferred with reason and trigger (E21, E22, E23, E24, E26, E31, E32, E33, STEWARDUNREAD) because no live document depends on them; E30 waits for the supervisor-related list from you (Q-U23); E34 and UNREADLEADS remain. | V50: Pivotal originals read; non-pivotal ones deferred with a reason and trigger. | X50: C-D01, C-D08 | Z50: LITERATURE-DIRECTED, ACCEPT-LIMITATION | AB50: SOURCE+ACCESS+RECORD | AC50: OPEN | AD50: NARROWED | AE50: 2026-10-20 | AF50: see the child rows | AG50: When a skipped source becomes pivotal or a paper version changes | AH50: No (AUTH-016 covers web fetches for this item) | AJ50: SRC-11 canonical | AK50: SRC-06 E20-E34, SRC-07 28 | AL50: S11
A51: C-E02/E21 | B51: Hajdas post, Cursor cap docs, Claude Code changelog not opened; 55K attribution | C51: DEFERRED | D51: =IFERROR(INDEX(Lists!$B$2:$B$14,MATCH(C51,Lists!$A$2:$A$14,0)),"?") | E51: =IF(COUNTIFS(Links!$B$2:$B$600,A51,Links!$E$2:$E$600,"Yes")>0,"REVISE","") | F51: =COUNTIFS(Links!$B$2:$B$600,A51,Links!$D$2:$D$600,"No",Links!$C$2:$C$600,"<>INFORMS") | G51: SOURCE-REREAD | H51: K14 Source & vendor verification | I51: G4 Before claims | J51: Normal | K51: 94 | L51: W2 Desk work (no model runs) | M51: S11 | N51: Lead + steward | O51: none until the trigger fires | P51: Partly | Q51: Source check | R51: Sub-item | S51: C-E02 | T51: SRC-06 E21: the Hajdas post, Cursor cap docs and Claude Code changelog were not opened; the 55K attribution is uncertain. | U51: Claude Code MCP docs stored; the other three not in the repo. Batch 4: three Cursor forum threads read (forum posts, not Cursor documentation): users report a cap of 40 tools with the rest unavailable to the agent (one user quotes the docs: 'Currently, Cursor will only send the first 40 tools to the Agent', 21 Mar 2025); in a 2026-03-03 thread a user replies that Cursor 'has already implemented Dynamic Context Discovery' and says they run more than 80 tools with no warning (older versions, below 2.3, warned to stay under 50); no staff statement was identified, and what the 40 limit became is not established by these posts. The Hajdas post, the Cursor docs page itself and the Claude Code changelog are still not stored, and the 55K attribution is unaddressed. Deferred 2026-10-20 with reason and trigger (the C-E02 criterion: 'non-pivotal ones deferred with a reason and trigger'): Lead's grep on 2026-10-20 of design/package-v3 and design/package-v4 files 01-05 finds no mention of Cursor, the 55K attribution or the Hajdas post, so no live claim depends on the Cursor documentation, the Hajdas post or the Claude Code changelog. The forum threads read in batch 4 stay user reports. | V51: Original read; claims it affects revised or marked unverified. | AB51: SOURCE+ACCESS | AC51: n/a (sub-item) | AD51: NEW (SRC-11 sub-row) | AE51: 2026-10-20 | AF51: grep of design/package-v3 and design/package-v4 01-05 (lead, 2026-10-20); see also this row's earlier basis | AG51: A document quotes the Cursor tool cap, the 55K attribution or the Hajdas post | AH51: No (AUTH-016 covers web fetches for this item) | AJ51: SRC-11 section D2 | AK51: SRC-06 E21 | AL51: S11
A52: C-E02/E22 | B52: Anthropic programmatic-tool docs partial; prompt-cache tail, pricing, MCP pages not read in full | C52: DEFERRED | D52: =IFERROR(INDEX(Lists!$B$2:$B$14,MATCH(C52,Lists!$A$2:$A$14,0)),"?") | E52: =IF(COUNTIFS(Links!$B$2:$B$600,A52,Links!$E$2:$E$600,"Yes")>0,"REVISE","") | F52: =COUNTIFS(Links!$B$2:$B$600,A52,Links!$D$2:$D$600,"No",Links!$C$2:$C$600,"<>INFORMS") | G52: SOURCE-REREAD | H52: K14 Source & vendor verification | I52: G4 Before claims | J52: Normal | K52: 95 | L52: W2 Desk work (no model runs) | M52: S11 | N52: Lead + steward | O52: none until the trigger fires | P52: Yes - stored text, unread | Q52: Source check | R52: Sub-item | S52: C-E02 | T52: SRC-06 E22: Anthropic programmatic docs partial; prompt-cache tail, pricing and MCP pages not read in full. | U52: Read now: Anthropic programmatic tool calling intro (vendor reports '24% fewer input tokens' and an 11% performance gain on BrowseComp and DeepSearchQA with web-search tools; allowed_callers makes a tool callable from code execution; nothing on caching or tool-definition counting) (EXT-0144); the MCP caching page in full (EXT-0143); the Anthropic prompt-caching ranges on invalidation and tool-definition caching (EXT-0115, EXT-0123); pricing earlier (EXT-0085). Still unread: the Anthropic 1-hour option and minimums, the 'Tool use with prompt caching' page. Batch 5 (lead): the Anthropic programmatic-tool-calling page, section 'Token efficiency' and 'Usage and pricing' (EXT-0183): vendor figures from internal evaluations, 38% fewer billed input tokens on a 75-tool project-management benchmark, scores unchanged and about 8% more cost on tau2-bench (sequential single calls do not benefit), typical 20-40% savings when the tools array holds 10 to 49 definitions (the intro stored earlier says 24%, EXT-0144: different statements on one vendor page); 'Tool results from programmatic invocations do not count toward your input/output token usage'; it advises measuring billed input tokens with and without allowed_callers. Vendor claims, no sample sizes. The 1-hour option and minimums were read in batch 2 (EXT-0152, EXT-0150) and the 'tool use with prompt caching' page in EXT-0158. Still unread: the programmatic page body (lines 37-1409, mostly code samples), the prompt-caching page tail. Deferred 2026-10-20 with reason and trigger (the C-E02 criterion: 'non-pivotal ones deferred with a reason and trigger'): the claims about caching in the live documents rest on the Anthropic pages read (EXT-0143, EXT-0115, EXT-0123, EXT-0150, EXT-0152, EXT-0158, EXT-0183); what is unread is the body of the programmatic-tool-calling page (mostly code samples) and the tail of the prompt-caching page. | V52: Original read; claims it affects revised or marked unverified. | AB52: SOURCE+ACCESS | AC52: n/a (sub-item) | AD52: NEW (SRC-11 sub-row) | AE52: 2026-10-20 | AF52: grep of design/package-v3 and design/package-v4 01-05 (lead, 2026-10-20); see also this row's earlier basis | AG52: A claim depends on the unread body of the programmatic page or the tail of the prompt-caching page | AH52: No (AUTH-016 covers web fetches for this item) | AJ52: SRC-11 section D2 | AK52: SRC-06 E22 | AL52: S11
A53: C-E02/E23 | B53: CE-MCP figures, ToolRet Figure 6, ToolShed trade-off not rendered | C53: DEFERRED | D53: =IFERROR(INDEX(Lists!$B$2:$B$14,MATCH(C53,Lists!$A$2:$A$14,0)),"?") | E53: =IF(COUNTIFS(Links!$B$2:$B$600,A53,Links!$E$2:$E$600,"Yes")>0,"REVISE","") | F53: =COUNTIFS(Links!$B$2:$B$600,A53,Links!$D$2:$D$600,"No",Links!$C$2:$C$600,"<>INFORMS") | G53: SOURCE-REREAD | H53: K14 Source & vendor verification | I53: G4 Before claims | J53: Normal | K53: 96 | L53: W2 Desk work (no model runs) | M53: S11 | N53: Lead + steward | O53: none until the trigger fires | P53: Partly | Q53: Source check | R53: Sub-item | S53: C-E02 | T53: SRC-06 E23: CE-MCP figures, ToolRet Figure 6 and the ToolShed trade-off were not rendered. | U53: Text stored; figures need page rendering (raw PDFs are not in the repo). Batch 8: the ToolRet part was read on the rendered Table 5 (with instruction) and from the text layer of Table 4 (without instruction): 50.60 is the ToolBench-G1 pass rate of gpt-3.5-turbo as the tool-use LLM with tools retrieved by bge-large-en-v1.5, against 62.00 with the oracle toolset (difference 11.40, as the text says); 33.83 is the average NDCG@10 of NV-Embed-v1 in Table 4 (without instruction; C@10 32.12), so 'best nDCG@10 33.83' holds only for that setting (with instruction NV-Embed-v1 reaches 42.71, gte-Qwen2-1.5B-instruct 45.96, bge-reranker-v2-gemma 47.52). The paper's own figures differ: the G2 oracle for gpt-3.5 is 64.20 in Figure 6 but 57.20 in appendix Table 14, and the G3 oracle 67.50 against 67.40, with no explanation. CE-MCP and the ToolShed trade-off are carried by C-E02/E29-OTHERS (DEFERRED). Deferred 2026-10-20 with reason and trigger (the C-E02 criterion: 'non-pivotal ones deferred with a reason and trigger'): the live documents quote ToolRet's 50.60 vs 62.00 from its prose (verified in batch 8); what remains is ToolRet Figure 6 and Table 14 (the G2 and G3 oracle values differ between them) and CE-MCP and ToolShed (carried by C-E02/E29-OTHERS). | V53: Original read; claims it affects revised or marked unverified. | Y53: Q-U22 | AB53: SOURCE+ACCESS | AC53: n/a (sub-item) | AD53: NEW (SRC-11 sub-row) | AE53: 2026-10-20 | AF53: grep of design/package-v3 and design/package-v4 01-05 (lead, 2026-10-20); see also this row's earlier basis | AG53: A document quotes a G2 or G3 oracle value, or Figure 6 | AH53: No (AUTH-016 covers web fetches for this item) | AJ53: SRC-11 section D2 | AK53: SRC-06 E23 | AL53: S11
A54: C-E02/E24 | B54: Speakeasy tables and Composio/Zapier/Pipedream/Smithery measurements missing | C54: DEFERRED | D54: =IFERROR(INDEX(Lists!$B$2:$B$14,MATCH(C54,Lists!$A$2:$A$14,0)),"?") | E54: =IF(COUNTIFS(Links!$B$2:$B$600,A54,Links!$E$2:$E$600,"Yes")>0,"REVISE","") | F54: =COUNTIFS(Links!$B$2:$B$600,A54,Links!$D$2:$D$600,"No",Links!$C$2:$C$600,"<>INFORMS") | G54: AUTHOR-OR-VENDOR | H54: K14 Source & vendor verification | I54: G4 Before claims | J54: Normal | K54: 97 | L54: W2 Desk work (no model runs) | M54: S11 | N54: Lead + steward | O54: none until the trigger fires | P54: Partly | Q54: Source check | R54: Sub-item | S54: C-E02 | T54: SRC-06 E24: Speakeasy tables and Composio/Zapier/Pipedream/Smithery measurements were missing from fetched pages. | U54: The Speakeasy table is present in the stored text (used in v4-01); the other four vendors are not in the repo. Deferred 2026-10-20 with reason and trigger (the C-E02 criterion: 'non-pivotal ones deferred with a reason and trigger'): Lead's grep on 2026-10-20 of design/package-v3 and design/package-v4 files 01-05 finds no mention of Composio, Zapier, Pipedream or Smithery; the Speakeasy table is present in the stored text. | V54: Original read; claims it affects revised or marked unverified. | AB54: SOURCE+ACCESS | AC54: n/a (sub-item) | AD54: NEW (SRC-11 sub-row) | AE54: 2026-10-20 | AF54: grep of design/package-v3 and design/package-v4 01-05 (lead, 2026-10-20); see also this row's earlier basis | AG54: A document quotes a measurement from Composio, Zapier, Pipedream or Smithery | AH54: No (AUTH-016 covers web fetches for this item) | AJ54: SRC-11 section D2 | AK54: SRC-06 E24 | AL54: S11
A55: C-E02/E25 | B55: Claude Code deferral bug reports known by title only | C55: PARTLY ANSWERED | D55: =IFERROR(INDEX(Lists!$B$2:$B$14,MATCH(C55,Lists!$A$2:$A$14,0)),"?") | E55: =IF(COUNTIFS(Links!$B$2:$B$600,A55,Links!$E$2:$E$600,"Yes")>0,"REVISE","") | F55: =COUNTIFS(Links!$B$2:$B$600,A55,Links!$D$2:$D$600,"No",Links!$C$2:$C$600,"<>INFORMS") | G55: AUTHOR-OR-VENDOR | H55: K14 Source & vendor verification | I55: G4 Before claims | J55: Normal | K55: 98 | L55: W2 Desk work (no model runs) | M55: S11 | N55: Reporters / lead | O55: Treat as a user report; verify only if the anecdote is used | P55: No | Q55: Source check | R55: Sub-item | S55: C-E02 | T55: SRC-06 E25: Claude Code deferral bug reports known by titles only; the cache-read inflation anecdote is unverified. | U55: Not stored. Batch 4: Claude Code issue #59650 (mirror) read: one user, Opus 4.7, 1M context, reports ~35.3M cumulative cache reads, one turn ~150k, and '/context' showing 'MCP tools (deferred): 87.8k' within a stated total of 239.9k; the listed items sum to more than the stated total (~343k), so the numbers do not reconcile; status closed, not planned; no maintainer reply or fix is in the mirror. Issue #30920 (v2.1.69): API 400 'cannot have both defer_loading=true and cache_control set'; workaround ENABLE_TOOL_SEARCH=false; status 'Closed - not planned', opened 5 Mar 2026, closed 2 Apr 2026. The cache-read inflation anecdote is a single user's self-measurement, still unverified. | V5 2026-10-22: one cache-bust issue stored with community data; Claude Code's tool-search docs stored | V55: Original read; claims it affects revised or marked unverified. | AB55: SOURCE+ACCESS | AC55: n/a (sub-item) | AD55: NEW (SRC-11 sub-row) | AE55: 2026-10-22 | AF55: L/v5-ccissue-92033-cachebust-20261022.txt:180-192; L/v5-claudecode-mcp-20261022.md:1441 | AH55: No (AUTH-016 covers web fetches for this item) | AJ55: SRC-11 section D2 | AK55: SRC-06 E25 | AL55: S11
A56: C-E02/E26 | B56: ToolHop repo 404, Schlapbach PDF unreadable, other agent docs not fetched | C56: DEFERRED | D56: =IFERROR(INDEX(Lists!$B$2:$B$14,MATCH(C56,Lists!$A$2:$A$14,0)),"?") | E56: =IF(COUNTIFS(Links!$B$2:$B$600,A56,Links!$E$2:$E$600,"Yes")>0,"REVISE","") | F56: =COUNTIFS(Links!$B$2:$B$600,A56,Links!$D$2:$D$600,"No",Links!$C$2:$C$600,"<>INFORMS") | G56: SOURCE-REREAD | H56: K14 Source & vendor verification | I56: G4 Before claims | J56: Normal | K56: 99 | L56: W2 Desk work (no model runs) | M56: S11 | N56: Lead + steward | O56: none until the trigger fires | P56: Partly | Q56: Source check | R56: Sub-item | S56: C-E02 | T56: SRC-06 E26: ToolHop repo 404, Schlapbach PDF unreadable, other agent docs not fetched. | U56: Agent-framework docs are stored; ToolHop and Schlapbach are not. Batch 4: ToolHop (arXiv 2501.02506v4) read in part: a multi-hop tool-composition benchmark (995 queries, 3,912 tools; GPT-4o 49.04%); it measures composition of tools, nothing on discovery of hidden tools or on token cost. The Schlapbach PDF and the other agent-framework docs are still not read. Deferred 2026-10-20 with reason and trigger (the C-E02 criterion: 'non-pivotal ones deferred with a reason and trigger'): Lead's grep on 2026-10-20 of design/package-v3 and design/package-v4 files 01-05 finds no mention of the Schlapbach PDF or of other agent-framework docs beyond those read; ToolHop was read (batch 4) and measures composition, not discovery or token cost. | V56: Original read; claims it affects revised or marked unverified. | AB56: SOURCE+ACCESS | AC56: n/a (sub-item) | AD56: NEW (SRC-11 sub-row) | AE56: 2026-10-20 | AF56: grep of design/package-v3 and design/package-v4 01-05 (lead, 2026-10-20); see also this row's earlier basis | AG56: A document quotes the Schlapbach PDF or an agent-framework doc that is not stored | AH56: No (AUTH-016 covers web fetches for this item) | AJ56: SRC-11 section D2 | AK56: SRC-06 E26 | AL56: S11
A57: C-E02/E29-OTHERS | B57: Papers in the garbled-table group that no live document quotes: Re-Invoke, Shi, ToolTweak, MCP-SafetyBench, CE-MCP, ToolShed trade-off | C57: DEFERRED | D57: =IFERROR(INDEX(Lists!$B$2:$B$14,MATCH(C57,Lists!$A$2:$A$14,0)),"?") | E57: =IF(COUNTIFS(Links!$B$2:$B$600,A57,Links!$E$2:$E$600,"Yes")>0,"REVISE","") | F57: =COUNTIFS(Links!$B$2:$B$600,A57,Links!$D$2:$D$600,"No",Links!$C$2:$C$600,"<>INFORMS") | G57: SOURCE-REREAD | H57: K14 Source & vendor verification | I57: G5 Housekeeping / no block | J57: Low | K57: 103 | L57: W2 Desk work (no model runs) | M57: S11 | N57: Lead + steward | O57: Render the table pages only if a claim quotes them | P57: Partly | Q57: Source check | R57: Sub-item | S57: C-E02 | T57: SRC-06 E23 and E29 listed these papers' tables and figures as garbled or not rendered. A grep of the live documents (design/package-v1..v4, design/tool-exposure-policy-proposal.md, design/proposals, design/choices, hypotheses, requirements, reviews, challenges) found no quotation of their figures: Re-Invoke appears only in CH-0009 (a challenge, not a figure), ToolTweak, MCP-SafetyBench and ToolShed in none; CE-MCP appears in DPR-0002 line 33, the v2 claim register and CH-0015 as a qualitative result only ('figures not cited'). They appear in historical governing stage reports. | U57: Deferred 2026-10-19 with reason and trigger, as the C-E02 criterion allows ('non-pivotal ones deferred with a reason and trigger'). The determination 'no live document quotes them' is the lead's grep and may miss a paraphrase. | V57: Reopened and read on rendered pages if any document quotes a figure from these papers; otherwise stays deferred. | AB57: SOURCE | AC57: n/a (sub-item) | AD57: NEW (repo sweep) | AE57: 2026-10-19 | AF57: grep of the live documents by the lead (2026-10-19); FND-0024 (findings/SUM-0026); EXT-0211; evidence/literature-20261019/pages/INDEX.md (page images with SHA-256; raw PDF hashes match the manifest) | AG57: Any live document, brief or thesis text quotes a figure, table or trade-off from Re-Invoke, Shi, ToolTweak, MCP-SafetyBench, CE-MCP or ToolShed | AH57: No (AUTH-016 covers web fetches for this item) | AJ57: Batch 8 split of C-E02/E23 and C-E02/E29 | AL57: S11
A58: C-E02/E30 | B58: Eight listed prior-art leads never fetched | C58: OPEN | D58: =IFERROR(INDEX(Lists!$B$2:$B$14,MATCH(C58,Lists!$A$2:$A$14,0)),"?") | E58: =IF(COUNTIFS(Links!$B$2:$B$600,A58,Links!$E$2:$E$600,"Yes")>0,"REVISE","") | F58: =COUNTIFS(Links!$B$2:$B$600,A58,Links!$D$2:$D$600,"No",Links!$C$2:$C$600,"<>INFORMS") | G58: LITERATURE-DIRECTED | H58: K14 Source & vendor verification | I58: G4 Before claims | J58: Normal | K58: 104 | L58: W2 Desk work (no model runs) | M58: S11 | N58: You (supply the list) then lead | O58: Directed search (needs scope) | P58: No | Q58: Source check | R58: Sub-item | S58: C-E02 | T58: SRC-06 E30: eight listed prior-art leads were never fetched by the earlier body. | U58: Names not available from SRC-11; cannot check against the repo. | V58: Original read; claims it affects revised or marked unverified. | Y58: Q-U23 | AB58: SOURCE+ACCESS | AC58: n/a (sub-item) | AD58: NEW (SRC-11 sub-row) | AE58: 2026-10-19 | AF58: the list is in SRC-08 (not in .workspace) | AH58: No (AUTH-016 covers web fetches for this item) | AJ58: SRC-11 section D2 | AK58: SRC-06 E30 | AL58: S11
A59: C-E02/E31 | B59: ScaleMCP/MemTool/Toolshed/Manus/HAL/tau-bench and Spring AI/langgraph-bigtool: follow-up status unclear | C59: PARTLY ANSWERED | D59: =IFERROR(INDEX(Lists!$B$2:$B$14,MATCH(C59,Lists!$A$2:$A$14,0)),"?") | E59: =IF(COUNTIFS(Links!$B$2:$B$600,A59,Links!$E$2:$E$600,"Yes")>0,"REVISE","") | F59: =COUNTIFS(Links!$B$2:$B$600,A59,Links!$D$2:$D$600,"No",Links!$C$2:$C$600,"<>INFORMS") | G59: SOURCE-REREAD | H59: K14 Source & vendor verification | I59: G4 Before claims | J59: Normal | K59: 105 | L59: W2 Desk work (no model runs) | M59: S11 | N59: Lead + steward | O59: Spring AI (origin r4-spring-tool-search-blog), Toolshed | P59: Partly | Q59: Source check | R59: Sub-item | S59: C-E02 | T59: SRC-06 E31: ScaleMCP, MemTool, Toolshed, Manus, HAL and tau-bench groups and Spring AI / langgraph-bigtool code; follow-up status is unclear. | U59: Fetched 2026-10-13 and stored; ScaleMCP, MCP-Zero and MemTool were read by the steward; the rest are stored with unknown read status. Deferred 2026-10-20 with reason and trigger (the C-E02 criterion: 'non-pivotal ones deferred with a reason and trigger'): Lead's grep on 2026-10-20 of design/package-v3 and design/package-v4 files 01-05 finds no mention of Manus, HAL, tau-bench, Spring AI, langgraph-bigtool or Toolshed (ScaleMCP and MemTool, which 04 and 05 cite, were read by a steward); the prior-art matrix (FND-0030) read parts of Spring AI and Toolshed. | V5 2026-10-22: ScaleMCP, MemTool, Manus, langgraph-bigtool stored and checked by stewards (FND-0040..0042); Spring AI and Toolshed remain unread | V59: Original read; claims it affects revised or marked unverified. | AB59: SOURCE+ACCESS | AC59: n/a (sub-item) | AD59: NEW (SRC-11 sub-row) | AE59: 2026-10-22 | AF59: FND-0040, FND-0041, FND-0042 | AG59: A document quotes Manus, HAL, tau-bench, Spring AI, langgraph-bigtool or Toolshed | AH59: No (AUTH-016 covers web fetches for this item) | AJ59: SRC-11 section D2 | AK59: SRC-06 E31 | AL59: S11
A60: C-E02/E32 | B60: 95 near-miss stored texts: abstracts read, ~12 read deeper | C60: DEFERRED | D60: =IFERROR(INDEX(Lists!$B$2:$B$14,MATCH(C60,Lists!$A$2:$A$14,0)),"?") | E60: =IF(COUNTIFS(Links!$B$2:$B$600,A60,Links!$E$2:$E$600,"Yes")>0,"REVISE","") | F60: =COUNTIFS(Links!$B$2:$B$600,A60,Links!$D$2:$D$600,"No",Links!$C$2:$C$600,"<>INFORMS") | G60: SOURCE-REREAD | H60: K14 Source & vendor verification | I60: G4 Before claims | J60: Normal | K60: 106 | L60: W2 Desk work (no model runs) | M60: S11 | N60: Lead + steward | O60: none until the trigger fires | P60: Partly | Q60: Source check | R60: Sub-item | S60: C-E02 | T60: SRC-06 E32: 95 near-miss stored texts had abstracts read; only about 12 were read deeper. | U60: Only some near-miss texts are in this repo's source set. Deferred 2026-10-20 with reason and trigger (the C-E02 criterion: 'non-pivotal ones deferred with a reason and trigger'): the live brief states that 'not found' is not 'does not exist' and that the check is a convenience sample (01 line 77), so no broad absence claim is made on the 95 near-miss texts; about 12 of them were read deeper. | V60: Decisive ones prioritised; broad absence claims not made. | AB60: SOURCE+ACCESS | AC60: n/a (sub-item) | AD60: NEW (SRC-11 sub-row) | AE60: 2026-10-20 | AF60: grep of design/package-v3 and design/package-v4 01-05 (lead, 2026-10-20); see also this row's earlier basis | AG60: A broad absence claim is about to be made, or a decisive near-miss text is identified | AH60: No (AUTH-016 covers web fetches for this item) | AJ60: SRC-11 section D2 | AK60: SRC-06 E32 | AL60: S11
A61: C-E02/E33 | B61: Historical web fetches were model-generated extracts; 'verbatim' may be paraphrase | C61: DEFERRED | D61: =IFERROR(INDEX(Lists!$B$2:$B$14,MATCH(C61,Lists!$A$2:$A$14,0)),"?") | E61: =IF(COUNTIFS(Links!$B$2:$B$600,A61,Links!$E$2:$E$600,"Yes")>0,"REVISE","") | F61: =COUNTIFS(Links!$B$2:$B$600,A61,Links!$D$2:$D$600,"No",Links!$C$2:$C$600,"<>INFORMS") | G61: SOURCE-REREAD | H61: K14 Source & vendor verification | I61: G4 Before claims | J61: Normal | K61: 107 | L61: W2 Desk work (no model runs) | M61: S11 | N61: Lead + steward | O61: none until the trigger fires | P61: Partly | Q61: Source check | R61: Sub-item | S61: C-E02 | T61: SRC-06 E33: historical web fetches were model-generated extracts, so 'verbatim' quotes may be paraphrase. | U61: Stored PDFs are raw text-layer extracts (verbatim); web-page extractor to be confirmed per source. Deferred 2026-10-20 with reason and trigger (the C-E02 criterion: 'non-pivotal ones deferred with a reason and trigger'): the direct quotes in the live documents are cited to hash-verified extracts of stored texts (EXT ids); the web-page sources stored in the origin were fetched by the earlier body, and whether any live sentence quotes one of them verbatim was not checked exhaustively. | V61: Raw original used before any direct quote. | AB61: SOURCE+ACCESS | AC61: n/a (sub-item) | AD61: NEW (SRC-11 sub-row) | AE61: 2026-10-20 | AF61: grep of design/package-v3 and design/package-v4 01-05 (lead, 2026-10-20); see also this row's earlier basis | AG61: Before any direct quote from a web page stored in the origin (r4-* pages): compare it with a fresh litfetch copy | AH61: No (AUTH-016 covers web fetches for this item) | AJ61: SRC-11 section D2 | AK61: SRC-06 E33 | AL61: S11
A62: C-E02/E34 | B62: Historical 'not found' claims used only 2-3 queries | C62: PARTLY ANSWERED | D62: =IFERROR(INDEX(Lists!$B$2:$B$14,MATCH(C62,Lists!$A$2:$A$14,0)),"?") | E62: =IF(COUNTIFS(Links!$B$2:$B$600,A62,Links!$E$2:$E$600,"Yes")>0,"REVISE","") | F62: =COUNTIFS(Links!$B$2:$B$600,A62,Links!$D$2:$D$600,"No",Links!$C$2:$C$600,"<>INFORMS") | G62: LITERATURE-DIRECTED | H62: K14 Source & vendor verification | I62: G4 Before claims | J62: Normal | K62: 108 | L62: W2 Desk work (no model runs) | M62: S11 | N62: Lead + steward | O62: Directed search (needs scope) | P62: Partly | Q62: Source check | R62: Sub-item | S62: C-E02 | T62: SRC-06 E34: historical 'not found' claims used only 2-3 queries and missed stored sources. | U62: The convention 'not found, never does not exist' is adopted; a search log exists for the AUTH-011/013 topics only. Batch 4: the 10 queries run for this batch are logged in ops/threads/T-20261019-102/TASK.md (standard-mode searches; search-engine summaries were not used as evidence); logs now exist for AUTH-011/013 and this batch. | V62: Each absence claim carries a bounded search log. | AB62: SOURCE+ACCESS | AC62: n/a (sub-item) | AD62: NEW (SRC-11 sub-row) | AE62: 2026-10-19 | AF62: ops/threads/T-20261019-102/TASK.md | AH62: No (AUTH-016 covers web fetches for this item) | AJ62: SRC-11 section D2 | AK62: SRC-06 E34 | AL62: S11
A63: C-E02/STEWARDUNREAD | B63: Steward did not read appendices of TheMCPCompany, LiveMCPBench, When2Call, SING, the cache study | C63: DEFERRED | D63: =IFERROR(INDEX(Lists!$B$2:$B$14,MATCH(C63,Lists!$A$2:$A$14,0)),"?") | E63: =IF(COUNTIFS(Links!$B$2:$B$600,A63,Links!$E$2:$E$600,"Yes")>0,"REVISE","") | F63: =COUNTIFS(Links!$B$2:$B$600,A63,Links!$D$2:$D$600,"No",Links!$C$2:$C$600,"<>INFORMS") | G63: SOURCE-REREAD | H63: K14 Source & vendor verification | I63: G4 Before claims | J63: Normal | K63: 109 | L63: W2 Desk work (no model runs) | M63: S11 | N63: Lead + fresh reviewer | O63: none until the trigger fires | P63: Yes - stored text, unread | Q63: Record fix | R63: Sub-item | S63: C-E02 | T63: v4-05 section 5: TheMCPCompany trajectories and appendices, LiveMCPBench appendices other than cited, When2Call appendices, SING appendices (prompts) and the cache-study appendices were not read. | U63: Batch 5: appendices read by a steward for four topics (T1 discovery without sight, T2 cost, T3 cache, T4 prompts). TheMCPCompany (parts): the system prompt tells the agent to use 'find tools' and to 'attempt 3-4 different potential trajectories' (Table 12, EXT-0199), so discovery is instructed there; Appendix E says models often call MCP tools directly and bypass the gateway call tool, with no rate (EXT-0200); the tool finder is dense retrieval returning 5 tools by default; Table 5 gives retrieval attempts and MCP calls per task (counts only, stored table partly scrambled). LiveMCPBench v1 and v2 appendices: prompts describe a retrieval tool and an execution tool and instruct discovery (Appendix J, EXT-0185); Appendix G states only the cost method (OpenRouter prices of 2026-01-31, input and output tokens), no figures. SING appendix: the prompts are data-synthesis prompts, not the tested agent's prompt; Table 7 is one traced search_tools / get_tool_schema / execute_tool example (EXT-0188); failure taxonomy in EXT-0189. Cache study appendix: provider prices and minimum cacheable lengths only (Sonnet 4.5 input 3.00, cached 0.30, write 3.75 USD per 1M; minimums 1,024 for OpenAI and Anthropic, 4,096 for Gemini 2.5 Pro; EXT-0192), no hit rates, nothing on tool definitions. No appendix gave an uninstructed discovery condition, a token or money cost of discovery, or cache rates tied to tool definitions. When2Call is stored in the workspace as evidence/literature-20261019/arxiv-2504.18851.txt (not an origin manifest source); its appendices were read only in part (see C-R03/RV7UNCHK). Not read: TheMCPCompany lines 1-879 and 1960-3527 (main text and later trajectories), LiveMCPBench main texts, SING and cache-study main texts. Deferred 2026-10-20 with reason and trigger (the C-E02 criterion: 'non-pivotal ones deferred with a reason and trigger'): the appendices were read for the four topics (batch 5); what remains unread is the main text of TheMCPCompany lines 1-879 and its later trajectories (lines 1960-3527), the main texts of LiveMCPBench, SING and the cache study, and When2Call's appendices beyond the parts read; earlier stewards read the bodies of TheMCPCompany, LiveMCPBench, SING and the cache study (C-X09), and no live claim is known to rest on the unread trajectories. | V63: Read if a claim depends on them. | AB63: RECORD+SOURCE | AC63: n/a (sub-item) | AD63: NEW (repo sweep) | AE63: 2026-10-20 | AF63: grep of design/package-v3 and design/package-v4 01-05 (lead, 2026-10-20); see also this row's earlier basis | AG63: A claim depends on an unread trajectory or appendix | AH63: No (AUTH-016 covers web fetches for this item) | AJ63: repo: v4-03 section 6 / RV-0005 / RV-0007 | AL63: S11
A64: C-X09 | B64: Re-read decisive papers/tables or ask authors (the check behind C-E01..E03 and C-S19). | C64: PARTLY ANSWERED | D64: =IFERROR(INDEX(Lists!$B$2:$B$14,MATCH(C64,Lists!$A$2:$A$14,0)),"?") | E64: =IF(COUNTIFS(Links!$B$2:$B$600,A64,Links!$E$2:$E$600,"Yes")>0,"REVISE","") | F64: =COUNTIFS(Links!$B$2:$B$600,A64,Links!$D$2:$D$600,"No",Links!$C$2:$C$600,"<>INFORMS") | G64: SOURCE-REREAD | H64: K14 Source & vendor verification | I64: G4 Before claims | J64: Normal | K64: 111 | L64: W2 Desk work (no model runs) | M64: S11 | N64: Lead + steward | O64: You send the author asks; approve 06 row 3.29 | P64: Yes - stored text, unread | Q64: Test | R64: Check | T64: Re-read decisive papers/tables or ask authors (the check behind C-E01..E03 and C-S19). | U64: Steward read many decisive bodies (TheMCPCompany, LiveMCPBench, SING, MCP-Zero, ScaleMCP, MemTool, When2Call, cache study); MCPVerse is a lead reading only; no author contacted. 2026-10-20: the pivotal tables were rendered and read (batches 3, 8, 9), the version maps are written (batch 14) and the author asks are drafted (design/ledger/notes/AUTHOR-ASKS-DRAFT-20261020.md); what remains is the human sending the asks and approving the version pointer. | V64: Pivotal sources read and cited with version; authors asked where needed. | X64: C-D01 | Z64: AUTHOR-OR-VENDOR | AB64: SOURCE | AC64: PARTLY DONE - OPEN | AD64: NARROWED | AE64: 2026-10-20 | AF64: SUM-0005..0009 | AH64: No (AUTH-016 covers web fetches for this item) | AJ64: SRC-11 canonical | AK64: SRC-06 X09 | AL64: S11
A65: C-S05 | B65: Vendor tool-search gain (49% to 74%) has no public method or sample and is unreplicated. | C65: NOT LOCATED | D65: =IFERROR(INDEX(Lists!$B$2:$B$14,MATCH(C65,Lists!$A$2:$A$14,0)),"?") | E65: =IF(COUNTIFS(Links!$B$2:$B$600,A65,Links!$E$2:$E$600,"Yes")>0,"REVISE","") | F65: =COUNTIFS(Links!$B$2:$B$600,A65,Links!$D$2:$D$600,"No",Links!$C$2:$C$600,"<>INFORMS") | G65: AUTHOR-OR-VENDOR | H65: K14 Source & vendor verification | I65: G4 Before claims | J65: Normal | K65: 113 | L65: W2 Desk work (no model runs) | M65: S12 | N65: Vendor (or an independent benchmark) | O65: You send the drafted ask (design/ledger/notes/AUTHOR-ASKS-DRAFT-20261020.md, section 3) and record the reply; until then it waits on the authors | P65: No | Q65: Source check | R65: Item | T65: Vendor tool-search gain (49% to 74%) has no public method or sample and is unreplicated. | U65: Three differently worded searches found no third-party measurement (not located is not 'does not exist'). | V65: Method/data supplied, or recorded as 'not provided' and cited as a vendor claim. | X65: C-S02 | Z65: TEST-PILOT | AA65: K11 End-to-end comparison | AB65: SOURCE+DATA | AC65: OPEN | AD65: NOT LOCATED | AE65: 2026-10-20 | AF65: v4-05 section 1B and saturation note; EXT-0074 | AH65: No for the ask | AJ65: SRC-11 canonical | AK65: SRC-06 S09 | AL65: S12
A66: C-S19 | B66: MCPVerse v1/v2 discrepancies (score shift, copied v2 Table 4 cells, denominators, pool, reproduction, nativ... | C66: PARTLY ANSWERED | D66: =IFERROR(INDEX(Lists!$B$2:$B$14,MATCH(C66,Lists!$A$2:$A$14,0)),"?") | E66: =IF(COUNTIFS(Links!$B$2:$B$600,A66,Links!$E$2:$E$600,"Yes")>0,"REVISE","") | F66: =COUNTIFS(Links!$B$2:$B$600,A66,Links!$D$2:$D$600,"No",Links!$C$2:$C$600,"<>INFORMS") | G66: AUTHOR-OR-VENDOR | H66: K14 Source & vendor verification | I66: G5 Housekeeping / no block | J66: Low | K66: 114 | L66: W2 Desk work (no model runs) | M66: S12 | N66: Authors; or defer | O66: Author asks (S40, S41, S43 judge identity) | P66: Yes - stored text, unread | Q66: Source check | R66: Item | T66: MCPVerse v1/v2 discrepancies (score shift, copied v2 Table 4 cells, denominators, pool, reproduction, native vs prompt calling). | U66: One unverified lead reading of the PDFs exists (AUTH-008); v4 files do not cite MCPVerse, so it is not pivotal to v4. Batch 9: S43 (mechanism and judge prompt) and S45 (12 contradictions) answered from v1, v2 and page images; the causes of the score shift (S40) and of the copied and duplicated cells (S41) are not stated by the paper and wait for the authors; S42 remains partly open. | V66: Author reply or 'author unavailable' recorded; defer unless it becomes a cited premise. | Z66: SOURCE-REREAD, ACCEPT-LIMITATION | AB66: SOURCE+AUTHOR+DATA | AC66: PARTLY ANSWERED - OPEN | AD66: UNCHANGED | AE66: 2026-10-19 | AF66: FND-0026 (findings/SUM-0028); EXT-0203, EXT-0204; evidence/literature-20261019/pages/INDEX.md (MCPVerse v2 pages 5, 7, 9) | AG66: If MCPVerse becomes a cited premise | AH66: No | AJ66: SRC-11 canonical | AK66: SRC-06 S40-S46, SRC-07 23, SRC-07 24 | AL66: S12
A67: C-S19/S40 | B67: Cause of the v1/v2 Claude score shift (judge change insufficient) | C67: PARTLY ANSWERED | D67: =IFERROR(INDEX(Lists!$B$2:$B$14,MATCH(C67,Lists!$A$2:$A$14,0)),"?") | E67: =IF(COUNTIFS(Links!$B$2:$B$600,A67,Links!$E$2:$E$600,"Yes")>0,"REVISE","") | F67: =COUNTIFS(Links!$B$2:$B$600,A67,Links!$D$2:$D$600,"No",Links!$C$2:$C$600,"<>INFORMS") | G67: AUTHOR-OR-VENDOR | H67: K14 Source & vendor verification | I67: G5 Housekeeping / no block | J67: Low | K67: 115 | L67: W2 Desk work (no model runs) | M67: S12 | N67: Authors / team | O67: You send the drafted ask (design/ledger/notes/AUTHOR-ASKS-DRAFT-20261020.md, section 1) and record the reply; until then it waits on the authors | P67: Partly | Q67: Source check | R67: Sub-item | S67: C-S19 | T67: SRC-06 S40 / SRC-07 23: a judge change does not explain the v1/v2 Claude shift; the actual cause (protocol, task/model mix, reruns) is open. | U67: Magnitude of the shift reproduced in one unverified lead reading; cause unknown. Batch 9: v1 Table 2 is ragged (the Claude values sit under the GPT-4o label; columns assigned by the L1-L3 means: Oracle 57.81, Standard 61.01, Max-Scale 57.77; v1's prose says Claude 'rises from 57.77 to 61.01', but 57.77 is the Max-Scale cell). v2 has 62.3, 62.4, 44.2 (shifts +4.5, +1.4, -13.6). Neither version says why: v2 never mentions v1, a re-run or a re-score. Visible differences: the judge changed (v1 GPT-4o-20241120 primary with Qwen-32B as a check; v2 QwQ-32B primary with GPT-4o as alternative); 8 models in v1 against 12; L1/L2/L3 shares differ; time-sensitive tasks 20.0% in v1 against 14.2% in v2; Standard tool count 218 in v1 against 220+ in v2; Oracle defined at MCP level in v1 and tool level in v2; annotator tool Trae against Cursor. The only judge-effect measure is v2 Table 8, Standard mode only: Claude 61.26 under GPT-4o and 62.36 under QwQ (1.1 points), so the Oracle and Max-Scale shifts cannot be attributed to the judge from these texts. | V67: Authors / raw logs / reproduction. | AB67: SOURCE+AUTHOR | AC67: n/a (sub-item) | AD67: NEW (SRC-11 sub-row) | AE67: 2026-10-20 | AF67: FND-0026 (findings/SUM-0028); EXT-0203, EXT-0204; evidence/literature-20261019/pages/INDEX.md (MCPVerse v2 pages 5, 7, 9); EXT-0204 | AH67: No | AJ67: SRC-11 section D3 | AK67: SRC-06 S40 | AL67: S12
A68: C-S19/S41 | B68: Copied cells in v2 Table 4 (Claude/Gemini) | C68: PARTLY ANSWERED | D68: =IFERROR(INDEX(Lists!$B$2:$B$14,MATCH(C68,Lists!$A$2:$A$14,0)),"?") | E68: =IF(COUNTIFS(Links!$B$2:$B$600,A68,Links!$E$2:$E$600,"Yes")>0,"REVISE","") | F68: =COUNTIFS(Links!$B$2:$B$600,A68,Links!$D$2:$D$600,"No",Links!$C$2:$C$600,"<>INFORMS") | G68: AUTHOR-OR-VENDOR | H68: K14 Source & vendor verification | I68: G5 Housekeeping / no block | J68: Low | K68: 116 | L68: W2 Desk work (no model runs) | M68: S12 | N68: Authors / team | O68: You send the drafted ask (design/ledger/notes/AUTHOR-ASKS-DRAFT-20261020.md, section 1) and record the reply; until then it waits on the authors | P68: Partly | Q68: Source check | R68: Sub-item | S68: C-S19 | T68: SRC-06 S41 / SRC-07 24: apparent copied cells identified; the correct v2 Table 4 Claude/Gemini cells are unknown. | U68: Consistent with SRC-11; one reader (the lead), page images outside the repo. Batch 9 (corrects the row's wording): the copied cells in v2 Table 4 are Claude-4-Sonnet's Oracle and Standard (44.8, 53.2), identical to Qwen3-235B-2507's and different from Claude's 62.3 / 62.4 (Table 2) and 62.28 / 62.36 (Table 3); Gemini is not in Table 4. Separately, Table 2's Gemini-2.5-Pro Max-Scale cells duplicate GPT-4o-20241120's Standard cells (page images 7 and 9; lead's reading of the images). Neither cause is stated in the paper. | V68: Authors / raw logs / reproduction. | AB68: SOURCE+AUTHOR | AC68: n/a (sub-item) | AD68: NEW (SRC-11 sub-row) | AE68: 2026-10-20 | AF68: FND-0026 (findings/SUM-0028); EXT-0203, EXT-0204; evidence/literature-20261019/pages/INDEX.md (MCPVerse v2 pages 5, 7, 9) | AH68: No | AJ68: SRC-11 section D3 | AK68: SRC-06 S41 | AL68: S12
A69: C-S19/S42 | B69: Printed per-level counts and 250-vs-311 mismatch | C69: PARTLY ANSWERED | D69: =IFERROR(INDEX(Lists!$B$2:$B$14,MATCH(C69,Lists!$A$2:$A$14,0)),"?") | E69: =IF(COUNTIFS(Links!$B$2:$B$600,A69,Links!$E$2:$E$600,"Yes")>0,"REVISE","") | F69: =COUNTIFS(Links!$B$2:$B$600,A69,Links!$D$2:$D$600,"No",Links!$C$2:$C$600,"<>INFORMS") | G69: SOURCE-REREAD | H69: K14 Source & vendor verification | I69: G5 Housekeeping / no block | J69: Low | K69: 117 | L69: W2 Desk work (no model runs) | M69: S12 | N69: Authors / team | O69: You send the drafted ask (design/ledger/notes/AUTHOR-ASKS-DRAFT-20261020.md, section 1) and record the reply; until then it waits on the authors | P69: Partly | Q69: Source check | R69: Sub-item | S69: C-S19 | T69: SRC-06 S42: printed per-level counts and a 250-vs-311 mismatch; denominators unknown. | U69: MCPVerse v2 text: 'we curate a benchmark consisting of 250 tasks' and 'the selected 65 MCPs expose more than 552 individual tools' (page 5, rendered; v1 also says 250). Figure 2 prints only percentages: (a) types 39.2% Information Retrieval, 40.2% 'System Interaction', 20.6% 'Hybrid Tasks' (the text names two main types, Information Retrieval and System Operation); (b) complexity L1 31.9%, L2 45.4%, L3 22.7%; (c) time-sensitive 14.2%, time-invariant 85.8%. Only 39.2% gives a whole number of tasks at N = 250 (98); the others imply half or quarter tasks (e.g. 40.2% = 100.5, 31.9% = 79.75), and 311 does not fit either. Lead search: only totals of 423 or 480 are consistent with all the printed percentages. The number 311 does not appear on the page. No per-level task counts are printed. Two independent readings of the page agree on the transcription. Batch 9: no token-per-task or cost figures appear in v1 or v2; Claude's native-versus-prompt Standard scores are 62.36 against 15.10 (Table 3), so some Standard and Max-Scale cells mix model and delivery method (the asterisked cells were obtained by prompt-based function calling). | V69: Authors / raw logs / reproduction. | Y69: Q-U22 | AB69: SOURCE+AUTHOR | AC69: n/a (sub-item) | AD69: NEW (SRC-11 sub-row) | AE69: 2026-10-20 | AF69: FND-0026 (findings/SUM-0028); EXT-0203, EXT-0204; evidence/literature-20261019/pages/INDEX.md (MCPVerse v2 pages 5, 7, 9) | AH69: No | AJ69: SRC-11 section D3 | AK69: SRC-06 S42 | AL69: S12
A70: C-S19/S43 | B70: Retrieve pool (32/65) and retrieve-mode judge behaviour | C70: PARTLY ANSWERED | D70: =IFERROR(INDEX(Lists!$B$2:$B$14,MATCH(C70,Lists!$A$2:$A$14,0)),"?") | E70: =IF(COUNTIFS(Links!$B$2:$B$600,A70,Links!$E$2:$E$600,"Yes")>0,"REVISE","") | F70: =COUNTIFS(Links!$B$2:$B$600,A70,Links!$D$2:$D$600,"No",Links!$C$2:$C$600,"<>INFORMS") | G70: SOURCE-REREAD | H70: K14 Source & vendor verification | I70: G5 Housekeeping / no block | J70: Low | K70: 118 | L70: W2 Desk work (no model runs) | M70: S12 | N70: Authors / team | O70: You send the drafted ask (design/ledger/notes/AUTHOR-ASKS-DRAFT-20261020.md, section 1) and record the reply; until then it waits on the authors | P70: Yes - stored text, unread | Q70: Source check | R70: Sub-item | S70: C-S19 | T70: SRC-06 S43: the retrieve pool (32/65) and retrieve-mode judge behaviour are unknown. | U70: Retrieve mode (v2): the descriptions of all MCP servers are embedded (text-embedding-3-large) and stored; each tested model first writes the descriptions of the servers it needs, these are embedded, and 'the top-5 most relevant servers are selected using cosine similarity' and mounted (EXT-0180, EXT-0153). So the retrieve pool is all MCP servers (65 in Max-Scale) and 5 are mounted; the '32/65' in the ledger wording are the Standard (32 MCPs, 220+ tools, ~44k tokens) and Max-Scale (65 MCPs, 550+ tools, ~140k tokens) mode sizes (EXT-0151). Table 4 (Oracle / Standard / Retrieve SR) quoted; Claude-4-Sonnet and Qwen3 Oracle/Standard cells are identical (44.8/53.2) with different Retrieve cells; the GPT-5 asterisk (23.4*) is unexplained (EXT-0153). The retrieve-mode judge is not stated in the ranges read. Batch 9: v2 section 4.3 (page 9 image): text-embedding-3-large embeds the descriptions of all MCP servers; the tested model first writes the descriptions of the servers it needs, these are embedded, and the top-5 servers by cosine similarity are mounted; pool size and tool count or tokens per run are not stated there. The judge prompt (Table 6) takes only question, reference answer and model output, so by construction the judge does not see retrieval. NOT FOUND in these texts: which judge scored Table 4 and any statement about judge behaviour in retrieve mode. Table 4 (page 9 image): GPT-5 Retrieve is 45.0 against Standard 23.4*, which contradicts the sentence that retrieve-mode performance is 'consistently and significantly lower than in oracle mode and standard mode'. | V70: Authors / raw logs / reproduction. | AB70: SOURCE+AUTHOR | AC70: n/a (sub-item) | AD70: NEW (SRC-11 sub-row) | AE70: 2026-10-20 | AF70: FND-0026 (findings/SUM-0028); EXT-0203, EXT-0204; evidence/literature-20261019/pages/INDEX.md (MCPVerse v2 pages 5, 7, 9) | AH70: No | AJ70: SRC-11 section D3 | AK70: SRC-06 S43 | AL70: S12
A71: C-S19/S44 | B71: Does the released repo reproduce the paper numbers? | C71: DEFERRED | D71: =IFERROR(INDEX(Lists!$B$2:$B$14,MATCH(C71,Lists!$A$2:$A$14,0)),"?") | E71: =IF(COUNTIFS(Links!$B$2:$B$600,A71,Links!$E$2:$E$600,"Yes")>0,"REVISE","") | F71: =COUNTIFS(Links!$B$2:$B$600,A71,Links!$D$2:$D$600,"No",Links!$C$2:$C$600,"<>INFORMS") | G71: TEST-PILOT | H71: K14 Source & vendor verification | I71: G5 Housekeeping / no block | J71: Low | K71: 119 | L71: W2 Desk work (no model runs) | M71: S12 | N71: Authors / team | O71: none until the trigger fires | P71: No | Q71: Source check | R71: Sub-item | S71: C-S19 | T71: SRC-06 S44: whether the released repository reproduces the paper's numbers is unknown (no reproduction in reviewed material). | U71: No reproduction anywhere in the repo. 2026-10-21 (AUTH-019): reproducing the MCPVerse authors' numbers is not needed for the policy: the paper's numbers are cited as the authors' claims only and nothing is built on them (FND-0037 (findings/SUM-0039)). | V71: Authors / raw logs / reproduction. | AB71: DATA | AC71: n/a (sub-item) | AD71: NEW (SRC-11 sub-row) | AE71: 2026-10-21 | AF71: FND-0037 (findings/SUM-0039) | AG71: A design choice is about to rest on MCPVerse numbers | AH71: No | AJ71: SRC-11 section D3 | AK71: SRC-06 S44 | AL71: S12
A72: C-S19/S46 | B72: Native vs prompt calling: frozen report's 'workaround' wording | C72: OPEN | D72: =IFERROR(INDEX(Lists!$B$2:$B$14,MATCH(C72,Lists!$A$2:$A$14,0)),"?") | E72: =IF(COUNTIFS(Links!$B$2:$B$600,A72,Links!$E$2:$E$600,"Yes")>0,"REVISE","") | F72: =COUNTIFS(Links!$B$2:$B$600,A72,Links!$D$2:$D$600,"No",Links!$C$2:$C$600,"<>INFORMS") | G72: RECORDS-AT-HAND | H72: K14 Source & vendor verification | I72: G5 Housekeeping / no block | J72: Low | K72: 121 | L72: W2 Desk work (no model runs) | M72: S12 | N72: Authors / team | O72: Lead drafts the fix; you approve | P72: No | Q72: Source check | R72: Sub-item | S72: C-S19 | T72: SRC-06 S46: native versus prompt calling is a different treatment; the frozen report's 'workaround' wording needs correcting. | U72: Outside the repo. | V72: Authors / raw logs / reproduction. | AB72: RECORD | AC72: n/a (sub-item) | AD72: NEW (SRC-11 sub-row) | AE72: 2026-10-19 | AF72: Phase 1 report outside repo | AH72: No | AJ72: SRC-11 section D3 | AK72: SRC-06 S46 | AL72: S12
A73: AS-09 | B73: Supervisor assertion A9: The partial-information idea comes from another party's documentation | C73: PARTLY ANSWERED | D73: =IFERROR(INDEX(Lists!$B$2:$B$14,MATCH(C73,Lists!$A$2:$A$14,0)),"?") | E73: =IF(COUNTIFS(Links!$B$2:$B$600,A73,Links!$E$2:$E$600,"Yes")>0,"REVISE","") | F73: =COUNTIFS(Links!$B$2:$B$600,A73,Links!$D$2:$D$600,"No",Links!$C$2:$C$600,"<>INFORMS") | G73: LITERATURE-DIRECTED | H73: K14 Source & vendor verification | I73: G5 Housekeeping / no block | J73: Low | K73: 126 | L73: W2 Desk work (no model runs) | M73: S13 | N73: Lead / team | O73: Q-J28 (source the supervisor meant) | P73: No | Q73: Claim to test | R73: Item | T73: REQ-A1 A9: The partial-information idea comes from another party's documentation. Source unnamed; prior art to locate. | U73: Recorded as the supervisor's position, to test, not to assume. Batch 12 (2026-10-20): twenty candidates of five kinds were found in the stored sources (the steward did not say which one the supervisor meant, and which one cannot be determined from the repo because the transcript line is not in it): definitions hidden with a search tool visible (Anthropic defer_loading, published 24 Nov 2025; LangChain; Spring AI blog 2025-12-11; AgentCore; AgentPatterns); a facade description visible with children revealed on invocation (Embabel UnfoldingTool; Slite's tool tree); names plus short descriptions visible (AIMultiple, names plus 60-character descriptions; Claude Code issue 59650, opened 16 May 2026, asks for a name-only form); a listing step separate from a schema step (Speakeasy list_tools vs describe_tools, 13 Nov 2025; Dynamic ReAct get_tool_info; SING get_tool_schema; MCP-Zero server summaries); a category statement in the system prompt (Anthropic docs advice, EXT-0131). Which one a third party would call 'partial information' is for the supervisor to say (Q-J28). 2026-10-21 (AUTH-018): 'what I have said this partial thingy this is also ... cames out from someone else. I didn't invent it ... I just read their doc' (INT-T-004 E593) and 'if you look at executor they are doing the same thing that I already mentioned ... giving you partial information' (E605-E607): the documentation is not named; Executor is the project he points to. | V5 2026-10-22: vendors ship partial-information tiers: an OpenAI deferred function shows name and description, schema deferred; a namespace shows only its own description | V73: Source unnamed; prior art to locate. | Y73: Q-J28 | AB73: SOURCE | AC73: n/a (REGISTER E) | AD73: NEW (repo sweep) | AE73: 2026-10-22 | AF73: L/v5-openai-tool-search-20261022.md:22 | AH73: No | AJ73: repo: REGISTER section E / EXT-0004 | AK73: REQ-A1 A9 | AL73: S11
A74: C-E02/UNREADLEADS | B74: Reference lists (KAIST, cache study), agent-memory survey 2602.06052 not read | C74: DEFERRED | D74: =IFERROR(INDEX(Lists!$B$2:$B$14,MATCH(C74,Lists!$A$2:$A$14,0)),"?") | E74: =IF(COUNTIFS(Links!$B$2:$B$600,A74,Links!$E$2:$E$600,"Yes")>0,"REVISE","") | F74: =COUNTIFS(Links!$B$2:$B$600,A74,Links!$D$2:$D$600,"No",Links!$C$2:$C$600,"<>INFORMS") | G74: LITERATURE-DIRECTED | H74: K14 Source & vendor verification | I74: G4 Before claims | J74: Normal | K74: 127 | L74: W2 Desk work (no model runs) | M74: S13 | N74: Lead + fresh reviewer | O74: none until the trigger fires | P74: Partly | Q74: Record fix | R74: Sub-item | S74: C-E02 | T74: v4-05 section 5 'not done': reference lists of KAIST and the cache study and the agent-memory survey (arXiv 2602.06052) were not read. | U74: Recorded as open in its source; not examined further in this review. 2026-10-20: the agent-memory survey (arXiv 2602.06052, 'A Survey of Agent Memory in the Second Half', TMLR 07/2026) was fetched and read in part by a steward (about 60% of its lines; FND-0032): it is a secondary source that describes other papers and reports no experiment of its own. What it says that bears on the supervisor's memory point: three axes (substrate, cognitive mechanism, subject user-centric vs agent-centric); tool-related memory sits under procedural and agent-centric memory; the two subjects are 'conceptual orientations rather than mutually exclusive categories' and a coding assistant may keep both (lines 1563-1568), while 'current benchmarks rarely require both simultaneously'; cross-session retention is a stated need (lines 510-512) with benchmark names and proposed metrics ('dependency distance', 'resume after long gaps', lines 3382-3387) but no measured result for an hours or days gap and no cold-start treatment found; costs of memory are qualitative ('thousands of tokens', latency; the survey says benchmarks should quantify token, storage and latency trade-offs and do not yet, lines 3992-3994); papers named for tool-related memory (ToolMem 2510.06664, MemTool 2507.21428, Memp 2508.06433, ReasoningBank 2509.25140, SkillsBench 2602.12670) with qualitative effects only and no library sizes; 'cache' in the survey means model-internal KV state discarded across sessions, not prompt caching or a stable prefix (prefix and cache layout: not found in this text); customer support, cloud agents and pre-loading before the first request: not found. It does not settle the memory scope question (Q-J05). The reference lists of KAIST and the cache study were not read and are deferred. | V74: Read or marked out of scope. | Y74: Q-U21 | AB74: RECORD+SOURCE | AC74: n/a (sub-item) | AD74: NEW (repo sweep) | AE74: 2026-10-20 | AF74: FND-0032 (findings/SUM-0034); evidence/literature-20261019/pdf-memory-survey-2602.06052.txt | AG74: A claim depends on a paper cited in the KAIST or cache-study reference lists, or on a survey section not read (lines 560-1015, 1777-2340, 2500-3005, 3065-3370) | AH74: No (AUTH-016 covers web fetches for this item) | AJ74: repo: v4-03 section 6 / RV-0005 / RV-0007 | AL74: S13
A75: N-19 | B75: Stale counts and safeguard text in records | C75: PARTLY ANSWERED | D75: =IFERROR(INDEX(Lists!$B$2:$B$14,MATCH(C75,Lists!$A$2:$A$14,0)),"?") | E75: =IF(COUNTIFS(Links!$B$2:$B$600,A75,Links!$E$2:$E$600,"Yes")>0,"REVISE","") | F75: =COUNTIFS(Links!$B$2:$B$600,A75,Links!$D$2:$D$600,"No",Links!$C$2:$C$600,"<>INFORMS") | G75: RECORDS-AT-HAND | H75: K17 Record repair & procedure error | I75: G5 Housekeeping / no block | J75: Low | K75: 130 | L75: W2 Desk work (no model runs) | M75: S15 | N75: Lead (STATE, v4-05); you (pinned files) | O75: You decide whether the proposed wording for CLAUDE.md and SAFEGUARDS rows 5 and 17 may be applied | P75: Answered (see basis) | Q75: Record fix | R75: Item | T75: STATE says AUTH-013 had 23 searches / 32 sources; v4-05 section 5 says 18 / 28 while its header says 27 / 37 (manifest has 37 rows); SAFEGUARDS rows 5 and 17 and CLAUDE.md predate AUTH-012/014/015. | U75: Pinned files (CLAUDE.md, SAFEGUARDS) need your review before edits. Batch 6: the counts reconcile as cumulative snapshots at different times: 8 searches and 12 stored fetches under AUTH-011 (thread T-20261019-97 summary); 15 more searches and 20 more sources in rounds 3-4 (23 and 32 in all, T-20261019-98 summary); 27 searches and 37 stored sources in the v4-05 header, which matches the 37 manifest rows before AUTH-016 (manifest timeline: 12 + 23 + 2 rows on 2026-10-19; the 'auth' tags in the manifest are unreliable because the fetch helper hard-codes AUTH-013); the 18 / 28 in v4-05 section 5 is an earlier round-3 snapshot. STATE said 'AUTH-013: 23 searches and 32 stored sources', which was the cumulative figure at round 4, not AUTH-013 alone; ops/STATE.md (lead-owned) is corrected. The brief (01 line 77: 8 searches and 12 fetches) and v4-05 are earlier packages and are not rewritten: this row is the successor note. The final 4 searches and 5 sources behind 27 / 37 are recorded only in the v4-05 header (no thread summary states them). Proposed wording for CLAUDE.md and SAFEGUARDS rows 5 and 17 (which predate AUTH-012/014/015/016) is drafted in design/ledger/notes/N-19-proposed-text-for-pinned-files.md and applied nowhere. 2026-10-20: the second part of Q-U11 (updating the stale safeguard text for review) was not answered; the proposal stays unapplied. Batch 14 (2026-10-20): the counts are now settled by arithmetic: the literature README gives 27 searches (3+5+10+5+4) and 37 sources (12+16+4+5), which matches the header of 05 (reviewer RV-0015); 18 / 28 is the end-of-round-3 figure and the 23 / 32 in STATE (now corrected) the round-4 figure. | V75: Counts and safeguard text updated. | Y75: Q-U11 | AB75: RECORD | AC75: n/a (new) | AD75: NEW (repo sweep) | AE75: 2026-10-20 | AF75: reviews/RV-0015.md; evidence/literature-20261019/README.md | AH75: No | AJ75: review 19 Oct section 6.6 | AL75: S03
A76: C-R01/C03 | B76: R6 timing, query source, recovery assumptions | C76: PARTLY ANSWERED | D76: =IFERROR(INDEX(Lists!$B$2:$B$14,MATCH(C76,Lists!$A$2:$A$14,0)),"?") | E76: =IF(COUNTIFS(Links!$B$2:$B$600,A76,Links!$E$2:$E$600,"Yes")>0,"REVISE","") | F76: =COUNTIFS(Links!$B$2:$B$600,A76,Links!$D$2:$D$600,"No",Links!$C$2:$C$600,"<>INFORMS") | G76: RECORDS-AT-HAND | H76: K17 Record repair & procedure error | I76: G3 Before confirmatory study | J76: Normal | K76: 133 | L76: W2 Desk work (no model runs) | M76: S15 | N76: Lead + fresh reviewer | O76: You approve RA14 and choose among the R1TRIG options | P76: Partly | Q76: Scientific unknown | R76: Sub-item | S76: C-R01 | T76: SRC-06 C03: R6 (trigger) timing, scripted-query provenance, recovery assumptions. | U76: Trigger placed after tool results and at finish; R6 itself has no supporting evidence. Batch 15 (2026-10-20): RV-0008 (CH-0041, APPLIED-PARTLY): the trigger is placed after tool results and when the agent proposes to finish (v4 02 line 42), the provenance of any scripted query is an arm-specification item (v3 02 line 71), RA12 and RA13 were added; missing: the assumption that the provider permits changing the visible tool set between turns (drafted as RA14 in design/package-v4/06-corrections-proposed.md section 4) and what the trigger does after the budget says no (C-R01/R1TRIG). | V76: Independent re-check and a dated fix. | AB76: RECORD+DATA | AC76: n/a (sub-item) | AD76: NEW (SRC-11 sub-row) | AE76: 2026-10-20 | AF76: reviews/RV-0008.md (fresh reviewer, same model family, read the current text); design/package-v4/06-corrections-proposed.md | AH76: No | AJ76: SRC-11 section D4 | AK76: SRC-06 C03, CH-0041 | AL76: S09
A77: C-R01/C04 | B77: Outcome-split accounting, provider usage, task shedding | C77: PARTLY ANSWERED | D77: =IFERROR(INDEX(Lists!$B$2:$B$14,MATCH(C77,Lists!$A$2:$A$14,0)),"?") | E77: =IF(COUNTIFS(Links!$B$2:$B$600,A77,Links!$E$2:$E$600,"Yes")>0,"REVISE","") | F77: =COUNTIFS(Links!$B$2:$B$600,A77,Links!$D$2:$D$600,"No",Links!$C$2:$C$600,"<>INFORMS") | G77: TEST-PILOT | H77: K17 Record repair & procedure error | I77: G3 Before confirmatory study | J77: Normal | K77: 134 | L77: W2 Desk work (no model runs) | M77: S15 | N77: Lead + fresh reviewer | O77: Test only the remainder, in the proof-of-concept loop | P77: Partly | Q77: Scientific unknown | R77: Sub-item | S77: C-R01 | T77: SRC-06 C04: outcome-split accounting, whether provider usage counts deferred definitions, and expensive-task shedding. | U77: Stratum guard added; tokens-by-outcome split belongs to E1. 2026-10-21 (AUTH-019): PARTLY ESTABLISHED under the human's principle: the providers' documented mechanism and prices are adopted without re-test; what stays to test is only the remainder stated in this row's entry in FND-0037 (findings/SUM-0039) (our policy's effect, our trajectories, or a quantity no source measures). | V77: Independent re-check and a dated fix. | AB77: RECORD+DATA | AC77: n/a (sub-item) | AD77: NEW (SRC-11 sub-row) | AE77: 2026-10-21 | AF77: FND-0037 (findings/SUM-0039) | AH77: No | AJ77: SRC-11 section D4 | AK77: SRC-06 C04, CH-0042 | AL77: S09
A78: C-R01/C06 | B78: No-miss searches; conditional I_disc / tau | C78: PARTLY ANSWERED | D78: =IFERROR(INDEX(Lists!$B$2:$B$14,MATCH(C78,Lists!$A$2:$A$14,0)),"?") | E78: =IF(COUNTIFS(Links!$B$2:$B$600,A78,Links!$E$2:$E$600,"Yes")>0,"REVISE","") | F78: =COUNTIFS(Links!$B$2:$B$600,A78,Links!$D$2:$D$600,"No",Links!$C$2:$C$600,"<>INFORMS") | G78: RECORDS-AT-HAND | H78: K17 Record repair & procedure error | I78: G3 Before confirmatory study | J78: Normal | K78: 136 | L78: W2 Desk work (no model runs) | M78: S15 | N78: Lead + fresh reviewer | O78: Specify with C-S08/EVENTS once the pilot design is chosen | P78: Partly | Q78: Scientific unknown | R78: Sub-item | S78: C-R01 | T78: SRC-06 C06: searches in trajectories that need no deferred tool; I_disc and tau must be conditional on the needed tool. | U78: Counted events defined in v4-05; the conditional terms are not specified. Batch 15 (2026-10-20): carried by C-S08/EVENTS: the counted events are defined in v4 05 (search or request call; domain-tool call; direct answer), the conditional terms for I_disc and tau (conditional on the needed tool being hidden) are a specification item on that row. | V78: Independent re-check and a dated fix. | AB78: RECORD+DATA | AC78: n/a (sub-item) | AD78: NEW (SRC-11 sub-row) | AE78: 2026-10-20 | AF78: v4 05 line 83; row C-S08/EVENTS | AH78: No | AJ78: SRC-11 section D4 | AK78: SRC-06 C06 | AL78: S09
A79: C-R01 | B79: v3 challenge residuals: D4 arm/multiplicity, substitute reference, trigger timing, outcome-split accounting... | C79: PARTLY ANSWERED | D79: =IFERROR(INDEX(Lists!$B$2:$B$14,MATCH(C79,Lists!$A$2:$A$14,0)),"?") | E79: =IF(COUNTIFS(Links!$B$2:$B$600,A79,Links!$E$2:$E$600,"Yes")>0,"REVISE","") | F79: =COUNTIFS(Links!$B$2:$B$600,A79,Links!$D$2:$D$600,"No",Links!$C$2:$C$600,"<>INFORMS") | G79: RECORDS-AT-HAND | H79: K17 Record repair & procedure error | I79: G3 Before confirmatory study | J79: Normal | K79: 137 | L79: W2 Desk work (no model runs) | M79: S15 | N79: Lead + fresh reviewer | O79: Lead drafts the fix; you approve | P79: Partly | Q79: Record fix | R79: Item | T79: v3 challenge residuals: D4 arm/multiplicity, substitute reference, trigger timing, outcome-split accounting, fair baseline, no-miss searches. | U79: v4 corrected the text; 11 of 13 v4 challenges closed; the last edits were not re-verified by the challenger; figures never rendered. | V79: Last edits re-checked independently; figures rendered; data residuals tied to their tests. | W79: C-D08 | X79: C-S14 | Z79: DESK-ANALYSIS, TEST-PILOT | AA79: K5 Evaluation contract | AB79: DATA+DEC+RECORD | AC79: PARTLY ANSWERED - OPEN | AD79: RE-CHARACTERISED | AE79: 2026-10-19 | AF79: v4-03 sections 5-6; CH-0045..0057; RV-0005 | AH79: No | AJ79: SRC-11 canonical | AK79: SRC-06 C01-C06, v4-03 residuals | AL79: S09
A80: C-R01/FIG2 | B80: Figure 2 has no path to the outcome for a Regime B run with no declared margin | C80: PARTLY ANSWERED | D80: =IFERROR(INDEX(Lists!$B$2:$B$14,MATCH(C80,Lists!$A$2:$A$14,0)),"?") | E80: =IF(COUNTIFS(Links!$B$2:$B$600,A80,Links!$E$2:$E$600,"Yes")>0,"REVISE","") | F80: =COUNTIFS(Links!$B$2:$B$600,A80,Links!$D$2:$D$600,"No",Links!$C$2:$C$600,"<>INFORMS") | G80: RECORDS-AT-HAND | H80: K17 Record repair & procedure error | I80: G1 Before any implementation | J80: High | K80: 138 | L80: W2 Desk work (no model runs) | M80: S15 | N80: Lead drafts, you approve | O80: You render the block in VS Code and approve or correct it; your approval (in your words) closes this row | P80: Answered (see basis) | Q80: Record fix | R80: Sub-item | S80: C-R01/V4RES | T80: RV-0009 F-2.1 and F-2.2 (lead re-read the figure: confirmed): in v4 02 Figure 2, node O ('a configuration, a frontier, or no arm established') has one incoming edge, from S6; S5B reaches S6 only 'if a margin or budget was declared', yet 02 line 73 says no margin is the default for Regime B and 'a frontier' is a named outcome; S5A to S6 is unconditional although F may be empty or option (b) may name no winner. The defect was created by the R6 fix and is recorded nowhere. Also: Figure 2 has no branch for a failed test-split confirmation (S6 goes straight to O), although v3 02 line 63 (b) says the procedure reports OUT2 for that setting. | U80: Confirmed by the lead in design/package-v4/02-policy-graph-and-protocol.md lines 66-70 (edges S5A --> S6, S5B -->|only if a margin or budget was declared| S6, S6 --> O). Not edited: package v4 is the meeting material; a figure change needs your approval. Batch 11 (2026-10-20): drafted in design/package-v4/06-corrections-proposed.md (proposed, nothing applied; files 01-05 are not edited) and checked by fresh reviewers (reviews/RV-0011.md, RV-0012.md, RV-0013.md (fresh reviewers, same model family, text checks)). Section 1 gives a replacement Figure 2 block: S5A has three exits (arm chosen; no feasible arm; option (b) set reported with no winner), S5B has three (confirm; declared but no arm meets it; frontier), S6 has two (confirmed; failed confirmation = OUT2 with no fallback), O gains the outcome 'a reported set with no single winner'. RV-0011 found every path from the input node reaches O, each outcome has an incoming edge and no syntax defect by reading; it flagged four open points (new row C-R01/FIG2-POINTS). | V80: Figure 2 (and the brief's copy, if any) has a path to O for every regime and outcome, re-read by a reviewer. | AB80: RECORD+DEC | AC80: n/a (sub-item) | AD80: NEW (repo sweep) | AE80: 2026-10-20 | AF80: design/package-v4/06-corrections-proposed.md section 1; reviews/RV-0011.md | AH80: No (editing needs the human's approval) | AJ80: RV-0009 (Reviewer 6b1), confirmed by the lead | AL80: S15
A81: C-R01/FIG2-POINTS | B81: Four design points the Figure 2 check left unresolved: expose-all in the feasible set, option (b), Regime B decision rule, the regime-size loop | C81: PARTLY ANSWERED | D81: =IFERROR(INDEX(Lists!$B$2:$B$14,MATCH(C81,Lists!$A$2:$A$14,0)),"?") | E81: =IF(COUNTIFS(Links!$B$2:$B$600,A81,Links!$E$2:$E$600,"Yes")>0,"REVISE","") | F81: =COUNTIFS(Links!$B$2:$B$600,A81,Links!$D$2:$D$600,"No",Links!$C$2:$C$600,"<>INFORMS") | G81: USER-DECISION | H81: K17 Record repair & procedure error | I81: G1 Before any implementation | J81: Normal | K81: 139 | L81: W2 Desk work (no model runs) | M81: S15 | N81: You (or Joaa) | O81: Settle (a), (b), (d) when the end-to-end study is designed | P81: Partly | Q81: Decision | R81: Sub-item | S81: C-R01/FIG2 | T81: RV-0011 (fresh reviewer) on the replacement Figure 2: (a) whether expose-all is in the feasible set by construction in Regime A: CH-0040 point 5 says the reference is an arm and always feasible against itself, so 'no feasible arm' could not occur in Regime A, while 02 line 102 says an empty F means 'no arm shown noninferior'; (b) under preference option (b) no arm is chosen, so S6 is never entered and a 'configuration' is never produced in Regime A without an epsilon (follows from 02 lines 104-105, not written there); (c) 02 gives a decision rule only for Regime A (section 6 is headed 'Decision rule S5A (Regime A)'), so what Regime B does with a declared margin or budget is unwritten; (d) the loop over catalogue sizes (02 line 73) is not drawn, so the figure reads as a single run. | U81: Found by a fresh reviewer on 2026-10-20; the sources do not settle (a) to (c); (d) is unchanged from the earlier figure. The drafted replacement draws exits the sources support and says in its text that these four points are open. 2026-10-21 (AUTH-019, the human's decisions): point (c) is decided: no margin or budget (line 16), so in Regime B the frontier is reported and a configuration is chosen with stated reasons; points (a), (b) and (d) remain. | V81: Each point decided in the human's or the supervisor's words, or recorded as open. | AB81: RECORD+DEC | AC81: n/a (sub-item) | AD81: NEW (repo sweep) | AE81: 2026-10-21 | AF81: INT-T-005 (requirements/intake/2026-10-21-user-decisions-after-meetings.md) | AH81: No | AJ81: RV-0011 (batch 11) | AL81: S15
A82: C-R01/R1TRIG | B82: A trigger can re-fire on every finish proposal when the budget is exhausted | C82: PARTLY ANSWERED | D82: =IFERROR(INDEX(Lists!$B$2:$B$14,MATCH(C82,Lists!$A$2:$A$14,0)),"?") | E82: =IF(COUNTIFS(Links!$B$2:$B$600,A82,Links!$E$2:$E$600,"Yes")>0,"REVISE","") | F82: =COUNTIFS(Links!$B$2:$B$600,A82,Links!$D$2:$D$600,"No",Links!$C$2:$C$600,"<>INFORMS") | G82: RECORDS-AT-HAND | H82: K17 Record repair & procedure error | I82: G2 Before the affected pilot/arm | J82: Normal | K82: 140 | L82: W2 Desk work (no model runs) | M82: S15 | N82: Lead drafts, you approve | O82: You or Joaa choose (a), (b) or (c) | P82: Answered (see basis) | Q82: Record fix | R82: Sub-item | S82: C-R01/V4RES | T82: RV-0009 R1 residual: P3/P3f 'yes' still goes to B and B 'no' still returns 'unavailable' to A (02 lines 24, 28, 33), so a trigger can fire on every finish proposal until the call limit; neither 02 nor 03 says what happens when the budget is exhausted. | U82: Reported by one reviewer from a text read; the interface rule that now exists is in 02 line 42. Batch 11 (2026-10-20): drafted in design/package-v4/06-corrections-proposed.md (proposed, nothing applied; files 01-05 are not edited) and checked by fresh reviewers (reviews/RV-0011.md, RV-0012.md, RV-0013.md (fresh reviewers, same model family, text checks)). Section 2 states the gap and three options without choosing: (a) the trigger fires at most once per task at each placement; (b) the trigger shares the discovery budget; (c) leave as drawn and count the wasted classifier calls. RV-0012 confirmed the loop exists in Figure 1 and added that 02 line 41 bounds it by the call limit except in vehicles whose budget counts only tool calls (EXT-0084). | V82: The protocol states what the trigger does after the call limit is reached. | AB82: RECORD+DEC | AC82: n/a (sub-item) | AD82: NEW (repo sweep) | AE82: 2026-10-20 | AF82: design/package-v4/06-corrections-proposed.md section 2; reviews/RV-0012.md | AH82: No (editing needs the human's approval) | AJ82: RV-0009 (Reviewer 6b1) | AL82: S15
A83: C-R01/RENDER | B83: Mermaid figures were never rendered | C83: PARTLY ANSWERED | D83: =IFERROR(INDEX(Lists!$B$2:$B$14,MATCH(C83,Lists!$A$2:$A$14,0)),"?") | E83: =IF(COUNTIFS(Links!$B$2:$B$600,A83,Links!$E$2:$E$600,"Yes")>0,"REVISE","") | F83: =COUNTIFS(Links!$B$2:$B$600,A83,Links!$D$2:$D$600,"No",Links!$C$2:$C$600,"<>INFORMS") | G83: RECORDS-AT-HAND | H83: K17 Record repair & procedure error | I83: G4 Before claims | J83: Normal | K83: 141 | L83: W2 Desk work (no model runs) | M83: S15 | N83: You (render in VS Code); lead (concept check) | O83: Lead fixes the concept defects in the successor note; you render the figures in VS Code and report anything that looks wrong | P83: No | Q83: Record fix | R83: Sub-item | S83: C-R01 | T83: No renderer was installed; Figure 1 and 2 syntax is unverified. | U83: Batch 6: a text reading of the Mermaid blocks in v4 02 (Figures 1 and 2) and the brief's copy of Figure 1 found no certain syntax defect (node ids, bracket and quote closure, edge forms, forward references, 'End' capitalised, no subgraph/style/class lines); low-risk points: nodes A, B and E are used before their labelled definitions, '<br/>' inside quoted labels, long labels (RV-0009). This is a reading, not a render; no renderer exists here and installs are not allowed, so rendering stays unverified. The drawings' semantic gaps are tracked in C-R01/FIG2. 2026-10-20: the human replied ("for mermaids rendring its okay i can render them with my vscode it has the extention ur job is to make sure it is showing the concept correctly"), so rendering is the human's check in VS Code and the limitation is not accepted as such. The lead's job under this row is that the figures show the concept correctly: the text reading found no certain syntax defect, and the concept defects found are in C-R01/FIG2 (no path to the outcome for a Regime B run with no declared margin; no failed-confirmation branch) and C-R01/R1TRIG; they are to be fixed in the successor note and re-read before the human renders the figures. | V83: Checked and corrected or labelled unverifiable: labelled unverifiable; your acceptance pending. | AB83: RECORD+SOURCE | AC83: n/a (sub-item) | AD83: NEW (repo sweep) | AE83: 2026-10-20 | AF83: chat message of 2026-10-20; RV-0009 | AH83: No | AI83: Rendering unverified; to be accepted as a stated limitation or checked by the human in any Mermaid viewer. | AJ83: repo: v4-03 section 6 / RV-0005 / RV-0007 | AL83: S15
